Workbook
Name Catalogo_Codigos: Catalogo_Detracciones!$A$4:$A$15
Name Catalogo_Etiquetas: Catalogo_Detracciones!$C$4:$C$15
Name Catalogo_Tasas: Catalogo_Detracciones!$D$4:$D$15
Name Catalogo_Umbrales: Catalogo_Detracciones!$E$4:$E$15
Name Feriados: Detracciones_Control!$P$4:$P$60
Name TC_Fechas: TC_Diario!$A$4:$A$1003
Name TC_Venta_Rango: TC_Diario!$C$4:$C$1003

Sheet Instrucciones
A1: Libro Diario — Braidy Wonders SAC
A2: Plantilla de registro de facturas de compra y venta, con clasificación automática de detracción (SPOT) y generación automática de asientos PCGE.
A4: Cómo está armado este archivo
A5: • Registro_Compras: una fila por factura de proveedor recibida. Al elegir el "Concepto" (según el catálogo de detracción), el archivo calcula solas la tasa, si aplica detracción, el monto a depositar y el neto a pagar.
A6: • Registro_Ventas: una fila por comprobante emitido a un cliente. El caso normal es sin detracción (Braidy Wonders casi siempre es el adquiriente, no el prestador, del servicio sujeto a SPOT) — la columna "¿Sujeto a detracción emitida?" queda en "NO" salvo que el servicio que facturas sea uno de los del catálogo (ej. transporte de personas).
A7: • Catalogo_Detracciones: tabla de referencia (Anexo 3 + transporte de carga) de la que se alimentan los menús desplegables y las fórmulas de Registro_Compras/Registro_Ventas. No editar las columnas de tasa/umbral sin confirmar el cambio normativo primero.
A8: • Libro_Diario: se genera solo, a partir de Registro_Compras y Registro_Ventas — no se edita a mano. Cada factura de compra con detracción genera 4 asientos (provisión del gasto, destino del gasto, depósito de la detracción, pago del neto); una compra sin detracción genera 3 (se salta el depósito). Cada venta genera el asiento de devengo y, si marcas "¿Cobrado?" = SI, el asiento de cobranza.
A10: Qué llenar tú (celdas en azul / con relleno amarillo)
A11: En Registro_Compras y Registro_Ventas: todo excepto las columnas de fórmula (tienen fondo blanco normal, texto negro). Las columnas de fórmula no se tocan — se recalculan solas.
A12: La fila 4 de Registro_Compras y de Registro_Ventas es un EJEMPLO (fondo verde claro) tomado de la guía de detracciones — bórrala o sobrescríbela con tu primera factura real; ya está incluida en el conteo del Libro_Diario para que veas el resultado completo de un caso real antes de cargar los tuyos.
A14: Alcance y limitaciones de esta plantilla
A15: • Cubre el lado de compras con y sin detracción (fuente: guía de detracciones consolidada) y el lado de ventas en su forma estándar — el asiento de venta (Debe 12 / Haber 70 y 40111) es la mecánica contable general del PCGE, no vino desglosada con ejemplo numérico en las fuentes que subiste; revísala con tu contador antes de depender de ella para un cierre.
... A21: Ver hoja Plan_Cuentas — indica cuáles cuentas vienen confirmadas en las fuentes que subiste y cuáles son la aplicación estándar del PCGE para el lado de ventas (12, 70) que no estaba desarrollada en las fuentes.

Sheet Catalogo_Detracciones
A1: Catálogo de servicios sujetos a detracción (Anexo 3 SUNAT) — Braidy Wonders SAC
A2: Fuente: guía de detracciones consolidada (20.08.2026). No editar tasas/umbrales sin confirmar la norma vigente.
A3: Código SUNAT | B3: Servicio / Bien | C3: Etiqueta (para menú desplegable) | D3: Tasa | E3: Umbral (moneda de la op.) | F3: Rubro típico en Braidy Wonders
A4: 012 | B4: Intermediación laboral y tercerización | C4: 012 - Intermediación laboral y tercerización | D4: 0.12 | E4: 700 | F4: Limpieza/lavandería tercerizada (alojamiento)
A5: 019 | B5: Arrendamiento de bienes muebles e inmuebles | C5: 019 - Arrendamiento de bienes muebles e inmuebles | D5: 0.1 | E5: 700 | F5: Alquiler de locales, equipos
A6: 020 | B6: Mantenimiento y reparación de bienes muebles | C6: 020 - Mantenimiento y reparación de bienes muebles | D6: 0.12 | E6: 700 | F6: Mantenimiento de equipos (alojamiento)
A7: 021 | B7: Movimiento de carga | C7: 021 - Movimiento de carga | D7: 0.1 | E7: 700 | F7: Logística de equipaje/carga
A8: 022 | B8: Otros servicios empresariales (legal, contable, consultoría, publicidad) | C8: 022 - Otros servicios empresariales (legal, contable, consultoría, publicidad) | D8: 0.12 | E8: 700 | F8: Asesoría, consultoría, publicidad
A9: 024 | B9: Comisión mercantil | C9: 024 - Comisión mercantil | D9: 0.1 | E9: 700 | F9: Comisiones de sub-agentes / intermediarios turísticos
A10: 025 | B10: Fabricación de bienes por encargo | C10: 025 - Fabricacion de bienes por encargo | D10: 0.1 | E10: 700 | F10: Poco frecuente en el giro de Braidy Wonders
A11: 026 | B11: Servicio de transporte de personas | C11: 026 - Servicio de transporte de personas | D11: 0.1 | E11: 700 | F11: Transporte terrestre de pasajeros (paquetes turísticos)
A12: 027 | B12: Transporte de bienes por vía terrestre (carga) | C12: 027 - Transporte de bienes por vía terrestre (carga) | D12: 0.04 | E12: 400 | F12: Transporte de carga/equipaje
A13: 030 | B13: Contratos de construcción | C13: 030 - Contratos de construcción | D13: 0.04 | E13: 700 | F13: Remodelación/reparación inmobiliaria (alojamiento)
A14: 037 | B14: Demás servicios gravados con IGV (residual) | C14: 037 - Demás servicios gravados con IGV (residual) | D14: 0.12 | E14: 700 | F14: Hoteles/alojamiento local, salud gravada con IGV, servicios sin categoría propia
A15: N/A | B15: No sujeto a detracción (aéreo regular, salud exonerada de IGV, importación de bienes, etc.) | C15: N/A - No sujeto a detracción (aéreo regular, salud exonerada de IGV, importación de bienes, etc.) | D15: 0 | E15: 999999999 | F15: Boletos aéreos, servicios médicos exonerados, importaciones (aplica percepción, no SPOT)

Sheet Registro_Compras
A1: Registro de Compras - Facturas de Proveedores
A2: Llena solo las columnas de ENTRADA. Las columnas (auto) y de calculo se resuelven solas y no se tocan. La columna C (N° Comprobante) es el disparador: si esta vacia, la fila no genera ningun asiento.
A3: N° | B3: Fecha Emisión | C3: N° Comprobante | D3: RUC Proveedor | E3: Proveedor | F3: Tipo Comprobante | G3: Código SPOT | H3: Concepto (auto) | I3: Moneda | J3: Valor Venta | K3: IGV | L3: Total Comprobante | M3: Cuenta de Gasto (63x) | N3: TC (auto) | O3: Total PEN | P3: % Detracción | Q3: Umbral S/ | R3: Sujeto a Detracción | S3: Detracción S/ (calculada) | T3: Detracción S/ (comprobante) | U3: Validación Detracción | V3: Retención 4ta (moneda fact.) | W3: Neto a Pagar (moneda fact.) | X3: Fecha Depósito Detracción | Y3: Fecha Pago Neto | Z3: N° Constancia SUNAT | AA3: Estado | AB3: Tipo Gasto
A4: 1 | B4: 46253 | C4: F001-00005653 | D4: 20307167442 | E4: COMISION DE PROMOCION DEL PERU PARA LA EXPORTACION Y EL TURISMO - PROMPERU | F4: FACTURA | G4: 037 | H4: =IF($G4="","",IFERROR(INDEX(Catalogo_Etiquetas,MATCH($G4,Catalogo_Codigos,0)),"CODIGO NO VALIDO")) | I4: PEN | J4: 5094.92 | K4: 917.08 | L4: =IF($C4="","",$J4+$K4) | M4: 637 | N4: =IF($C4="","",IF($I4="PEN",1,IFERROR(IF(_xlfn.XLOOKUP($B4,TC_Fechas,TC_Venta_Rango,"",-1)="","",_xlfn.XLOOKUP($B4,TC_Fechas,TC_Venta_Rango,"",-1)),""))) | O4: =IF(OR($C4="",$N4=""),"",ROUND($J4*$N4,2)+ROUND($K4*$N4,2)) | P4: =IF($G4="","",IFERROR(INDEX(Catalogo_Tasas,MATCH($G4,Catalogo_Codigos,0)),"")) | Q4: =IF($G4="","",IFERROR(INDEX(Catalogo_Umbrales,MATCH($G4,Catalogo_Codigos,0)),"")) | R4: =IF(OR($C4="",$P4="",$O4=""),"",IF($F4<>"FACTURA","NO",IF(AND($P4>0,$O4>$Q4),"SI","NO"))) | S4: =IF($R4="SI",ROUND($O4*$P4,2),IF($C4="","",0)) | T4: 721.44 | U4: =IF($C4="","",IF($R4<>"SI","",IF($T4="","SIN DATO",IF(ABS($T4-$S4)<=0.5,"OK","REVISAR")))) | W4: =IF(OR($C4="",$N4=""),"",IF($F4="RHE",ROUND($L4-$V4,2),ROUND($L4-($S4/$N4),2))) | AA4: PENDIENTE | AB4: ADMINISTRATIVO
A5: 2 | B5: 46254 | C5: FL09-00136064 | D5: 20419195317 | E5: INKA TERRA PERU S.A.C. (INKATERRA MACHU PICCHU PUEBLO HOTEL) | F5: FACTURA | G5: N/A | H5: =IF($G5="","",IFERROR(INDEX(Catalogo_Etiquetas,MATCH($G5,Catalogo_Codigos,0)),"CODIGO NO VALIDO")) | I5: USD | J5: 806.96 | K5: 0 | L5: =IF($C5="","",$J5+$K5) | M5: 639 | N5: =IF($C5="","",IF($I5="PEN",1,IFERROR(IF(_xlfn.XLOOKUP($B5,TC_Fechas,TC_Venta_Rango,"",-1)="","",_xlfn.XLOOKUP($B5,TC_Fechas,TC_Venta_Rango,"",-1)),""))) | O5: =IF(OR($C5="",$N5=""),"",ROUND($J5*$N5,2)+ROUND($K5*$N5,2)) | P5: =IF($G5="","",IFERROR(INDEX(Catalogo_Tasas,MATCH($G5,Catalogo_Codigos,0)),"")) | Q5: =IF($G5="","",IFERROR(INDEX(Catalogo_Umbrales,MATCH($G5,Catalogo_Codigos,0)),"")) | R5: =IF(OR($C5="",$P5="",$O5=""),"",IF($F5<>"FACTURA","NO",IF(AND($P5>0,$O5>$Q5),"SI","NO"))) | S5: =IF($R5="SI",ROUND($O5*$P5,2),IF($C5="","",0)) | U5: =IF($C5="","",IF($R5<>"SI","",IF($T5="","SIN DATO",IF(ABS($T5-$S5)<=0.5,"OK","REVISAR")))) | W5: =IF(OR($C5="",$N5=""),"",IF($F5="RHE",ROUND($L5-$V5,2),ROUND($L5-($S5/$N5),2))) | AA5: PENDIENTE | AB5: PROVEEDOR
A6: 3 | B6: 46254 | C6: F078-00006851 | D6: 20510931514 | E6: PERUVIAN TOURS AGENCY S.A.C. (ARANWA - HOTEL COLCA) | F6: FACTURA | G6: N/A | H6: =IF($G6="","",IFERROR(INDEX(Catalogo_Etiquetas,MATCH($G6,Catalogo_Codigos,0)),"CODIGO NO VALIDO")) | I6: USD | J6: 936 | K6: 0 | L6: =IF($C6="","",$J6+$K6) | M6: 639 | N6: =IF($C6="","",IF($I6="PEN",1,IFERROR(IF(_xlfn.XLOOKUP($B6,TC_Fechas,TC_Venta_Rango,"",-1)="","",_xlfn.XLOOKUP($B6,TC_Fechas,TC_Venta_Rango,"",-1)),""))) | O6: =IF(OR($C6="",$N6=""),"",ROUND($J6*$N6,2)+ROUND($K6*$N6,2)) | P6: =IF($G6="","",IFERROR(INDEX(Catalogo_Tasas,MATCH($G6,Catalogo_Codigos,0)),"")) | Q6: =IF($G6="","",IFERROR(INDEX(Catalogo_Umbrales,MATCH($G6,Catalogo_Codigos,0)),"")) | R6: =IF(OR($C6="",$P6="",$O6=""),"",IF($F6<>"FACTURA","NO",IF(AND($P6>0,$O6>$Q6),"SI","NO"))) | S6: =IF($R6="SI",ROUND($O6*$P6,2),IF($C6="","",0)) | U6: =IF($C6="","",IF($R6<>"SI","",IF($T6="","SIN DATO",IF(ABS($T6-$S6)<=0.5,"OK","REVISAR")))) | W6: =IF(OR($C6="",$N6=""),"",IF($F6="RHE",ROUND($L6-$V6,2),ROUND($L6-($S6/$N6),2))) | AA6: PENDIENTE | AB6: PROVEEDOR
A7: 4 | B7: 46254 | C7: F007-00024508 | D7: 20536047906 | E7: HOTELERIA PERUANA S.A.C. (TIERRA VIVA HOTELS) | F7: FACTURA | G7: N/A | H7: =IF($G7="","",IFERROR(INDEX(Catalogo_Etiquetas,MATCH($G7,Catalogo_Codigos,0)),"CODIGO NO VALIDO")) | I7: USD | J7: 68 | K7: 0 | L7: =IF($C7="","",$J7+$K7) | M7: 639 | N7: =IF($C7="","",IF($I7="PEN",1,IFERROR(IF(_xlfn.XLOOKUP($B7,TC_Fechas,TC_Venta_Rango,"",-1)="","",_xlfn.XLOOKUP($B7,TC_Fechas,TC_Venta_Rango,"",-1)),""))) | O7: =IF(OR($C7="",$N7=""),"",ROUND($J7*$N7,2)+ROUND($K7*$N7,2)) | P7: =IF($G7="","",IFERROR(INDEX(Catalogo_Tasas,MATCH($G7,Catalogo_Codigos,0)),"")) | Q7: =IF($G7="","",IFERROR(INDEX(Catalogo_Umbrales,MATCH($G7,Catalogo_Codigos,0)),"")) | R7: =IF(OR($C7="",$P7="",$O7=""),"",IF($F7<>"FACTURA","NO",IF(AND($P7>0,$O7>$Q7),"SI","NO"))) | S7: =IF($R7="SI",ROUND($O7*$P7,2),IF($C7="","",0)) | U7: =IF($C7="","",IF($R7<>"SI","",IF($T7="","SIN DATO",IF(ABS($T7-$S7)<=0.5,"OK","REVISAR")))) | W7: =IF(OR($C7="",$N7=""),"",IF($F7="RHE",ROUND($L7-$V7,2),ROUND($L7-($S7/$N7),2))) | AA7: PENDIENTE | AB7: PROVEEDOR
A8: 5 | B8: 46254 | C8: F008-00035739 | D8: 20536047906 | E8: HOTELERIA PERUANA S.A.C. (TIERRA VIVA HOTELS) | F8: FACTURA | G8: N/A | H8: =IF($G8="","",IFERROR(INDEX(Catalogo_Etiquetas,MATCH($G8,Catalogo_Codigos,0)),"CODIGO NO VALIDO")) | I8: USD | J8: 152 | K8: 0 | L8: =IF($C8="","",$J8+$K8) | M8: 639 | N8: =IF($C8="","",IF($I8="PEN",1,IFERROR(IF(_xlfn.XLOOKUP($B8,TC_Fechas,TC_Venta_Rango,"",-1)="","",_xlfn.XLOOKUP($B8,TC_Fechas,TC_Venta_Rango,"",-1)),""))) | O8: =IF(OR($C8="",$N8=""),"",ROUND($J8*$N8,2)+ROUND($K8*$N8,2)) | P8: =IF($G8="","",IFERROR(INDEX(Catalogo_Tasas,MATCH($G8,Catalogo_Codigos,0)),"")) | Q8: =IF($G8="","",IFERROR(INDEX(Catalogo_Umbrales,MATCH($G8,Catalogo_Codigos,0)),"")) | R8: =IF(OR($C8="",$P8="",$O8=""),"",IF($F8<>"FACTURA","NO",IF(AND($P8>0,$O8>$Q8),"SI","NO"))) | S8: =IF($R8="SI",ROUND($O8*$P8,2),IF($C8="","",0)) | U8: =IF($C8="","",IF($R8<>"SI","",IF($T8="","SIN DATO",IF(ABS($T8-$S8)<=0.5,"OK","REVISAR")))) | W8: =IF(OR($C8="",$N8=""),"",IF($F8="RHE",ROUND($L8-$V8,2),ROUND($L8-($S8/$N8),2))) | AA8: PENDIENTE | AB8: PROVEEDOR
A9: 6 | B9: 46254 | C9: F003-00017125 | D9: 20563817675 | E9: CCM HOTEL GROUP S.A.C. (CASA REPUBLICA BARRANCO) | F9: FACTURA | G9: N/A | H9: =IF($G9="","",IFERROR(INDEX(Catalogo_Etiquetas,MATCH($G9,Catalogo_Codigos,0)),"CODIGO NO VALIDO")) | I9: USD | J9: 196.27 | K9: 18.73 | L9: =IF($C9="","",$J9+$K9) | M9: 639 | N9: =IF($C9="","",IF($I9="PEN",1,IFERROR(IF(_xlfn.XLOOKUP($B9,TC_Fechas,TC_Venta_Rango,"",-1)="","",_xlfn.XLOOKUP($B9,TC_Fechas,TC_Venta_Rango,"",-1)),""))) | O9: =IF(OR($C9="",$N9=""),"",ROUND($J9*$N9,2)+ROUND($K9*$N9,2)) | P9: =IF($G9="","",IFERROR(INDEX(Catalogo_Tasas,MATCH($G9,Catalogo_Codigos,0)),"")) | Q9: =IF($G9="","",IFERROR(INDEX(Catalogo_Umbrales,MATCH($G9,Catalogo_Codigos,0)),"")) | R9: =IF(OR($C9="",$P9="",$O9=""),"",IF($F9<>"FACTURA","NO",IF(AND($P9>0,$O9>$Q9),"SI","NO"))) | S9: =IF($R9="SI",ROUND($O9*$P9,2),IF($C9="","",0)) | U9: =IF($C9="","",IF($R9<>"SI","",IF($T9="","SIN DATO",IF(ABS($T9-$S9)<=0.5,"OK","REVISAR")))) | W9: =IF(OR($C9="",$N9=""),"",IF($F9="RHE",ROUND($L9-$V9,2),ROUND($L9-($S9/$N9),2))) | AA9: PENDIENTE | AB9: PROVEEDOR
A10: 7 | B10: 46254 | C10: F003-00017127 | D10: 20563817675 | E10: CCM HOTEL GROUP S.A.C. (CASA REPUBLICA BARRANCO) | F10: FACTURA | G10: N/A | H10: =IF($G10="","",IFERROR(INDEX(Catalogo_Etiquetas,MATCH($G10,Catalogo_Codigos,0)),"CODIGO NO VALIDO")) | I10: USD | J10: 230 | K10: 0 | L10: =IF($C10="","",$J10+$K10) | M10: 639 | N10: =IF($C10="","",IF($I10="PEN",1,IFERROR(IF(_xlfn.XLOOKUP($B10,TC_Fechas,TC_Venta_Rango,"",-1)="","",_xlfn.XLOOKUP($B10,TC_Fechas,TC_Venta_Rango,"",-1)),""))) | O10: =IF(OR($C10="",$N10=""),"",ROUND($J10*$N10,2)+ROUND($K10*$N10,2)) | P10: =IF($G10="","",IFERROR(INDEX(Catalogo_Tasas,MATCH($G10,Catalogo_Codigos,0)),"")) | Q10: =IF($G10="","",IFERROR(INDEX(Catalogo_Umbrales,MATCH($G10,Catalogo_Codigos,0)),"")) | R10: =IF(OR($C10="",$P10="",$O10=""),"",IF($F10<>"FACTURA","NO",IF(AND($P10>0,$O10>$Q10),"SI","NO"))) | S10: =IF($R10="SI",ROUND($O10*$P10,2),IF($C10="","",0)) | U10: =IF($C10="","",IF($R10<>"SI","",IF($T10="","SIN DATO",IF(ABS($T10-$S10)<=0.5,"OK","REVISAR")))) | W10: =IF(OR($C10="",$N10=""),"",IF($F10="RHE",ROUND($L10-$V10,2),ROUND($L10-($S10/$N10),2))) | AA10: PENDIENTE | AB10: PROVEEDOR
A11: 8 | B11: 46254 | C11: FNC3-00001843 | D11: 20563817675 | E11: CCM HOTEL GROUP S.A.C. (CASA REPUBLICA BARRANCO) | F11: NOTA DE CREDITO | G11: N/A | H11: =IF($G11="","",IFERROR(INDEX(Catalogo_Etiquetas,MATCH($G11,Catalogo_Codigos,0)),"CODIGO NO VALIDO")) | I11: USD | J11: -209.96 | K11: -20.04 | L11: =IF($C11="","",$J11+$K11) | M11: 639 | N11: =IF($C11="","",IF($I11="PEN",1,IFERROR(IF(_xlfn.XLOOKUP($B11,TC_Fechas,TC_Venta_Rango,"",-1)="","",_xlfn.XLOOKUP($B11,TC_Fechas,TC_Venta_Rango,"",-1)),""))) | O11: =IF(OR($C11="",$N11=""),"",ROUND($J11*$N11,2)+ROUND($K11*$N11,2)) | P11: =IF($G11="","",IFERROR(INDEX(Catalogo_Tasas,MATCH($G11,Catalogo_Codigos,0)),"")) | Q11: =IF($G11="","",IFERROR(INDEX(Catalogo_Umbrales,MATCH($G11,Catalogo_Codigos,0)),"")) | R11: =IF(OR($C11="",$P11="",$O11=""),"",IF($F11<>"FACTURA","NO",IF(AND($P11>0,$O11>$Q11),"SI","NO"))) | S11: =IF($R11="SI",ROUND($O11*$P11,2),IF($C11="","",0)) | U11: =IF($C11="","",IF($R11<>"SI","",IF($T11="","SIN DATO",IF(ABS($T11-$S11)<=0.5,"OK","REVISAR")))) | W11: =IF(OR($C11="",$N11=""),"",IF($F11="RHE",ROUND($L11-$V11,2),ROUND($L11-($S11/$N11),2))) | AA11: PENDIENTE | AB11: PROVEEDOR
A12: 9 | B12: 46254 | C12: E001-7201 | D12: 20225253529 | E12: ARCOBALENO SOCIEDAD COMERCIAL DE RESPONSABILIDAD LIMITADA | F12: FACTURA | G12: 037 | H12: =IF($G12="","",IFERROR(INDEX(Catalogo_Etiquetas,MATCH($G12,Catalogo_Codigos,0)),"CODIGO NO VALIDO")) | I12: USD | J12: 186.03 | K12: 33.49 | L12: =IF($C12="","",$J12+$K12) | M12: 639 | N12: =IF($C12="","",IF($I12="PEN",1,IFERROR(IF(_xlfn.XLOOKUP($B12,TC_Fechas,TC_Venta_Rango,"",-1)="","",_xlfn.XLOOKUP($B12,TC_Fechas,TC_Venta_Rango,"",-1)),""))) | O12: =IF(OR($C12="",$N12=""),"",ROUND($J12*$N12,2)+ROUND($K12*$N12,2)) | P12: =IF($G12="","",IFERROR(INDEX(Catalogo_Tasas,MATCH($G12,Catalogo_Codigos,0)),"")) | Q12: =IF($G12="","",IFERROR(INDEX(Catalogo_Umbrales,MATCH($G12,Catalogo_Codigos,0)),"")) | R12: =IF(OR($C12="",$P12="",$O12=""),"",IF($F12<>"FACTURA","NO",IF(AND($P12>0,$O12>$Q12),"SI","NO"))) | S12: =IF($R12="SI",ROUND($O12*$P12,2),IF($C12="","",0)) | T12: 89 | U12: =IF($C12="","",IF($R12<>"SI","",IF($T12="","SIN DATO",IF(ABS($T12-$S12)<=0.5,"OK","REVISAR")))) | W12: =IF(OR($C12="",$N12=""),"",IF($F12="RHE",ROUND($L12-$V12,2),ROUND($L12-($S12/$N12),2))) | AA12: PENDIENTE | AB12: PROVEEDOR
A13: 10 | B13: =DATE(2026,8,11) | C13: F001-0003289 | D13: 20510815522 | E13: AERODIANA | F13: NOTA DE CREDITO | G13: N/A | H13: =IF($G13="","",IFERROR(INDEX(Catalogo_Etiquetas,MATCH($G13,Catalogo_Codigos,0)),"CODIGO NO VALIDO")) | I13: USD | J13: -498.31 | K13: -89.69 | L13: =IF($C13="","",$J13+$K13) | M13: 639 | N13: =IF($C13="","",IF($I13="PEN",1,IFERROR(IF(_xlfn.XLOOKUP($B13,TC_Fechas,TC_Venta_Rango,"",-1)="","",_xlfn.XLOOKUP($B13,TC_Fechas,TC_Venta_Rango,"",-1)),""))) | O13: =IF(OR($C13="",$N13=""),"",ROUND($J13*$N13,2)+ROUND($K13*$N13,2)) | P13: =IF($G13="","",IFERROR(INDEX(Catalogo_Tasas,MATCH($G13,Catalogo_Codigos,0)),"")) | Q13: =IF($G13="","",IFERROR(INDEX(Catalogo_Umbrales,MATCH($G13,Catalogo_Codigos,0)),"")) | R13: =IF(OR($C13="",$P13="",$O13=""),"",IF($F13<>"FACTURA","NO",IF(AND($P13>0,$O13>$Q13),"SI","NO"))) | S13: =IF($R13="SI",ROUND($O13*$P13,2),IF($C13="","",0)) | U13: =IF($C13="","",IF($R13<>"SI","",IF($T13="","SIN DATO",IF(ABS($T13-$S13)<=0.5,"OK","REVISAR")))) | W13: =IF(OR($C13="",$N13=""),"",IF($F13="RHE",ROUND($L13-$V13,2),ROUND($L13-($S13/$N13),2))) | AB13: PROVEEDOR
A14: 11 | B14: =DATE(2026,8,6) | C14: F001-038853 | D14: 20358806237 | E14: AMERICANA DE TURISMO E.I.R.L. | F14: FACTURA | G14: N/A | H14: =IF($G14="","",IFERROR(INDEX(Catalogo_Etiquetas,MATCH($G14,Catalogo_Codigos,0)),"CODIGO NO VALIDO")) | I14: USD | J14: 61.02 | K14: 10.98 | L14: =IF($C14="","",$J14+$K14) | M14: 639 | N14: =IF($C14="","",IF($I14="PEN",1,IFERROR(IF(_xlfn.XLOOKUP($B14,TC_Fechas,TC_Venta_Rango,"",-1)="","",_xlfn.XLOOKUP($B14,TC_Fechas,TC_Venta_Rango,"",-1)),""))) | O14: =IF(OR($C14="",$N14=""),"",ROUND($J14*$N14,2)+ROUND($K14*$N14,2)) | P14: =IF($G14="","",IFERROR(INDEX(Catalogo_Tasas,MATCH($G14,Catalogo_Codigos,0)),"")) | Q14: =IF($G14="","",IFERROR(INDEX(Catalogo_Umbrales,MATCH($G14,Catalogo_Codigos,0)),"")) | R14: =IF(OR($C14="",$P14="",$O14=""),"",IF($F14<>"FACTURA","NO",IF(AND($P14>0,$O14>$Q14),"SI","NO"))) | S14: =IF($R14="SI",ROUND($O14*$P14,2),IF($C14="","",0)) | U14: =IF($C14="","",IF($R14<>"SI","",IF($T14="","SIN DATO",IF(ABS($T14-$S14)<=0.5,"OK","REVISAR")))) | W14: =IF(OR($C14="",$N14=""),"",IF($F14="RHE",ROUND($L14-$V14,2),ROUND($L14-($S14/$N14),2))) | AB14: PROVEEDOR
A15: 12 | B15: =DATE(2026,8,10) | C15: E001- 173 | D15: 10408744151 | E15: BEOUTIS BAZAN URSULA CATHERINE | F15: RHE | G15: N/A | H15: =IF($G15="","",IFERROR(INDEX(Catalogo_Etiquetas,MATCH($G15,Catalogo_Codigos,0)),"CODIGO NO VALIDO")) | I15: PEN | J15: 1025 | K15: 0 | L15: =IF($C15="","",$J15+$K15) | M15: 632 | N15: =IF($C15="","",IF($I15="PEN",1,IFERROR(IF(_xlfn.XLOOKUP($B15,TC_Fechas,TC_Venta_Rango,"",-1)="","",_xlfn.XLOOKUP($B15,TC_Fechas,TC_Venta_Rango,"",-1)),""))) | O15: =IF(OR($C15="",$N15=""),"",ROUND($J15*$N15,2)+ROUND($K15*$N15,2)) | P15: =IF($G15="","",IFERROR(INDEX(Catalogo_Tasas,MATCH($G15,Catalogo_Codigos,0)),"")) | Q15: =IF($G15="","",IFERROR(INDEX(Catalogo_Umbrales,MATCH($G15,Catalogo_Codigos,0)),"")) | R15: =IF(OR($C15="",$P15="",$O15=""),"",IF($F15<>"FACTURA","NO",IF(AND($P15>0,$O15>$Q15),"SI","NO"))) | S15: =IF($R15="SI",ROUND($O15*$P15,2),IF($C15="","",0)) | U15: =IF($C15="","",IF($R15<>"SI","",IF($T15="","SIN DATO",IF(ABS($T15-$S15)<=0.5,"OK","REVISAR")))) | W15: =IF(OR($C15="",$N15=""),"",IF($F15="RHE",ROUND($L15-$V15,2),ROUND($L15-($S15/$N15),2))) | AB15: ADMINISTRATIVO
A16: 13 | B16: =DATE(2026,8,14) | C16: E001-129 | D16: 10239541181 | E16: CALLAÃ‘AUPA DE HENDRICKSON FLORA | F16: RHE | G16: N/A | H16: =IF($G16="","",IFERROR(INDEX(Catalogo_Etiquetas,MATCH($G16,Catalogo_Codigos,0)),"CODIGO NO VALIDO")) | I16: USD | J16: 65 | K16: 0 | L16: =IF($C16="","",$J16+$K16) | M16: 632 | N16: =IF($C16="","",IF($I16="PEN",1,IFERROR(IF(_xlfn.XLOOKUP($B16,TC_Fechas,TC_Venta_Rango,"",-1)="","",_xlfn.XLOOKUP($B16,TC_Fechas,TC_Venta_Rango,"",-1)),""))) | O16: =IF(OR($C16="",$N16=""),"",ROUND($J16*$N16,2)+ROUND($K16*$N16,2)) | P16: =IF($G16="","",IFERROR(INDEX(Catalogo_Tasas,MATCH($G16,Catalogo_Codigos,0)),"")) | Q16: =IF($G16="","",IFERROR(INDEX(Catalogo_Umbrales,MATCH($G16,Catalogo_Codigos,0)),"")) | R16: =IF(OR($C16="",$P16="",$O16=""),"",IF($F16<>"FACTURA","NO",IF(AND($P16>0,$O16>$Q16),"SI","NO"))) | S16: =IF($R16="SI",ROUND($O16*$P16,2),IF($C16="","",0)) | U16: =IF($C16="","",IF($R16<>"SI","",IF($T16="","SIN DATO",IF(ABS($T16-$S16)<=0.5,"OK","REVISAR")))) | V16: 7.8 | W16: =IF(OR($C16="",$N16=""),"",IF($F16="RHE",ROUND($L16-$V16,2),ROUND($L16-($S16/$N16),2))) | AB16: PROVEEDOR
A17: 14 | B17: =DATE(2026,8,12) | C17: FA02-00001849 | D17: 20527992525 | E17: CUSCO RESTAURANTS S.A.C. | F17: FACTURA | G17: N/A | H17: =IF($G17="","",IFERROR(INDEX(Catalogo_Etiquetas,MATCH($G17,Catalogo_Codigos,0)),"CODIGO NO VALIDO")) | I17: USD | J17: 54.69 | K17: 9.84 | L17: =IF($C17="","",$J17+$K17) | M17: 639 | N17: =IF($C17="","",IF($I17="PEN",1,IFERROR(IF(_xlfn.XLOOKUP($B17,TC_Fechas,TC_Venta_Rango,"",-1)="","",_xlfn.XLOOKUP($B17,TC_Fechas,TC_Venta_Rango,"",-1)),""))) | O17: =IF(OR($C17="",$N17=""),"",ROUND($J17*$N17,2)+ROUND($K17*$N17,2)) | P17: =IF($G17="","",IFERROR(INDEX(Catalogo_Tasas,MATCH($G17,Catalogo_Codigos,0)),"")) | Q17: =IF($G17="","",IFERROR(INDEX(Catalogo_Umbrales,MATCH($G17,Catalogo_Codigos,0)),"")) | R17: =IF(OR($C17="",$P17="",$O17=""),"",IF($F17<>"FACTURA","NO",IF(AND($P17>0,$O17>$Q17),"SI","NO"))) | S17: =IF($R17="SI",ROUND($O17*$P17,2),IF($C17="","",0)) | U17: =IF($C17="","",IF($R17<>"SI","",IF($T17="","SIN DATO",IF(ABS($T17-$S17)<=0.5,"OK","REVISAR")))) | W17: =IF(OR($C17="",$N17=""),"",IF($F17="RHE",ROUND($L17-$V17,2),ROUND($L17-($S17/$N17),2))) | AB17: PROVEEDOR
A18: 15 | B18: =DATE(2026,8,6) | C18: F005-018812 | D18: 20252796623 | E18: GRESCO S.A.C. | F18: FACTURA | G18: N/A | H18: =IF($G18="","",IFERROR(INDEX(Catalogo_Etiquetas,MATCH($G18,Catalogo_Codigos,0)),"CODIGO NO VALIDO")) | I18: PEN | J18: 158.73 | K18: 28.57 | L18: =IF($C18="","",$J18+$K18) | M18: 639 | N18: =IF($C18="","",IF($I18="PEN",1,IFERROR(IF(_xlfn.XLOOKUP($B18,TC_Fechas,TC_Venta_Rango,"",-1)="","",_xlfn.XLOOKUP($B18,TC_Fechas,TC_Venta_Rango,"",-1)),""))) | O18: =IF(OR($C18="",$N18=""),"",ROUND($J18*$N18,2)+ROUND($K18*$N18,2)) | P18: =IF($G18="","",IFERROR(INDEX(Catalogo_Tasas,MATCH($G18,Catalogo_Codigos,0)),"")) | Q18: =IF($G18="","",IFERROR(INDEX(Catalogo_Umbrales,MATCH($G18,Catalogo_Codigos,0)),"")) | R18: =IF(OR($C18="",$P18="",$O18=""),"",IF($F18<>"FACTURA","NO",IF(AND($P18>0,$O18>$Q18),"SI","NO"))) | S18: =IF($R18="SI",ROUND($O18*$P18,2),IF($C18="","",0)) | U18: =IF($C18="","",IF($R18<>"SI","",IF($T18="","SIN DATO",IF(ABS($T18-$S18)<=0.5,"OK","REVISAR")))) | W18: =IF(OR($C18="",$N18=""),"",IF($F18="RHE",ROUND($L18-$V18,2),ROUND($L18-($S18/$N18),2))) | AB18: PROVEEDOR
A19: 16 | B19: =DATE(2026,8,4) | C19: E001- 558 | D19: 10239898993 | E19: HANCO ASTETE ANDY | F19: RHE | G19: N/A | H19: =IF($G19="","",IFERROR(INDEX(Catalogo_Etiquetas,MATCH($G19,Catalogo_Codigos,0)),"CODIGO NO VALIDO")) | I19: USD | J19: 75 | K19: 0 | L19: =IF($C19="","",$J19+$K19) | M19: 632 | N19: =IF($C19="","",IF($I19="PEN",1,IFERROR(IF(_xlfn.XLOOKUP($B19,TC_Fechas,TC_Venta_Rango,"",-1)="","",_xlfn.XLOOKUP($B19,TC_Fechas,TC_Venta_Rango,"",-1)),""))) | O19: =IF(OR($C19="",$N19=""),"",ROUND($J19*$N19,2)+ROUND($K19*$N19,2)) | P19: =IF($G19="","",IFERROR(INDEX(Catalogo_Tasas,MATCH($G19,Catalogo_Codigos,0)),"")) | Q19: =IF($G19="","",IFERROR(INDEX(Catalogo_Umbrales,MATCH($G19,Catalogo_Codigos,0)),"")) | R19: =IF(OR($C19="",$P19="",$O19=""),"",IF($F19<>"FACTURA","NO",IF(AND($P19>0,$O19>$Q19),"SI","NO"))) | S19: =IF($R19="SI",ROUND($O19*$P19,2),IF($C19="","",0)) | U19: =IF($C19="","",IF($R19<>"SI","",IF($T19="","SIN DATO",IF(ABS($T19-$S19)<=0.5,"OK","REVISAR")))) | W19: =IF(OR($C19="",$N19=""),"",IF($F19="RHE",ROUND($L19-$V19,2),ROUND($L19-($S19/$N19),2))) | AB19: PROVEEDOR
A20: 17 | B20: =DATE(2026,8,14) | C20: F006-00003152 | D20: 20610235736 | E20: HOTELES LA HACIENDA S.A.C. | F20: FACTURA | G20: N/A | H20: =IF($G20="","",IFERROR(INDEX(Catalogo_Etiquetas,MATCH($G20,Catalogo_Codigos,0)),"CODIGO NO VALIDO")) | I20: USD | J20: 460.18 | K20: 0 | L20: =IF($C20="","",$J20+$K20) | M20: 639 | N20: =IF($C20="","",IF($I20="PEN",1,IFERROR(IF(_xlfn.XLOOKUP($B20,TC_Fechas,TC_Venta_Rango,"",-1)="","",_xlfn.XLOOKUP($B20,TC_Fechas,TC_Venta_Rango,"",-1)),""))) | O20: =IF(OR($C20="",$N20=""),"",ROUND($J20*$N20,2)+ROUND($K20*$N20,2)) | P20: =IF($G20="","",IFERROR(INDEX(Catalogo_Tasas,MATCH($G20,Catalogo_Codigos,0)),"")) | Q20: =IF($G20="","",IFERROR(INDEX(Catalogo_Umbrales,MATCH($G20,Catalogo_Codigos,0)),"")) | R20: =IF(OR($C20="",$P20="",$O20=""),"",IF($F20<>"FACTURA","NO",IF(AND($P20>0,$O20>$Q20),"SI","NO"))) | S20: =IF($R20="SI",ROUND($O20*$P20,2),IF($C20="","",0)) | U20: =IF($C20="","",IF($R20<>"SI","",IF($T20="","SIN DATO",IF(ABS($T20-$S20)<=0.5,"OK","REVISAR")))) | W20: =IF(OR($C20="",$N20=""),"",IF($F20="RHE",ROUND($L20-$V20,2),ROUND($L20-($S20/$N20),2))) | AB20: PROVEEDOR
A21: 18 | B21: =DATE(2026,8,4) | C21: E001-1678 | D21: 20602511007 | E21: INVERSIONES FENIX TOURS E.I.R.L. | F21: FACTURA | G21: 026 | H21: =IF($G21="","",IFERROR(INDEX(Catalogo_Etiquetas,MATCH($G21,Catalogo_Codigos,0)),"CODIGO NO VALIDO")) | I21: USD | J21: 282.2 | K21: 50.8 | L21: =IF($C21="","",$J21+$K21) | M21: 631 | N21: =IF($C21="","",IF($I21="PEN",1,IFERROR(IF(_xlfn.XLOOKUP($B21,TC_Fechas,TC_Venta_Rango,"",-1)="","",_xlfn.XLOOKUP($B21,TC_Fechas,TC_Venta_Rango,"",-1)),""))) | O21: =IF(OR($C21="",$N21=""),"",ROUND($J21*$N21,2)+ROUND($K21*$N21,2)) | P21: =IF($G21="","",IFERROR(INDEX(Catalogo_Tasas,MATCH($G21,Catalogo_Codigos,0)),"")) | Q21: =IF($G21="","",IFERROR(INDEX(Catalogo_Umbrales,MATCH($G21,Catalogo_Codigos,0)),"")) | R21: =IF(OR($C21="",$P21="",$O21=""),"",IF($F21<>"FACTURA","NO",IF(AND($P21>0,$O21>$Q21),"SI","NO"))) | S21: =IF($R21="SI",ROUND($O21*$P21,2),IF($C21="","",0)) | T21: 113 | U21: =IF($C21="","",IF($R21<>"SI","",IF($T21="","SIN DATO",IF(ABS($T21-$S21)<=0.5,"OK","REVISAR")))) | W21: =IF(OR($C21="",$N21=""),"",IF($F21="RHE",ROUND($L21-$V21,2),ROUND($L21-($S21/$N21),2))) | AB21: PROVEEDOR
A22: 19 | B22: =DATE(2026,8,14) | C22: E001-2661 | D22: 20602860958 | E22: J & R TURISMO E.I.R.L. | F22: FACTURA | G22: 026 | H22: =IF($G22="","",IFERROR(INDEX(Catalogo_Etiquetas,MATCH($G22,Catalogo_Codigos,0)),"CODIGO NO VALIDO")) | I22: USD | J22: 660 | K22: 118.8 | L22: =IF($C22="","",$J22+$K22) | M22: 631 | N22: =IF($C22="","",IF($I22="PEN",1,IFERROR(IF(_xlfn.XLOOKUP($B22,TC_Fechas,TC_Venta_Rango,"",-1)="","",_xlfn.XLOOKUP($B22,TC_Fechas,TC_Venta_Rango,"",-1)),""))) | O22: =IF(OR($C22="",$N22=""),"",ROUND($J22*$N22,2)+ROUND($K22*$N22,2)) | P22: =IF($G22="","",IFERROR(INDEX(Catalogo_Tasas,MATCH($G22,Catalogo_Codigos,0)),"")) | Q22: =IF($G22="","",IFERROR(INDEX(Catalogo_Umbrales,MATCH($G22,Catalogo_Codigos,0)),"")) | R22: =IF(OR($C22="",$P22="",$O22=""),"",IF($F22<>"FACTURA","NO",IF(AND($P22>0,$O22>$Q22),"SI","NO"))) | S22: =IF($R22="SI",ROUND($O22*$P22,2),IF($C22="","",0)) | T22: 262.53 | U22: =IF($C22="","",IF($R22<>"SI","",IF($T22="","SIN DATO",IF(ABS($T22-$S22)<=0.5,"OK","REVISAR")))) | W22: =IF(OR($C22="",$N22=""),"",IF($F22="RHE",ROUND($L22-$V22,2),ROUND($L22-($S22/$N22),2))) | AB22: PROVEEDOR
A23: 20 | B23: =DATE(2026,8,13) | C23: E001-9 | D23: 10726172591 | E23: LUCERO KARLA MADGE BOCANEGRA | F23: RHE | G23: N/A | H23: =IF($G23="","",IFERROR(INDEX(Catalogo_Etiquetas,MATCH($G23,Catalogo_Codigos,0)),"CODIGO NO VALIDO")) | I23: PEN | J23: 1100 | K23: 0 | L23: =IF($C23="","",$J23+$K23) | M23: 632 | N23: =IF($C23="","",IF($I23="PEN",1,IFERROR(IF(_xlfn.XLOOKUP($B23,TC_Fechas,TC_Venta_Rango,"",-1)="","",_xlfn.XLOOKUP($B23,TC_Fechas,TC_Venta_Rango,"",-1)),""))) | O23: =IF(OR($C23="",$N23=""),"",ROUND($J23*$N23,2)+ROUND($K23*$N23,2)) | P23: =IF($G23="","",IFERROR(INDEX(Catalogo_Tasas,MATCH($G23,Catalogo_Codigos,0)),"")) | Q23: =IF($G23="","",IFERROR(INDEX(Catalogo_Umbrales,MATCH($G23,Catalogo_Codigos,0)),"")) | R23: =IF(OR($C23="",$P23="",$O23=""),"",IF($F23<>"FACTURA","NO",IF(AND($P23>0,$O23>$Q23),"SI","NO"))) | S23: =IF($R23="SI",ROUND($O23*$P23,2),IF($C23="","",0)) | U23: =IF($C23="","",IF($R23<>"SI","",IF($T23="","SIN DATO",IF(ABS($T23-$S23)<=0.5,"OK","REVISAR")))) | W23: =IF(OR($C23="",$N23=""),"",IF($F23="RHE",ROUND($L23-$V23,2),ROUND($L23-($S23/$N23),2))) | AB23: ADMINISTRATIVO
A24: 21 | B24: =DATE(2026,8,14) | C24: E001- 32 | D24: 10490200784 | E24: NIKOLSKAIA VALENTINA | F24: RHE | G24: N/A | H24: =IF($G24="","",IFERROR(INDEX(Catalogo_Etiquetas,MATCH($G24,Catalogo_Codigos,0)),"CODIGO NO VALIDO")) | I24: USD | J24: 700 | K24: 0 | L24: =IF($C24="","",$J24+$K24) | M24: 632 | N24: =IF($C24="","",IF($I24="PEN",1,IFERROR(IF(_xlfn.XLOOKUP($B24,TC_Fechas,TC_Venta_Rango,"",-1)="","",_xlfn.XLOOKUP($B24,TC_Fechas,TC_Venta_Rango,"",-1)),""))) | O24: =IF(OR($C24="",$N24=""),"",ROUND($J24*$N24,2)+ROUND($K24*$N24,2)) | P24: =IF($G24="","",IFERROR(INDEX(Catalogo_Tasas,MATCH($G24,Catalogo_Codigos,0)),"")) | Q24: =IF($G24="","",IFERROR(INDEX(Catalogo_Umbrales,MATCH($G24,Catalogo_Codigos,0)),"")) | R24: =IF(OR($C24="",$P24="",$O24=""),"",IF($F24<>"FACTURA","NO",IF(AND($P24>0,$O24>$Q24),"SI","NO"))) | S24: =IF($R24="SI",ROUND($O24*$P24,2),IF($C24="","",0)) | U24: =IF($C24="","",IF($R24<>"SI","",IF($T24="","SIN DATO",IF(ABS($T24-$S24)<=0.5,"OK","REVISAR")))) | W24: =IF(OR($C24="",$N24=""),"",IF($F24="RHE",ROUND($L24-$V24,2),ROUND($L24-($S24/$N24),2))) | AB24: PROVEEDOR
A25: 22 | B25: =DATE(2026,8,12) | C25: F001-00000737 | D25: 20603386214 | E25: PERUVIAN CULTURE TRAVEL AGENCIA DE VIAJES Y TURISMO S.R.L. | F25: FACTURA | G25: N/A | H25: =IF($G25="","",IFERROR(INDEX(Catalogo_Etiquetas,MATCH($G25,Catalogo_Codigos,0)),"CODIGO NO VALIDO")) | I25: USD | J25: 61.02 | K25: 10.98 | L25: =IF($C25="","",$J25+$K25) | M25: 639 | N25: =IF($C25="","",IF($I25="PEN",1,IFERROR(IF(_xlfn.XLOOKUP($B25,TC_Fechas,TC_Venta_Rango,"",-1)="","",_xlfn.XLOOKUP($B25,TC_Fechas,TC_Venta_Rango,"",-1)),""))) | O25: =IF(OR($C25="",$N25=""),"",ROUND($J25*$N25,2)+ROUND($K25*$N25,2)) | P25: =IF($G25="","",IFERROR(INDEX(Catalogo_Tasas,MATCH($G25,Catalogo_Codigos,0)),"")) | Q25: =IF($G25="","",IFERROR(INDEX(Catalogo_Umbrales,MATCH($G25,Catalogo_Codigos,0)),"")) | R25: =IF(OR($C25="",$P25="",$O25=""),"",IF($F25<>"FACTURA","NO",IF(AND($P25>0,$O25>$Q25),"SI","NO"))) | S25: =IF($R25="SI",ROUND($O25*$P25,2),IF($C25="","",0)) | U25: =IF($C25="","",IF($R25<>"SI","",IF($T25="","SIN DATO",IF(ABS($T25-$S25)<=0.5,"OK","REVISAR")))) | W25: =IF(OR($C25="",$N25=""),"",IF($F25="RHE",ROUND($L25-$V25,2),ROUND($L25-($S25/$N25),2))) | AB25: PROVEEDOR
A26: 23 | B26: =DATE(2026,8,17) | C26: E001- 504 | D26: 10422800102 | E26: SARMIENTO LOPEZ LUIS RONALD | F26: RHE | G26: N/A | H26: =IF($G26="","",IFERROR(INDEX(Catalogo_Etiquetas,MATCH($G26,Catalogo_Codigos,0)),"CODIGO NO VALIDO")) | I26: USD | J26: 157 | K26: 0 | L26: =IF($C26="","",$J26+$K26) | M26: 632 | N26: =IF($C26="","",IF($I26="PEN",1,IFERROR(IF(_xlfn.XLOOKUP($B26,TC_Fechas,TC_Venta_Rango,"",-1)="","",_xlfn.XLOOKUP($B26,TC_Fechas,TC_Venta_Rango,"",-1)),""))) | O26: =IF(OR($C26="",$N26=""),"",ROUND($J26*$N26,2)+ROUND($K26*$N26,2)) | P26: =IF($G26="","",IFERROR(INDEX(Catalogo_Tasas,MATCH($G26,Catalogo_Codigos,0)),"")) | Q26: =IF($G26="","",IFERROR(INDEX(Catalogo_Umbrales,MATCH($G26,Catalogo_Codigos,0)),"")) | R26: =IF(OR($C26="",$P26="",$O26=""),"",IF($F26<>"FACTURA","NO",IF(AND($P26>0,$O26>$Q26),"SI","NO"))) | S26: =IF($R26="SI",ROUND($O26*$P26,2),IF($C26="","",0)) | U26: =IF($C26="","",IF($R26<>"SI","",IF($T26="","SIN DATO",IF(ABS($T26-$S26)<=0.5,"OK","REVISAR")))) | V26: 12.56 | W26: =IF(OR($C26="",$N26=""),"",IF($F26="RHE",ROUND($L26-$V26,2),ROUND($L26-($S26/$N26),2))) | AB26: PROVEEDOR
A27: 24 | B27: =DATE(2026,8,8) | C27: E001-1230 | D27: 20600179005 | E27: TRANSPORTES TURISTICOS LASER S.A.C. | F27: FACTURA | G27: 026 | H27: =IF($G27="","",IFERROR(INDEX(Catalogo_Etiquetas,MATCH($G27,Catalogo_Codigos,0)),"CODIGO NO VALIDO")) | I27: USD | J27: 1267.74 | K27: 228.19 | L27: =IF($C27="","",$J27+$K27) | M27: 631 | N27: =IF($C27="","",IF($I27="PEN",1,IFERROR(IF(_xlfn.XLOOKUP($B27,TC_Fechas,TC_Venta_Rango,"",-1)="","",_xlfn.XLOOKUP($B27,TC_Fechas,TC_Venta_Rango,"",-1)),""))) | O27: =IF(OR($C27="",$N27=""),"",ROUND($J27*$N27,2)+ROUND($K27*$N27,2)) | P27: =IF($G27="","",IFERROR(INDEX(Catalogo_Tasas,MATCH($G27,Catalogo_Codigos,0)),"")) | Q27: =IF($G27="","",IFERROR(INDEX(Catalogo_Umbrales,MATCH($G27,Catalogo_Codigos,0)),"")) | R27: =IF(OR($C27="",$P27="",$O27=""),"",IF($F27<>"FACTURA","NO",IF(AND($P27>0,$O27>$Q27),"SI","NO"))) | S27: =IF($R27="SI",ROUND($O27*$P27,2),IF($C27="","",0)) | T27: 508 | U27: =IF($C27="","",IF($R27<>"SI","",IF($T27="","SIN DATO",IF(ABS($T27-$S27)<=0.5,"OK","REVISAR")))) | W27: =IF(OR($C27="",$N27=""),"",IF($F27="RHE",ROUND($L27-$V27,2),ROUND($L27-($S27/$N27),2))) | AB27: PROVEEDOR
A28: 25 | B28: =DATE(2026,8,8) | C28: E001-1881 | D28: 20358309870 | E28: CAMPING TOURS E.I.R.LTDA | F28: FACTURA | G28: 037 | H28: =IF($G28="","",IFERROR(INDEX(Catalogo_Etiquetas,MATCH($G28,Catalogo_Codigos,0)),"CODIGO NO VALIDO")) | I28: USD | J28: 247.42 | K28: 44.53 | L28: =IF($C28="","",$J28+$K28) | M28: 639 | N28: =IF($C28="","",IF($I28="PEN",1,IFERROR(IF(_xlfn.XLOOKUP($B28,TC_Fechas,TC_Venta_Rango,"",-1)="","",_xlfn.XLOOKUP($B28,TC_Fechas,TC_Venta_Rango,"",-1)),""))) | O28: =IF(OR($C28="",$N28=""),"",ROUND($J28*$N28,2)+ROUND($K28*$N28,2)) | P28: =IF($G28="","",IFERROR(INDEX(Catalogo_Tasas,MATCH($G28,Catalogo_Codigos,0)),"")) | Q28: =IF($G28="","",IFERROR(INDEX(Catalogo_Umbrales,MATCH($G28,Catalogo_Codigos,0)),"")) | R28: =IF(OR($C28="",$P28="",$O28=""),"",IF($F28<>"FACTURA","NO",IF(AND($P28>0,$O28>$Q28),"SI","NO"))) | S28: =IF($R28="SI",ROUND($O28*$P28,2),IF($C28="","",0)) | T28: 118.8 | U28: =IF($C28="","",IF($R28<>"SI","",IF($T28="","SIN DATO",IF(ABS($T28-$S28)<=0.5,"OK","REVISAR")))) | W28: =IF(OR($C28="",$N28=""),"",IF($F28="RHE",ROUND($L28-$V28,2),ROUND($L28-($S28/$N28),2))) | AB28: PROVEEDOR
A29: 26 | B29: =DATE(2026,8,18) | C29: F078-00047775 | D29: 20505670443 | E29: NESSUS HOTELES PERU S.A. (Casa Andina Select Arequipa) | F29: FACTURA | G29: N/A | H29: =IF($G29="","",IFERROR(INDEX(Catalogo_Etiquetas,MATCH($G29,Catalogo_Codigos,0)),"CODIGO NO VALIDO")) | I29: USD | J29: 274 | K29: 0 | L29: =IF($C29="","",$J29+$K29) | M29: 639 | N29: =IF($C29="","",IF($I29="PEN",1,IFERROR(IF(_xlfn.XLOOKUP($B29,TC_Fechas,TC_Venta_Rango,"",-1)="","",_xlfn.XLOOKUP($B29,TC_Fechas,TC_Venta_Rango,"",-1)),""))) | O29: =IF(OR($C29="",$N29=""),"",ROUND($J29*$N29,2)+ROUND($K29*$N29,2)) | P29: =IF($G29="","",IFERROR(INDEX(Catalogo_Tasas,MATCH($G29,Catalogo_Codigos,0)),"")) | Q29: =IF($G29="","",IFERROR(INDEX(Catalogo_Umbrales,MATCH($G29,Catalogo_Codigos,0)),"")) | R29: =IF(OR($C29="",$P29="",$O29=""),"",IF($F29<>"FACTURA","NO",IF(AND($P29>0,$O29>$Q29),"SI","NO"))) | S29: =IF($R29="SI",ROUND($O29*$P29,2),IF($C29="","",0)) | U29: =IF($C29="","",IF($R29<>"SI","",IF($T29="","SIN DATO",IF(ABS($T29-$S29)<=0.5,"OK","REVISAR")))) | W29: =IF(OR($C29="",$N29=""),"",IF($F29="RHE",ROUND($L29-$V29,2),ROUND($L29-($S29/$N29),2))) | AB29: PROVEEDOR
A30: 27 | B30: =DATE(2026,8,6) | C30: E001-327 | D30: 20603668406 | E30: LUXURY ADVENTURE CUSCO PERU E.I.R.L. | F30: FACTURA | G30: N/A | H30: =IF($G30="","",IFERROR(INDEX(Catalogo_Etiquetas,MATCH($G30,Catalogo_Codigos,0)),"CODIGO NO VALIDO")) | I30: USD | J30: 88.98 | K30: 16.02 | L30: =IF($C30="","",$J30+$K30) | M30: 639 | N30: =IF($C30="","",IF($I30="PEN",1,IFERROR(IF(_xlfn.XLOOKUP($B30,TC_Fechas,TC_Venta_Rango,"",-1)="","",_xlfn.XLOOKUP($B30,TC_Fechas,TC_Venta_Rango,"",-1)),""))) | O30: =IF(OR($C30="",$N30=""),"",ROUND($J30*$N30,2)+ROUND($K30*$N30,2)) | P30: =IF($G30="","",IFERROR(INDEX(Catalogo_Tasas,MATCH($G30,Catalogo_Codigos,0)),"")) | Q30: =IF($G30="","",IFERROR(INDEX(Catalogo_Umbrales,MATCH($G30,Catalogo_Codigos,0)),"")) | R30: =IF(OR($C30="",$P30="",$O30=""),"",IF($F30<>"FACTURA","NO",IF(AND($P30>0,$O30>$Q30),"SI","NO"))) | S30: =IF($R30="SI",ROUND($O30*$P30,2),IF($C30="","",0)) | U30: =IF($C30="","",IF($R30<>"SI","",IF($T30="","SIN DATO",IF(ABS($T30-$S30)<=0.5,"OK","REVISAR")))) | W30: =IF(OR($C30="",$N30=""),"",IF($F30="RHE",ROUND($L30-$V30,2),ROUND($L30-($S30/$N30),2))) | AB30: PROVEEDOR
A31: 28 | B31: =DATE(2026,8,6) | C31: E001-332 | D31: 20603668406 | E31: LUXURY ADVENTURE CUSCO PERU E.I.R.L. | F31: FACTURA | G31: N/A | H31: =IF($G31="","",IFERROR(INDEX(Catalogo_Etiquetas,MATCH($G31,Catalogo_Codigos,0)),"CODIGO NO VALIDO")) | I31: USD | J31: 103.81 | K31: 18.69 | L31: =IF($C31="","",$J31+$K31) | M31: 639 | N31: =IF($C31="","",IF($I31="PEN",1,IFERROR(IF(_xlfn.XLOOKUP($B31,TC_Fechas,TC_Venta_Rango,"",-1)="","",_xlfn.XLOOKUP($B31,TC_Fechas,TC_Venta_Rango,"",-1)),""))) | O31: =IF(OR($C31="",$N31=""),"",ROUND($J31*$N31,2)+ROUND($K31*$N31,2)) | P31: =IF($G31="","",IFERROR(INDEX(Catalogo_Tasas,MATCH($G31,Catalogo_Codigos,0)),"")) | Q31: =IF($G31="","",IFERROR(INDEX(Catalogo_Umbrales,MATCH($G31,Catalogo_Codigos,0)),"")) | R31: =IF(OR($C31="",$P31="",$O31=""),"",IF($F31<>"FACTURA","NO",IF(AND($P31>0,$O31>$Q31),"SI","NO"))) | S31: =IF($R31="SI",ROUND($O31*$P31,2),IF($C31="","",0)) | U31: =IF($C31="","",IF($R31<>"SI","",IF($T31="","SIN DATO",IF(ABS($T31-$S31)<=0.5,"OK","REVISAR")))) | W31: =IF(OR($C31="",$N31=""),"",IF($F31="RHE",ROUND($L31-$V31,2),ROUND($L31-($S31/$N31),2))) | AB31: PROVEEDOR
A32: 29 | B32: =DATE(2026,8,19) | C32: F011-30391 | D32: 20442088811 | E32: ALBERGUE OLLANTAYTAMBO EIRL | F32: FACTURA | G32: N/A | H32: =IF($G32="","",IFERROR(INDEX(Catalogo_Etiquetas,MATCH($G32,Catalogo_Codigos,0)),"CODIGO NO VALIDO")) | I32: USD | J32: 89.06 | K32: 16.03 | L32: =IF($C32="","",$J32+$K32) | M32: 639 | N32: =IF($C32="","",IF($I32="PEN",1,IFERROR(IF(_xlfn.XLOOKUP($B32,TC_Fechas,TC_Venta_Rango,"",-1)="","",_xlfn.XLOOKUP($B32,TC_Fechas,TC_Venta_Rango,"",-1)),""))) | O32: =IF(OR($C32="",$N32=""),"",ROUND($J32*$N32,2)+ROUND($K32*$N32,2)) | P32: =IF($G32="","",IFERROR(INDEX(Catalogo_Tasas,MATCH($G32,Catalogo_Codigos,0)),"")) | Q32: =IF($G32="","",IFERROR(INDEX(Catalogo_Umbrales,MATCH($G32,Catalogo_Codigos,0)),"")) | R32: =IF(OR($C32="",$P32="",$O32=""),"",IF($F32<>"FACTURA","NO",IF(AND($P32>0,$O32>$Q32),"SI","NO"))) | S32: =IF($R32="SI",ROUND($O32*$P32,2),IF($C32="","",0)) | U32: =IF($C32="","",IF($R32<>"SI","",IF($T32="","SIN DATO",IF(ABS($T32-$S32)<=0.5,"OK","REVISAR")))) | W32: =IF(OR($C32="",$N32=""),"",IF($F32="RHE",ROUND($L32-$V32,2),ROUND($L32-($S32/$N32),2))) | AB32: PROVEEDOR
A33: 30 | B33: =DATE(2026,8,5) | C33: E001- 468 | D33: 10448269201 | E33: ANCAYPURO TORRES JOSE LUIS | F33: RHE | G33: N/A | H33: =IF($G33="","",IFERROR(INDEX(Catalogo_Etiquetas,MATCH($G33,Catalogo_Codigos,0)),"CODIGO NO VALIDO")) | I33: PEN | J33: 40 | K33: 0 | L33: =IF($C33="","",$J33+$K33) | M33: 632 | N33: =IF($C33="","",IF($I33="PEN",1,IFERROR(IF(_xlfn.XLOOKUP($B33,TC_Fechas,TC_Venta_Rango,"",-1)="","",_xlfn.XLOOKUP($B33,TC_Fechas,TC_Venta_Rango,"",-1)),""))) | O33: =IF(OR($C33="",$N33=""),"",ROUND($J33*$N33,2)+ROUND($K33*$N33,2)) | P33: =IF($G33="","",IFERROR(INDEX(Catalogo_Tasas,MATCH($G33,Catalogo_Codigos,0)),"")) | Q33: =IF($G33="","",IFERROR(INDEX(Catalogo_Umbrales,MATCH($G33,Catalogo_Codigos,0)),"")) | R33: =IF(OR($C33="",$P33="",$O33=""),"",IF($F33<>"FACTURA","NO",IF(AND($P33>0,$O33>$Q33),"SI","NO"))) | S33: =IF($R33="SI",ROUND($O33*$P33,2),IF($C33="","",0)) | U33: =IF($C33="","",IF($R33<>"SI","",IF($T33="","SIN DATO",IF(ABS($T33-$S33)<=0.5,"OK","REVISAR")))) | W33: =IF(OR($C33="",$N33=""),"",IF($F33="RHE",ROUND($L33-$V33,2),ROUND($L33-($S33/$N33),2))) | AB33: PROVEEDOR
A34: 31 | B34: =DATE(2026,8,10) | C34: E001- 174 | D34: 10408744151 | E34: BEOUTIS BAZAN URSULA CATHERINE | F34: RHE | G34: N/A | H34: =IF($G34="","",IFERROR(INDEX(Catalogo_Etiquetas,MATCH($G34,Catalogo_Codigos,0)),"CODIGO NO VALIDO")) | I34: PEN | J34: 1025 | K34: 0 | L34: =IF($C34="","",$J34+$K34) | M34: 632 | N34: =IF($C34="","",IF($I34="PEN",1,IFERROR(IF(_xlfn.XLOOKUP($B34,TC_Fechas,TC_Venta_Rango,"",-1)="","",_xlfn.XLOOKUP($B34,TC_Fechas,TC_Venta_Rango,"",-1)),""))) | O34: =IF(OR($C34="",$N34=""),"",ROUND($J34*$N34,2)+ROUND($K34*$N34,2)) | P34: =IF($G34="","",IFERROR(INDEX(Catalogo_Tasas,MATCH($G34,Catalogo_Codigos,0)),"")) | Q34: =IF($G34="","",IFERROR(INDEX(Catalogo_Umbrales,MATCH($G34,Catalogo_Codigos,0)),"")) | R34: =IF(OR($C34="",$P34="",$O34=""),"",IF($F34<>"FACTURA","NO",IF(AND($P34>0,$O34>$Q34),"SI","NO"))) | S34: =IF($R34="SI",ROUND($O34*$P34,2),IF($C34="","",0)) | U34: =IF($C34="","",IF($R34<>"SI","",IF($T34="","SIN DATO",IF(ABS($T34-$S34)<=0.5,"OK","REVISAR")))) | W34: =IF(OR($C34="",$N34=""),"",IF($F34="RHE",ROUND($L34-$V34,2),ROUND($L34-($S34/$N34),2))) | AB34: ADMINISTRATIVO
A35: 32 | B35: =DATE(2026,8,18) | C35: E001- 546 | D35: 10408222490 | E35: CARRASCO ALEGRE ROLLY VICTOR | F35: RHE | G35: N/A | H35: =IF($G35="","",IFERROR(INDEX(Catalogo_Etiquetas,MATCH($G35,Catalogo_Codigos,0)),"CODIGO NO VALIDO")) | I35: USD | J35: 60 | K35: 0 | L35: =IF($C35="","",$J35+$K35) | M35: 632 | N35: =IF($C35="","",IF($I35="PEN",1,IFERROR(IF(_xlfn.XLOOKUP($B35,TC_Fechas,TC_Venta_Rango,"",-1)="","",_xlfn.XLOOKUP($B35,TC_Fechas,TC_Venta_Rango,"",-1)),""))) | O35: =IF(OR($C35="",$N35=""),"",ROUND($J35*$N35,2)+ROUND($K35*$N35,2)) | P35: =IF($G35="","",IFERROR(INDEX(Catalogo_Tasas,MATCH($G35,Catalogo_Codigos,0)),"")) | Q35: =IF($G35="","",IFERROR(INDEX(Catalogo_Umbrales,MATCH($G35,Catalogo_Codigos,0)),"")) | R35: =IF(OR($C35="",$P35="",$O35=""),"",IF($F35<>"FACTURA","NO",IF(AND($P35>0,$O35>$Q35),"SI","NO"))) | S35: =IF($R35="SI",ROUND($O35*$P35,2),IF($C35="","",0)) | U35: =IF($C35="","",IF($R35<>"SI","",IF($T35="","SIN DATO",IF(ABS($T35-$S35)<=0.5,"OK","REVISAR")))) | W35: =IF(OR($C35="",$N35=""),"",IF($F35="RHE",ROUND($L35-$V35,2),ROUND($L35-($S35/$N35),2))) | AB35: PROVEEDOR
A36: 33 | B36: =DATE(2026,8,14) | C36: FA02-00001856 | D36: 20527992525 | E36: CUSCO RESTAURANTS S.A.C. | F36: FACTURA | G36: N/A | H36: =IF($G36="","",IFERROR(INDEX(Catalogo_Etiquetas,MATCH($G36,Catalogo_Codigos,0)),"CODIGO NO VALIDO")) | I36: USD | J36: 54.69 | K36: 9.84 | L36: =IF($C36="","",$J36+$K36) | M36: 639 | N36: =IF($C36="","",IF($I36="PEN",1,IFERROR(IF(_xlfn.XLOOKUP($B36,TC_Fechas,TC_Venta_Rango,"",-1)="","",_xlfn.XLOOKUP($B36,TC_Fechas,TC_Venta_Rango,"",-1)),""))) | O36: =IF(OR($C36="",$N36=""),"",ROUND($J36*$N36,2)+ROUND($K36*$N36,2)) | P36: =IF($G36="","",IFERROR(INDEX(Catalogo_Tasas,MATCH($G36,Catalogo_Codigos,0)),"")) | Q36: =IF($G36="","",IFERROR(INDEX(Catalogo_Umbrales,MATCH($G36,Catalogo_Codigos,0)),"")) | R36: =IF(OR($C36="",$P36="",$O36=""),"",IF($F36<>"FACTURA","NO",IF(AND($P36>0,$O36>$Q36),"SI","NO"))) | S36: =IF($R36="SI",ROUND($O36*$P36,2),IF($C36="","",0)) | U36: =IF($C36="","",IF($R36<>"SI","",IF($T36="","SIN DATO",IF(ABS($T36-$S36)<=0.5,"OK","REVISAR")))) | W36: =IF(OR($C36="",$N36=""),"",IF($F36="RHE",ROUND($L36-$V36,2),ROUND($L36-($S36/$N36),2))) | AB36: PROVEEDOR
A37: 34 | B37: =DATE(2026,8,14) | C37: F005-019033 | D37: 20252796623 | E37: GRESCO S.A.C. | F37: FACTURA | G37: N/A | H37: =IF($G37="","",IFERROR(INDEX(Catalogo_Etiquetas,MATCH($G37,Catalogo_Codigos,0)),"CODIGO NO VALIDO")) | I37: PEN | J37: 630.56 | K37: 113.5 | L37: =IF($C37="","",$J37+$K37) | M37: 639 | N37: =IF($C37="","",IF($I37="PEN",1,IFERROR(IF(_xlfn.XLOOKUP($B37,TC_Fechas,TC_Venta_Rango,"",-1)="","",_xlfn.XLOOKUP($B37,TC_Fechas,TC_Venta_Rango,"",-1)),""))) | O37: =IF(OR($C37="",$N37=""),"",ROUND($J37*$N37,2)+ROUND($K37*$N37,2)) | P37: =IF($G37="","",IFERROR(INDEX(Catalogo_Tasas,MATCH($G37,Catalogo_Codigos,0)),"")) | Q37: =IF($G37="","",IFERROR(INDEX(Catalogo_Umbrales,MATCH($G37,Catalogo_Codigos,0)),"")) | R37: =IF(OR($C37="",$P37="",$O37=""),"",IF($F37<>"FACTURA","NO",IF(AND($P37>0,$O37>$Q37),"SI","NO"))) | S37: =IF($R37="SI",ROUND($O37*$P37,2),IF($C37="","",0)) | U37: =IF($C37="","",IF($R37<>"SI","",IF($T37="","SIN DATO",IF(ABS($T37-$S37)<=0.5,"OK","REVISAR")))) | W37: =IF(OR($C37="",$N37=""),"",IF($F37="RHE",ROUND($L37-$V37,2),ROUND($L37-($S37/$N37),2))) | AB37: PROVEEDOR
A38: 35 | B38: =DATE(2026,8,13) | C38: F008-00035633 | D38: 20536047906 | E38: HOTELERIA PERUANA S.A.C. (TIERRA VIVA HOTELS) | F38: FACTURA | G38: N/A | H38: =IF($G38="","",IFERROR(INDEX(Catalogo_Etiquetas,MATCH($G38,Catalogo_Codigos,0)),"CODIGO NO VALIDO")) | I38: USD | J38: 138.18 | K38: 0 | L38: =IF($C38="","",$J38+$K38) | M38: 639 | N38: =IF($C38="","",IF($I38="PEN",1,IFERROR(IF(_xlfn.XLOOKUP($B38,TC_Fechas,TC_Venta_Rango,"",-1)="","",_xlfn.XLOOKUP($B38,TC_Fechas,TC_Venta_Rango,"",-1)),""))) | O38: =IF(OR($C38="",$N38=""),"",ROUND($J38*$N38,2)+ROUND($K38*$N38,2)) | P38: =IF($G38="","",IFERROR(INDEX(Catalogo_Tasas,MATCH($G38,Catalogo_Codigos,0)),"")) | Q38: =IF($G38="","",IFERROR(INDEX(Catalogo_Umbrales,MATCH($G38,Catalogo_Codigos,0)),"")) | R38: =IF(OR($C38="",$P38="",$O38=""),"",IF($F38<>"FACTURA","NO",IF(AND($P38>0,$O38>$Q38),"SI","NO"))) | S38: =IF($R38="SI",ROUND($O38*$P38,2),IF($C38="","",0)) | U38: =IF($C38="","",IF($R38<>"SI","",IF($T38="","SIN DATO",IF(ABS($T38-$S38)<=0.5,"OK","REVISAR")))) | W38: =IF(OR($C38="",$N38=""),"",IF($F38="RHE",ROUND($L38-$V38,2),ROUND($L38-($S38/$N38),2))) | AB38: PROVEEDOR
A39: 36 | B39: =DATE(2026,8,17) | C39: F006-00003185 | D39: 20610235736 | E39: HOTELES LA HACIENDA S.A.C. | F39: FACTURA | G39: N/A | H39: =IF($G39="","",IFERROR(INDEX(Catalogo_Etiquetas,MATCH($G39,Catalogo_Codigos,0)),"CODIGO NO VALIDO")) | I39: USD | J39: 318.58 | K39: 0 | L39: =IF($C39="","",$J39+$K39) | M39: 639 | N39: =IF($C39="","",IF($I39="PEN",1,IFERROR(IF(_xlfn.XLOOKUP($B39,TC_Fechas,TC_Venta_Rango,"",-1)="","",_xlfn.XLOOKUP($B39,TC_Fechas,TC_Venta_Rango,"",-1)),""))) | O39: =IF(OR($C39="",$N39=""),"",ROUND($J39*$N39,2)+ROUND($K39*$N39,2)) | P39: =IF($G39="","",IFERROR(INDEX(Catalogo_Tasas,MATCH($G39,Catalogo_Codigos,0)),"")) | Q39: =IF($G39="","",IFERROR(INDEX(Catalogo_Umbrales,MATCH($G39,Catalogo_Codigos,0)),"")) | R39: =IF(OR($C39="",$P39="",$O39=""),"",IF($F39<>"FACTURA","NO",IF(AND($P39>0,$O39>$Q39),"SI","NO"))) | S39: =IF($R39="SI",ROUND($O39*$P39,2),IF($C39="","",0)) | U39: =IF($C39="","",IF($R39<>"SI","",IF($T39="","SIN DATO",IF(ABS($T39-$S39)<=0.5,"OK","REVISAR")))) | W39: =IF(OR($C39="",$N39=""),"",IF($F39="RHE",ROUND($L39-$V39,2),ROUND($L39-($S39/$N39),2))) | AB39: PROVEEDOR
A40: 37 | B40: =DATE(2026,8,18) | C40: F302-00029273 | D40: 20114803228 | E40: INVERSIONES NACIONALES DE TURISMO S.A. (Palacio del Inka Hotel) | F40: FACTURA | G40: N/A | H40: =IF($G40="","",IFERROR(INDEX(Catalogo_Etiquetas,MATCH($G40,Catalogo_Codigos,0)),"CODIGO NO VALIDO")) | I40: USD | J40: 1102 | K40: 0 | L40: =IF($C40="","",$J40+$K40) | M40: 639 | N40: =IF($C40="","",IF($I40="PEN",1,IFERROR(IF(_xlfn.XLOOKUP($B40,TC_Fechas,TC_Venta_Rango,"",-1)="","",_xlfn.XLOOKUP($B40,TC_Fechas,TC_Venta_Rango,"",-1)),""))) | O40: =IF(OR($C40="",$N40=""),"",ROUND($J40*$N40,2)+ROUND($K40*$N40,2)) | P40: =IF($G40="","",IFERROR(INDEX(Catalogo_Tasas,MATCH($G40,Catalogo_Codigos,0)),"")) | Q40: =IF($G40="","",IFERROR(INDEX(Catalogo_Umbrales,MATCH($G40,Catalogo_Codigos,0)),"")) | R40: =IF(OR($C40="",$P40="",$O40=""),"",IF($F40<>"FACTURA","NO",IF(AND($P40>0,$O40>$Q40),"SI","NO"))) | S40: =IF($R40="SI",ROUND($O40*$P40,2),IF($C40="","",0)) | U40: =IF($C40="","",IF($R40<>"SI","",IF($T40="","SIN DATO",IF(ABS($T40-$S40)<=0.5,"OK","REVISAR")))) | W40: =IF(OR($C40="",$N40=""),"",IF($F40="RHE",ROUND($L40-$V40,2),ROUND($L40-($S40/$N40),2))) | AB40: PROVEEDOR
A41: 38 | B41: =DATE(2026,8,14) | C41: E001-2662 | D41: 20602860958 | E41: J & R TURISMO E.I.R.L. | F41: FACTURA | G41: 026 | H41: =IF($G41="","",IFERROR(INDEX(Catalogo_Etiquetas,MATCH($G41,Catalogo_Codigos,0)),"CODIGO NO VALIDO")) | I41: USD | J41: 300 | K41: 54 | L41: =IF($C41="","",$J41+$K41) | M41: 631 | N41: =IF($C41="","",IF($I41="PEN",1,IFERROR(IF(_xlfn.XLOOKUP($B41,TC_Fechas,TC_Venta_Rango,"",-1)="","",_xlfn.XLOOKUP($B41,TC_Fechas,TC_Venta_Rango,"",-1)),""))) | O41: =IF(OR($C41="",$N41=""),"",ROUND($J41*$N41,2)+ROUND($K41*$N41,2)) | P41: =IF($G41="","",IFERROR(INDEX(Catalogo_Tasas,MATCH($G41,Catalogo_Codigos,0)),"")) | Q41: =IF($G41="","",IFERROR(INDEX(Catalogo_Umbrales,MATCH($G41,Catalogo_Codigos,0)),"")) | R41: =IF(OR($C41="",$P41="",$O41=""),"",IF($F41<>"FACTURA","NO",IF(AND($P41>0,$O41>$Q41),"SI","NO"))) | S41: =IF($R41="SI",ROUND($O41*$P41,2),IF($C41="","",0)) | T41: 119.33 | U41: =IF($C41="","",IF($R41<>"SI","",IF($T41="","SIN DATO",IF(ABS($T41-$S41)<=0.5,"OK","REVISAR")))) | W41: =IF(OR($C41="",$N41=""),"",IF($F41="RHE",ROUND($L41-$V41,2),ROUND($L41-($S41/$N41),2))) | AB41: PROVEEDOR
A42: 39 | B42: =DATE(2026,8,1) | C42: E001-2237 | D42: 20525581315 | E42: MANCORA TRAVEL S.A.C. | F42: FACTURA | G42: 026 | H42: =IF($G42="","",IFERROR(INDEX(Catalogo_Etiquetas,MATCH($G42,Catalogo_Codigos,0)),"CODIGO NO VALIDO")) | I42: PEN | J42: 949.15 | K42: 170.85 | L42: =IF($C42="","",$J42+$K42) | M42: 631 | N42: =IF($C42="","",IF($I42="PEN",1,IFERROR(IF(_xlfn.XLOOKUP($B42,TC_Fechas,TC_Venta_Rango,"",-1)="","",_xlfn.XLOOKUP($B42,TC_Fechas,TC_Venta_Rango,"",-1)),""))) | O42: =IF(OR($C42="",$N42=""),"",ROUND($J42*$N42,2)+ROUND($K42*$N42,2)) | P42: =IF($G42="","",IFERROR(INDEX(Catalogo_Tasas,MATCH($G42,Catalogo_Codigos,0)),"")) | Q42: =IF($G42="","",IFERROR(INDEX(Catalogo_Umbrales,MATCH($G42,Catalogo_Codigos,0)),"")) | R42: =IF(OR($C42="",$P42="",$O42=""),"",IF($F42<>"FACTURA","NO",IF(AND($P42>0,$O42>$Q42),"SI","NO"))) | S42: =IF($R42="SI",ROUND($O42*$P42,2),IF($C42="","",0)) | T42: 112 | U42: =IF($C42="","",IF($R42<>"SI","",IF($T42="","SIN DATO",IF(ABS($T42-$S42)<=0.5,"OK","REVISAR")))) | W42: =IF(OR($C42="",$N42=""),"",IF($F42="RHE",ROUND($L42-$V42,2),ROUND($L42-($S42/$N42),2))) | AB42: PROVEEDOR
A43: 40 | B43: =DATE(2026,8,13) | C43: FL05-00036295 | D43: 20309001037 | E43: PALMA REAL S.A.C. (INKATERRA) | F43: FACTURA | G43: N/A | H43: =IF($G43="","",IFERROR(INDEX(Catalogo_Etiquetas,MATCH($G43,Catalogo_Codigos,0)),"CODIGO NO VALIDO")) | I43: USD | J43: 1684.76 | K43: 0 | L43: =IF($C43="","",$J43+$K43) | M43: 639 | N43: =IF($C43="","",IF($I43="PEN",1,IFERROR(IF(_xlfn.XLOOKUP($B43,TC_Fechas,TC_Venta_Rango,"",-1)="","",_xlfn.XLOOKUP($B43,TC_Fechas,TC_Venta_Rango,"",-1)),""))) | O43: =IF(OR($C43="",$N43=""),"",ROUND($J43*$N43,2)+ROUND($K43*$N43,2)) | P43: =IF($G43="","",IFERROR(INDEX(Catalogo_Tasas,MATCH($G43,Catalogo_Codigos,0)),"")) | Q43: =IF($G43="","",IFERROR(INDEX(Catalogo_Umbrales,MATCH($G43,Catalogo_Codigos,0)),"")) | R43: =IF(OR($C43="",$P43="",$O43=""),"",IF($F43<>"FACTURA","NO",IF(AND($P43>0,$O43>$Q43),"SI","NO"))) | S43: =IF($R43="SI",ROUND($O43*$P43,2),IF($C43="","",0)) | U43: =IF($C43="","",IF($R43<>"SI","",IF($T43="","SIN DATO",IF(ABS($T43-$S43)<=0.5,"OK","REVISAR")))) | W43: =IF(OR($C43="",$N43=""),"",IF($F43="RHE",ROUND($L43-$V43,2),ROUND($L43-($S43/$N43),2))) | AB43: PROVEEDOR
A44: 41 | B44: =DATE(2026,8,18) | C44: F078-00006828 | D44: 20510931514 | E44: PERUVIAN TOURS AGENCY SOCIEDAD ANONIMA CERRADA (Hotel Colca - Aranwa) | F44: FACTURA | G44: N/A | H44: =IF($G44="","",IFERROR(INDEX(Catalogo_Etiquetas,MATCH($G44,Catalogo_Codigos,0)),"CODIGO NO VALIDO")) | I44: USD | J44: 360 | K44: 0 | L44: =IF($C44="","",$J44+$K44) | M44: 639 | N44: =IF($C44="","",IF($I44="PEN",1,IFERROR(IF(_xlfn.XLOOKUP($B44,TC_Fechas,TC_Venta_Rango,"",-1)="","",_xlfn.XLOOKUP($B44,TC_Fechas,TC_Venta_Rango,"",-1)),""))) | O44: =IF(OR($C44="",$N44=""),"",ROUND($J44*$N44,2)+ROUND($K44*$N44,2)) | P44: =IF($G44="","",IFERROR(INDEX(Catalogo_Tasas,MATCH($G44,Catalogo_Codigos,0)),"")) | Q44: =IF($G44="","",IFERROR(INDEX(Catalogo_Umbrales,MATCH($G44,Catalogo_Codigos,0)),"")) | R44: =IF(OR($C44="",$P44="",$O44=""),"",IF($F44<>"FACTURA","NO",IF(AND($P44>0,$O44>$Q44),"SI","NO"))) | S44: =IF($R44="SI",ROUND($O44*$P44,2),IF($C44="","",0)) | U44: =IF($C44="","",IF($R44<>"SI","",IF($T44="","SIN DATO",IF(ABS($T44-$S44)<=0.5,"OK","REVISAR")))) | W44: =IF(OR($C44="",$N44=""),"",IF($F44="RHE",ROUND($L44-$V44,2),ROUND($L44-($S44/$N44),2))) | AB44: PROVEEDOR
A45: 42 | B45: =DATE(2026,8,17) | C45: E001- 505 | D45: 10422800102 | E45: SARMIENTO LOPEZ LUIS RONALD | F45: RHE | G45: N/A | H45: =IF($G45="","",IFERROR(INDEX(Catalogo_Etiquetas,MATCH($G45,Catalogo_Codigos,0)),"CODIGO NO VALIDO")) | I45: USD | J45: 70 | K45: 0 | L45: =IF($C45="","",$J45+$K45) | M45: 632 | N45: =IF($C45="","",IF($I45="PEN",1,IFERROR(IF(_xlfn.XLOOKUP($B45,TC_Fechas,TC_Venta_Rango,"",-1)="","",_xlfn.XLOOKUP($B45,TC_Fechas,TC_Venta_Rango,"",-1)),""))) | O45: =IF(OR($C45="",$N45=""),"",ROUND($J45*$N45,2)+ROUND($K45*$N45,2)) | P45: =IF($G45="","",IFERROR(INDEX(Catalogo_Tasas,MATCH($G45,Catalogo_Codigos,0)),"")) | Q45: =IF($G45="","",IFERROR(INDEX(Catalogo_Umbrales,MATCH($G45,Catalogo_Codigos,0)),"")) | R45: =IF(OR($C45="",$P45="",$O45=""),"",IF($F45<>"FACTURA","NO",IF(AND($P45>0,$O45>$Q45),"SI","NO"))) | S45: =IF($R45="SI",ROUND($O45*$P45,2),IF($C45="","",0)) | U45: =IF($C45="","",IF($R45<>"SI","",IF($T45="","SIN DATO",IF(ABS($T45-$S45)<=0.5,"OK","REVISAR")))) | V45: 5.6 | W45: =IF(OR($C45="",$N45=""),"",IF($F45="RHE",ROUND($L45-$V45,2),ROUND($L45-($S45/$N45),2))) | AB45: PROVEEDOR
A46: 43 | B46: =DATE(2026,8,18) | C46: F002-813 | D46: 20602052703 | E46: TURISMO Y CONSERVACION SAC (Amazon Journeys) | F46: FACTURA | G46: N/A | H46: =IF($G46="","",IFERROR(INDEX(Catalogo_Etiquetas,MATCH($G46,Catalogo_Codigos,0)),"CODIGO NO VALIDO")) | I46: USD | J46: 2100 | K46: 0 | L46: =IF($C46="","",$J46+$K46) | M46: 639 | N46: =IF($C46="","",IF($I46="PEN",1,IFERROR(IF(_xlfn.XLOOKUP($B46,TC_Fechas,TC_Venta_Rango,"",-1)="","",_xlfn.XLOOKUP($B46,TC_Fechas,TC_Venta_Rango,"",-1)),""))) | O46: =IF(OR($C46="",$N46=""),"",ROUND($J46*$N46,2)+ROUND($K46*$N46,2)) | P46: =IF($G46="","",IFERROR(INDEX(Catalogo_Tasas,MATCH($G46,Catalogo_Codigos,0)),"")) | Q46: =IF($G46="","",IFERROR(INDEX(Catalogo_Umbrales,MATCH($G46,Catalogo_Codigos,0)),"")) | R46: =IF(OR($C46="",$P46="",$O46=""),"",IF($F46<>"FACTURA","NO",IF(AND($P46>0,$O46>$Q46),"SI","NO"))) | S46: =IF($R46="SI",ROUND($O46*$P46,2),IF($C46="","",0)) | U46: =IF($C46="","",IF($R46<>"SI","",IF($T46="","SIN DATO",IF(ABS($T46-$S46)<=0.5,"OK","REVISAR")))) | W46: =IF(OR($C46="",$N46=""),"",IF($F46="RHE",ROUND($L46-$V46,2),ROUND($L46-($S46/$N46),2))) | AB46: PROVEEDOR
A47: 44 | B47: =DATE(2026,8,4) | C47: E001 742 | D47: 10214605606 | E47: CATACORA RAMIREZ PAUL FRED | F47: RHE | G47: N/A | H47: =IF($G47="","",IFERROR(INDEX(Catalogo_Etiquetas,MATCH($G47,Catalogo_Codigos,0)),"CODIGO NO VALIDO")) | I47: USD | J47: 400 | K47: 0 | L47: =IF($C47="","",$J47+$K47) | M47: 632 | N47: =IF($C47="","",IF($I47="PEN",1,IFERROR(IF(_xlfn.XLOOKUP($B47,TC_Fechas,TC_Venta_Rango,"",-1)="","",_xlfn.XLOOKUP($B47,TC_Fechas,TC_Venta_Rango,"",-1)),""))) | O47: =IF(OR($C47="",$N47=""),"",ROUND($J47*$N47,2)+ROUND($K47*$N47,2)) | P47: =IF($G47="","",IFERROR(INDEX(Catalogo_Tasas,MATCH($G47,Catalogo_Codigos,0)),"")) | Q47: =IF($G47="","",IFERROR(INDEX(Catalogo_Umbrales,MATCH($G47,Catalogo_Codigos,0)),"")) | R47: =IF(OR($C47="",$P47="",$O47=""),"",IF($F47<>"FACTURA","NO",IF(AND($P47>0,$O47>$Q47),"SI","NO"))) | S47: =IF($R47="SI",ROUND($O47*$P47,2),IF($C47="","",0)) | U47: =IF($C47="","",IF($R47<>"SI","",IF($T47="","SIN DATO",IF(ABS($T47-$S47)<=0.5,"OK","REVISAR")))) | W47: =IF(OR($C47="",$N47=""),"",IF($F47="RHE",ROUND($L47-$V47,2),ROUND($L47-($S47/$N47),2))) | AB47: PROVEEDOR
A48: 45 | B48: =DATE(2026,8,14) | C48: F019-00032586 | D48: 20505670443 | E48: NESSUS HOTELES PERU S.A. (CASA ANDINA) | F48: FACTURA | G48: N/A | H48: =IF($G48="","",IFERROR(INDEX(Catalogo_Etiquetas,MATCH($G48,Catalogo_Codigos,0)),"CODIGO NO VALIDO")) | I48: USD | J48: 677.02 | K48: 0 | L48: =IF($C48="","",$J48+$K48) | M48: 639 | N48: =IF($C48="","",IF($I48="PEN",1,IFERROR(IF(_xlfn.XLOOKUP($B48,TC_Fechas,TC_Venta_Rango,"",-1)="","",_xlfn.XLOOKUP($B48,TC_Fechas,TC_Venta_Rango,"",-1)),""))) | O48: =IF(OR($C48="",$N48=""),"",ROUND($J48*$N48,2)+ROUND($K48*$N48,2)) | P48: =IF($G48="","",IFERROR(INDEX(Catalogo_Tasas,MATCH($G48,Catalogo_Codigos,0)),"")) | Q48: =IF($G48="","",IFERROR(INDEX(Catalogo_Umbrales,MATCH($G48,Catalogo_Codigos,0)),"")) | R48: =IF(OR($C48="",$P48="",$O48=""),"",IF($F48<>"FACTURA","NO",IF(AND($P48>0,$O48>$Q48),"SI","NO"))) | S48: =IF($R48="SI",ROUND($O48*$P48,2),IF($C48="","",0)) | U48: =IF($C48="","",IF($R48<>"SI","",IF($T48="","SIN DATO",IF(ABS($T48-$S48)<=0.5,"OK","REVISAR")))) | W48: =IF(OR($C48="",$N48=""),"",IF($F48="RHE",ROUND($L48-$V48,2),ROUND($L48-($S48/$N48),2))) | AB48: PROVEEDOR
A49: 46 | B49: =DATE(2026,8,6) | C49: E001-328 | D49: 20603668406 | E49: LUXURY ADVENTURE CUSCO PERU E.I.R.L. | F49: FACTURA | G49: N/A | H49: =IF($G49="","",IFERROR(INDEX(Catalogo_Etiquetas,MATCH($G49,Catalogo_Codigos,0)),"CODIGO NO VALIDO")) | I49: USD | J49: 133.48 | K49: 24.03 | L49: =IF($C49="","",$J49+$K49) | M49: 639 | N49: =IF($C49="","",IF($I49="PEN",1,IFERROR(IF(_xlfn.XLOOKUP($B49,TC_Fechas,TC_Venta_Rango,"",-1)="","",_xlfn.XLOOKUP($B49,TC_Fechas,TC_Venta_Rango,"",-1)),""))) | O49: =IF(OR($C49="",$N49=""),"",ROUND($J49*$N49,2)+ROUND($K49*$N49,2)) | P49: =IF($G49="","",IFERROR(INDEX(Catalogo_Tasas,MATCH($G49,Catalogo_Codigos,0)),"")) | Q49: =IF($G49="","",IFERROR(INDEX(Catalogo_Umbrales,MATCH($G49,Catalogo_Codigos,0)),"")) | R49: =IF(OR($C49="",$P49="",$O49=""),"",IF($F49<>"FACTURA","NO",IF(AND($P49>0,$O49>$Q49),"SI","NO"))) | S49: =IF($R49="SI",ROUND($O49*$P49,2),IF($C49="","",0)) | U49: =IF($C49="","",IF($R49<>"SI","",IF($T49="","SIN DATO",IF(ABS($T49-$S49)<=0.5,"OK","REVISAR")))) | W49: =IF(OR($C49="",$N49=""),"",IF($F49="RHE",ROUND($L49-$V49,2),ROUND($L49-($S49/$N49),2))) | AB49: PROVEEDOR
A50: 47 | B50: =DATE(2026,8,6) | C50: E001-333 | D50: 20603668406 | E50: LUXURY ADVENTURE CUSCO PERU E.I.R.L. | F50: FACTURA | G50: N/A | H50: =IF($G50="","",IFERROR(INDEX(Catalogo_Etiquetas,MATCH($G50,Catalogo_Codigos,0)),"CODIGO NO VALIDO")) | I50: USD | J50: 103.81 | K50: 18.69 | L50: =IF($C50="","",$J50+$K50) | M50: 639 | N50: =IF($C50="","",IF($I50="PEN",1,IFERROR(IF(_xlfn.XLOOKUP($B50,TC_Fechas,TC_Venta_Rango,"",-1)="","",_xlfn.XLOOKUP($B50,TC_Fechas,TC_Venta_Rango,"",-1)),""))) | O50: =IF(OR($C50="",$N50=""),"",ROUND($J50*$N50,2)+ROUND($K50*$N50,2)) | P50: =IF($G50="","",IFERROR(INDEX(Catalogo_Tasas,MATCH($G50,Catalogo_Codigos,0)),"")) | Q50: =IF($G50="","",IFERROR(INDEX(Catalogo_Umbrales,MATCH($G50,Catalogo_Codigos,0)),"")) | R50: =IF(OR($C50="",$P50="",$O50=""),"",IF($F50<>"FACTURA","NO",IF(AND($P50>0,$O50>$Q50),"SI","NO"))) | S50: =IF($R50="SI",ROUND($O50*$P50,2),IF($C50="","",0)) | U50: =IF($C50="","",IF($R50<>"SI","",IF($T50="","SIN DATO",IF(ABS($T50-$S50)<=0.5,"OK","REVISAR")))) | W50: =IF(OR($C50="",$N50=""),"",IF($F50="RHE",ROUND($L50-$V50,2),ROUND($L50-($S50/$N50),2))) | AB50: PROVEEDOR
A51: 48 | B51: =DATE(2026,8,5) | C51: E001 - 109 | D51: 10731722124 | E51: ALCAZAR GONZALES ERNESTO ANDRES | F51: RHE | G51: N/A | H51: =IF($G51="","",IFERROR(INDEX(Catalogo_Etiquetas,MATCH($G51,Catalogo_Codigos,0)),"CODIGO NO VALIDO")) | I51: PEN | J51: 1575 | K51: 0 | L51: =IF($C51="","",$J51+$K51) | M51: 632 | N51: =IF($C51="","",IF($I51="PEN",1,IFERROR(IF(_xlfn.XLOOKUP($B51,TC_Fechas,TC_Venta_Rango,"",-1)="","",_xlfn.XLOOKUP($B51,TC_Fechas,TC_Venta_Rango,"",-1)),""))) | O51: =IF(OR($C51="",$N51=""),"",ROUND($J51*$N51,2)+ROUND($K51*$N51,2)) | P51: =IF($G51="","",IFERROR(INDEX(Catalogo_Tasas,MATCH($G51,Catalogo_Codigos,0)),"")) | Q51: =IF($G51="","",IFERROR(INDEX(Catalogo_Umbrales,MATCH($G51,Catalogo_Codigos,0)),"")) | R51: =IF(OR($C51="",$P51="",$O51=""),"",IF($F51<>"FACTURA","NO",IF(AND($P51>0,$O51>$Q51),"SI","NO"))) | S51: =IF($R51="SI",ROUND($O51*$P51,2),IF($C51="","",0)) | U51: =IF($C51="","",IF($R51<>"SI","",IF($T51="","SIN DATO",IF(ABS($T51-$S51)<=0.5,"OK","REVISAR")))) | W51: =IF(OR($C51="",$N51=""),"",IF($F51="RHE",ROUND($L51-$V51,2),ROUND($L51-($S51/$N51),2))) | AB51: PROVEEDOR
A52: 49 | B52: =DATE(2026,8,7) | C52: E001-122 | D52: 10438198984 | E52: ANICAMA ZAMORA SAULO CHRIS | F52: RHE | G52: N/A | H52: =IF($G52="","",IFERROR(INDEX(Catalogo_Etiquetas,MATCH($G52,Catalogo_Codigos,0)),"CODIGO NO VALIDO")) | I52: PEN | J52: 2500 | K52: 0 | L52: =IF($C52="","",$J52+$K52) | M52: 632 | N52: =IF($C52="","",IF($I52="PEN",1,IFERROR(IF(_xlfn.XLOOKUP($B52,TC_Fechas,TC_Venta_Rango,"",-1)="","",_xlfn.XLOOKUP($B52,TC_Fechas,TC_Venta_Rango,"",-1)),""))) | O52: =IF(OR($C52="",$N52=""),"",ROUND($J52*$N52,2)+ROUND($K52*$N52,2)) | P52: =IF($G52="","",IFERROR(INDEX(Catalogo_Tasas,MATCH($G52,Catalogo_Codigos,0)),"")) | Q52: =IF($G52="","",IFERROR(INDEX(Catalogo_Umbrales,MATCH($G52,Catalogo_Codigos,0)),"")) | R52: =IF(OR($C52="",$P52="",$O52=""),"",IF($F52<>"FACTURA","NO",IF(AND($P52>0,$O52>$Q52),"SI","NO"))) | S52: =IF($R52="SI",ROUND($O52*$P52,2),IF($C52="","",0)) | U52: =IF($C52="","",IF($R52<>"SI","",IF($T52="","SIN DATO",IF(ABS($T52-$S52)<=0.5,"OK","REVISAR")))) | W52: =IF(OR($C52="",$N52=""),"",IF($F52="RHE",ROUND($L52-$V52,2),ROUND($L52-($S52/$N52),2))) | AB52: ADMINISTRATIVO
A53: 50 | B53: =DATE(2026,8,10) | C53: E001- 175 | D53: 10408744151 | E53: BEOUTIS BAZAN URSULA CATHERINE | F53: RHE | G53: N/A | H53: =IF($G53="","",IFERROR(INDEX(Catalogo_Etiquetas,MATCH($G53,Catalogo_Codigos,0)),"CODIGO NO VALIDO")) | I53: PEN | J53: 1025 | K53: 0 | L53: =IF($C53="","",$J53+$K53) | M53: 632 | N53: =IF($C53="","",IF($I53="PEN",1,IFERROR(IF(_xlfn.XLOOKUP($B53,TC_Fechas,TC_Venta_Rango,"",-1)="","",_xlfn.XLOOKUP($B53,TC_Fechas,TC_Venta_Rango,"",-1)),""))) | O53: =IF(OR($C53="",$N53=""),"",ROUND($J53*$N53,2)+ROUND($K53*$N53,2)) | P53: =IF($G53="","",IFERROR(INDEX(Catalogo_Tasas,MATCH($G53,Catalogo_Codigos,0)),"")) | Q53: =IF($G53="","",IFERROR(INDEX(Catalogo_Umbrales,MATCH($G53,Catalogo_Codigos,0)),"")) | R53: =IF(OR($C53="",$P53="",$O53=""),"",IF($F53<>"FACTURA","NO",IF(AND($P53>0,$O53>$Q53),"SI","NO"))) | S53: =IF($R53="SI",ROUND($O53*$P53,2),IF($C53="","",0)) | U53: =IF($C53="","",IF($R53<>"SI","",IF($T53="","SIN DATO",IF(ABS($T53-$S53)<=0.5,"OK","REVISAR")))) | W53: =IF(OR($C53="",$N53=""),"",IF($F53="RHE",ROUND($L53-$V53,2),ROUND($L53-($S53/$N53),2))) | AB53: ADMINISTRATIVO
A54: 51 | B54: =DATE(2026,8,16) | C54: FM01-00004843 | D54: 20503909007 | E54: CLABE ANDINA S.A.C. (SUMAQ MACHU PICCHU HOTEL) | F54: FACTURA | G54: N/A | H54: =IF($G54="","",IFERROR(INDEX(Catalogo_Etiquetas,MATCH($G54,Catalogo_Codigos,0)),"CODIGO NO VALIDO")) | I54: USD | J54: 504 | K54: 0 | L54: =IF($C54="","",$J54+$K54) | M54: 639 | N54: =IF($C54="","",IF($I54="PEN",1,IFERROR(IF(_xlfn.XLOOKUP($B54,TC_Fechas,TC_Venta_Rango,"",-1)="","",_xlfn.XLOOKUP($B54,TC_Fechas,TC_Venta_Rango,"",-1)),""))) | O54: =IF(OR($C54="",$N54=""),"",ROUND($J54*$N54,2)+ROUND($K54*$N54,2)) | P54: =IF($G54="","",IFERROR(INDEX(Catalogo_Tasas,MATCH($G54,Catalogo_Codigos,0)),"")) | Q54: =IF($G54="","",IFERROR(INDEX(Catalogo_Umbrales,MATCH($G54,Catalogo_Codigos,0)),"")) | R54: =IF(OR($C54="",$P54="",$O54=""),"",IF($F54<>"FACTURA","NO",IF(AND($P54>0,$O54>$Q54),"SI","NO"))) | S54: =IF($R54="SI",ROUND($O54*$P54,2),IF($C54="","",0)) | U54: =IF($C54="","",IF($R54<>"SI","",IF($T54="","SIN DATO",IF(ABS($T54-$S54)<=0.5,"OK","REVISAR")))) | W54: =IF(OR($C54="",$N54=""),"",IF($F54="RHE",ROUND($L54-$V54,2),ROUND($L54-($S54/$N54),2))) | AB54: PROVEEDOR
A55: 52 | B55: =DATE(2026,8,15) | C55: E001-2031 | D55: 20601320500 | E55: ETT HOUSE TOURS S.A.C. | F55: FACTURA | G55: N/A | H55: =IF($G55="","",IFERROR(INDEX(Catalogo_Etiquetas,MATCH($G55,Catalogo_Codigos,0)),"CODIGO NO VALIDO")) | I55: USD | J55: 769.61 | K55: 138.53 | L55: =IF($C55="","",$J55+$K55) | M55: 639 | N55: =IF($C55="","",IF($I55="PEN",1,IFERROR(IF(_xlfn.XLOOKUP($B55,TC_Fechas,TC_Venta_Rango,"",-1)="","",_xlfn.XLOOKUP($B55,TC_Fechas,TC_Venta_Rango,"",-1)),""))) | O55: =IF(OR($C55="",$N55=""),"",ROUND($J55*$N55,2)+ROUND($K55*$N55,2)) | P55: =IF($G55="","",IFERROR(INDEX(Catalogo_Tasas,MATCH($G55,Catalogo_Codigos,0)),"")) | Q55: =IF($G55="","",IFERROR(INDEX(Catalogo_Umbrales,MATCH($G55,Catalogo_Codigos,0)),"")) | R55: =IF(OR($C55="",$P55="",$O55=""),"",IF($F55<>"FACTURA","NO",IF(AND($P55>0,$O55>$Q55),"SI","NO"))) | S55: =IF($R55="SI",ROUND($O55*$P55,2),IF($C55="","",0)) | U55: =IF($C55="","",IF($R55<>"SI","",IF($T55="","SIN DATO",IF(ABS($T55-$S55)<=0.5,"OK","REVISAR")))) | W55: =IF(OR($C55="",$N55=""),"",IF($F55="RHE",ROUND($L55-$V55,2),ROUND($L55-($S55/$N55),2))) | AB55: PROVEEDOR
A56: 53 | B56: =DATE(2026,8,7) | C56: E001-71 | D56: 10465858414 | E56: GUILLEN GALLO ANDRES ALEJANDRO | F56: RHE | G56: N/A | H56: =IF($G56="","",IFERROR(INDEX(Catalogo_Etiquetas,MATCH($G56,Catalogo_Codigos,0)),"CODIGO NO VALIDO")) | I56: PEN | J56: 500 | K56: 0 | L56: =IF($C56="","",$J56+$K56) | M56: 632 | N56: =IF($C56="","",IF($I56="PEN",1,IFERROR(IF(_xlfn.XLOOKUP($B56,TC_Fechas,TC_Venta_Rango,"",-1)="","",_xlfn.XLOOKUP($B56,TC_Fechas,TC_Venta_Rango,"",-1)),""))) | O56: =IF(OR($C56="",$N56=""),"",ROUND($J56*$N56,2)+ROUND($K56*$N56,2)) | P56: =IF($G56="","",IFERROR(INDEX(Catalogo_Tasas,MATCH($G56,Catalogo_Codigos,0)),"")) | Q56: =IF($G56="","",IFERROR(INDEX(Catalogo_Umbrales,MATCH($G56,Catalogo_Codigos,0)),"")) | R56: =IF(OR($C56="",$P56="",$O56=""),"",IF($F56<>"FACTURA","NO",IF(AND($P56>0,$O56>$Q56),"SI","NO"))) | S56: =IF($R56="SI",ROUND($O56*$P56,2),IF($C56="","",0)) | U56: =IF($C56="","",IF($R56<>"SI","",IF($T56="","SIN DATO",IF(ABS($T56-$S56)<=0.5,"OK","REVISAR")))) | V56: 60 | W56: =IF(OR($C56="",$N56=""),"",IF($F56="RHE",ROUND($L56-$V56,2),ROUND($L56-($S56/$N56),2))) | AB56: ADMINISTRATIVO
A57: 54 | B57: =DATE(2026,8,13) | C57: FC55-00002098 | D57: 20536047906 | E57: HOTELERIA PERUANA S.A.C. (TIERRA VIVA HOTELS) | F57: NOTA DE CREDITO | G57: N/A | H57: =IF($G57="","",IFERROR(INDEX(Catalogo_Etiquetas,MATCH($G57,Catalogo_Codigos,0)),"CODIGO NO VALIDO")) | I57: USD | J57: -237.5 | K57: -42.75 | L57: =IF($C57="","",$J57+$K57) | M57: 639 | N57: =IF($C57="","",IF($I57="PEN",1,IFERROR(IF(_xlfn.XLOOKUP($B57,TC_Fechas,TC_Venta_Rango,"",-1)="","",_xlfn.XLOOKUP($B57,TC_Fechas,TC_Venta_Rango,"",-1)),""))) | O57: =IF(OR($C57="",$N57=""),"",ROUND($J57*$N57,2)+ROUND($K57*$N57,2)) | P57: =IF($G57="","",IFERROR(INDEX(Catalogo_Tasas,MATCH($G57,Catalogo_Codigos,0)),"")) | Q57: =IF($G57="","",IFERROR(INDEX(Catalogo_Umbrales,MATCH($G57,Catalogo_Codigos,0)),"")) | R57: =IF(OR($C57="",$P57="",$O57=""),"",IF($F57<>"FACTURA","NO",IF(AND($P57>0,$O57>$Q57),"SI","NO"))) | S57: =IF($R57="SI",ROUND($O57*$P57,2),IF($C57="","",0)) | U57: =IF($C57="","",IF($R57<>"SI","",IF($T57="","SIN DATO",IF(ABS($T57-$S57)<=0.5,"OK","REVISAR")))) | W57: =IF(OR($C57="",$N57=""),"",IF($F57="RHE",ROUND($L57-$V57,2),ROUND($L57-($S57/$N57),2))) | AB57: PROVEEDOR
A58: 55 | B58: =DATE(2026,8,17) | C58: F006-00003192 | D58: 20610235736 | E58: HOTELES LA HACIENDA S.A.C. | F58: FACTURA | G58: N/A | H58: =IF($G58="","",IFERROR(INDEX(Catalogo_Etiquetas,MATCH($G58,Catalogo_Codigos,0)),"CODIGO NO VALIDO")) | I58: USD | J58: 94.66 | K58: 17.04 | L58: =IF($C58="","",$J58+$K58) | M58: 639 | N58: =IF($C58="","",IF($I58="PEN",1,IFERROR(IF(_xlfn.XLOOKUP($B58,TC_Fechas,TC_Venta_Rango,"",-1)="","",_xlfn.XLOOKUP($B58,TC_Fechas,TC_Venta_Rango,"",-1)),""))) | O58: =IF(OR($C58="",$N58=""),"",ROUND($J58*$N58,2)+ROUND($K58*$N58,2)) | P58: =IF($G58="","",IFERROR(INDEX(Catalogo_Tasas,MATCH($G58,Catalogo_Codigos,0)),"")) | Q58: =IF($G58="","",IFERROR(INDEX(Catalogo_Umbrales,MATCH($G58,Catalogo_Codigos,0)),"")) | R58: =IF(OR($C58="",$P58="",$O58=""),"",IF($F58<>"FACTURA","NO",IF(AND($P58>0,$O58>$Q58),"SI","NO"))) | S58: =IF($R58="SI",ROUND($O58*$P58,2),IF($C58="","",0)) | U58: =IF($C58="","",IF($R58<>"SI","",IF($T58="","SIN DATO",IF(ABS($T58-$S58)<=0.5,"OK","REVISAR")))) | W58: =IF(OR($C58="",$N58=""),"",IF($F58="RHE",ROUND($L58-$V58,2),ROUND($L58-($S58/$N58),2))) | AB58: PROVEEDOR
A59: 56 | B59: =DATE(2026,8,18) | C59: F302-00001674 | D59: 20114803228 | E59: INVERSIONES NACIONALES DE TURISMO S.A. (Palacio del Inka Hotel) | F59: NOTA DE CREDITO | G59: N/A | H59: =IF($G59="","",IFERROR(INDEX(Catalogo_Etiquetas,MATCH($G59,Catalogo_Codigos,0)),"CODIGO NO VALIDO")) | I59: USD | J59: -1102 | K59: -198.36 | L59: =IF($C59="","",$J59+$K59) | M59: 639 | N59: =IF($C59="","",IF($I59="PEN",1,IFERROR(IF(_xlfn.XLOOKUP($B59,TC_Fechas,TC_Venta_Rango,"",-1)="","",_xlfn.XLOOKUP($B59,TC_Fechas,TC_Venta_Rango,"",-1)),""))) | O59: =IF(OR($C59="",$N59=""),"",ROUND($J59*$N59,2)+ROUND($K59*$N59,2)) | P59: =IF($G59="","",IFERROR(INDEX(Catalogo_Tasas,MATCH($G59,Catalogo_Codigos,0)),"")) | Q59: =IF($G59="","",IFERROR(INDEX(Catalogo_Umbrales,MATCH($G59,Catalogo_Codigos,0)),"")) | R59: =IF(OR($C59="",$P59="",$O59=""),"",IF($F59<>"FACTURA","NO",IF(AND($P59>0,$O59>$Q59),"SI","NO"))) | S59: =IF($R59="SI",ROUND($O59*$P59,2),IF($C59="","",0)) | U59: =IF($C59="","",IF($R59<>"SI","",IF($T59="","SIN DATO",IF(ABS($T59-$S59)<=0.5,"OK","REVISAR")))) | W59: =IF(OR($C59="",$N59=""),"",IF($F59="RHE",ROUND($L59-$V59,2),ROUND($L59-($S59/$N59),2))) | AB59: PROVEEDOR
A60: 57 | B60: =DATE(2026,8,14) | C60: E001-2663 | D60: 20602860958 | E60: J & R TURISMO E.I.R.L. | F60: FACTURA | G60: 026 | H60: =IF($G60="","",IFERROR(INDEX(Catalogo_Etiquetas,MATCH($G60,Catalogo_Codigos,0)),"CODIGO NO VALIDO")) | I60: USD | J60: 260 | K60: 46.8 | L60: =IF($C60="","",$J60+$K60) | M60: 631 | N60: =IF($C60="","",IF($I60="PEN",1,IFERROR(IF(_xlfn.XLOOKUP($B60,TC_Fechas,TC_Venta_Rango,"",-1)="","",_xlfn.XLOOKUP($B60,TC_Fechas,TC_Venta_Rango,"",-1)),""))) | O60: =IF(OR($C60="",$N60=""),"",ROUND($J60*$N60,2)+ROUND($K60*$N60,2)) | P60: =IF($G60="","",IFERROR(INDEX(Catalogo_Tasas,MATCH($G60,Catalogo_Codigos,0)),"")) | Q60: =IF($G60="","",IFERROR(INDEX(Catalogo_Umbrales,MATCH($G60,Catalogo_Codigos,0)),"")) | R60: =IF(OR($C60="",$P60="",$O60=""),"",IF($F60<>"FACTURA","NO",IF(AND($P60>0,$O60>$Q60),"SI","NO"))) | S60: =IF($R60="SI",ROUND($O60*$P60,2),IF($C60="","",0)) | T60: 103.42 | U60: =IF($C60="","",IF($R60<>"SI","",IF($T60="","SIN DATO",IF(ABS($T60-$S60)<=0.5,"OK","REVISAR")))) | W60: =IF(OR($C60="",$N60=""),"",IF($F60="RHE",ROUND($L60-$V60,2),ROUND($L60-($S60/$N60),2))) | AB60: PROVEEDOR
A61: 58 | B61: =DATE(2026,8,12) | C61: E001-52 | D61: 20615850609 | E61: MCA LUXURY CORPORATION S.A.C. | F61: FACTURA | G61: 026 | H61: =IF($G61="","",IFERROR(INDEX(Catalogo_Etiquetas,MATCH($G61,Catalogo_Codigos,0)),"CODIGO NO VALIDO")) | I61: USD | J61: 662.63 | K61: 119.27 | L61: =IF($C61="","",$J61+$K61) | M61: 631 | N61: =IF($C61="","",IF($I61="PEN",1,IFERROR(IF(_xlfn.XLOOKUP($B61,TC_Fechas,TC_Venta_Rango,"",-1)="","",_xlfn.XLOOKUP($B61,TC_Fechas,TC_Venta_Rango,"",-1)),""))) | O61: =IF(OR($C61="",$N61=""),"",ROUND($J61*$N61,2)+ROUND($K61*$N61,2)) | P61: =IF($G61="","",IFERROR(INDEX(Catalogo_Tasas,MATCH($G61,Catalogo_Codigos,0)),"")) | Q61: =IF($G61="","",IFERROR(INDEX(Catalogo_Umbrales,MATCH($G61,Catalogo_Codigos,0)),"")) | R61: =IF(OR($C61="",$P61="",$O61=""),"",IF($F61<>"FACTURA","NO",IF(AND($P61>0,$O61>$Q61),"SI","NO"))) | S61: =IF($R61="SI",ROUND($O61*$P61,2),IF($C61="","",0)) | T61: 264 | U61: =IF($C61="","",IF($R61<>"SI","",IF($T61="","SIN DATO",IF(ABS($T61-$S61)<=0.5,"OK","REVISAR")))) | W61: =IF(OR($C61="",$N61=""),"",IF($F61="RHE",ROUND($L61-$V61,2),ROUND($L61-($S61/$N61),2))) | AB61: ADMINISTRATIVO
A62: 59 | B62: =DATE(2026,8,10) | C62: F001-00000733 | D62: 20603386214 | E62: PERUVIAN CULTURE TRAVEL AGENCIA DE VIAJES Y TURISMO S.R.L. | F62: FACTURA | G62: 037 | H62: =IF($G62="","",IFERROR(INDEX(Catalogo_Etiquetas,MATCH($G62,Catalogo_Codigos,0)),"CODIGO NO VALIDO")) | I62: USD | J62: 1041.86 | K62: 187.54 | L62: =IF($C62="","",$J62+$K62) | M62: 639 | N62: =IF($C62="","",IF($I62="PEN",1,IFERROR(IF(_xlfn.XLOOKUP($B62,TC_Fechas,TC_Venta_Rango,"",-1)="","",_xlfn.XLOOKUP($B62,TC_Fechas,TC_Venta_Rango,"",-1)),""))) | O62: =IF(OR($C62="",$N62=""),"",ROUND($J62*$N62,2)+ROUND($K62*$N62,2)) | P62: =IF($G62="","",IFERROR(INDEX(Catalogo_Tasas,MATCH($G62,Catalogo_Codigos,0)),"")) | Q62: =IF($G62="","",IFERROR(INDEX(Catalogo_Umbrales,MATCH($G62,Catalogo_Codigos,0)),"")) | R62: =IF(OR($C62="",$P62="",$O62=""),"",IF($F62<>"FACTURA","NO",IF(AND($P62>0,$O62>$Q62),"SI","NO"))) | S62: =IF($R62="SI",ROUND($O62*$P62,2),IF($C62="","",0)) | T62: 500.27 | U62: =IF($C62="","",IF($R62<>"SI","",IF($T62="","SIN DATO",IF(ABS($T62-$S62)<=0.5,"OK","REVISAR")))) | W62: =IF(OR($C62="",$N62=""),"",IF($F62="RHE",ROUND($L62-$V62,2),ROUND($L62-($S62/$N62),2))) | AB62: PROVEEDOR
A63: 60 | B63: =DATE(2026,8,12) | C63: FC03-00002537 | D63: 20387253191 | E63: PETIT POIS S.A.C. (HOTEL SOL Y LUNA) | F63: FACTURA | G63: N/A | H63: =IF($G63="","",IFERROR(INDEX(Catalogo_Etiquetas,MATCH($G63,Catalogo_Codigos,0)),"CODIGO NO VALIDO")) | I63: USD | J63: 2184.75 | K63: 393.25 | L63: =IF($C63="","",$J63+$K63) | M63: 639 | N63: =IF($C63="","",IF($I63="PEN",1,IFERROR(IF(_xlfn.XLOOKUP($B63,TC_Fechas,TC_Venta_Rango,"",-1)="","",_xlfn.XLOOKUP($B63,TC_Fechas,TC_Venta_Rango,"",-1)),""))) | O63: =IF(OR($C63="",$N63=""),"",ROUND($J63*$N63,2)+ROUND($K63*$N63,2)) | P63: =IF($G63="","",IFERROR(INDEX(Catalogo_Tasas,MATCH($G63,Catalogo_Codigos,0)),"")) | Q63: =IF($G63="","",IFERROR(INDEX(Catalogo_Umbrales,MATCH($G63,Catalogo_Codigos,0)),"")) | R63: =IF(OR($C63="",$P63="",$O63=""),"",IF($F63<>"FACTURA","NO",IF(AND($P63>0,$O63>$Q63),"SI","NO"))) | S63: =IF($R63="SI",ROUND($O63*$P63,2),IF($C63="","",0)) | U63: =IF($C63="","",IF($R63<>"SI","",IF($T63="","SIN DATO",IF(ABS($T63-$S63)<=0.5,"OK","REVISAR")))) | W63: =IF(OR($C63="",$N63=""),"",IF($F63="RHE",ROUND($L63-$V63,2),ROUND($L63-($S63/$N63),2))) | AB63: PROVEEDOR
A64: 61 | B64: =DATE(2026,8,8) | C64: FW01-00000409 | D64: 20611806893 | E64: SIETE APUS E.I.R.L. | F64: FACTURA | G64: N/A | H64: =IF($G64="","",IFERROR(INDEX(Catalogo_Etiquetas,MATCH($G64,Catalogo_Codigos,0)),"CODIGO NO VALIDO")) | I64: PEN | J64: 180.09 | K64: 18.91 | L64: =IF($C64="","",$J64+$K64) | M64: 639 | N64: =IF($C64="","",IF($I64="PEN",1,IFERROR(IF(_xlfn.XLOOKUP($B64,TC_Fechas,TC_Venta_Rango,"",-1)="","",_xlfn.XLOOKUP($B64,TC_Fechas,TC_Venta_Rango,"",-1)),""))) | O64: =IF(OR($C64="",$N64=""),"",ROUND($J64*$N64,2)+ROUND($K64*$N64,2)) | P64: =IF($G64="","",IFERROR(INDEX(Catalogo_Tasas,MATCH($G64,Catalogo_Codigos,0)),"")) | Q64: =IF($G64="","",IFERROR(INDEX(Catalogo_Umbrales,MATCH($G64,Catalogo_Codigos,0)),"")) | R64: =IF(OR($C64="",$P64="",$O64=""),"",IF($F64<>"FACTURA","NO",IF(AND($P64>0,$O64>$Q64),"SI","NO"))) | S64: =IF($R64="SI",ROUND($O64*$P64,2),IF($C64="","",0)) | U64: =IF($C64="","",IF($R64<>"SI","",IF($T64="","SIN DATO",IF(ABS($T64-$S64)<=0.5,"OK","REVISAR")))) | W64: =IF(OR($C64="",$N64=""),"",IF($F64="RHE",ROUND($L64-$V64,2),ROUND($L64-($S64/$N64),2))) | AB64: ADMINISTRATIVO
A65: 62 | B65: =DATE(2026,8,4) | C65: E001- 542 | D65: 10408222490 | E65: CARRASCO ALEGRE ROLLY VICTOR | F65: RHE | G65: N/A | H65: =IF($G65="","",IFERROR(INDEX(Catalogo_Etiquetas,MATCH($G65,Catalogo_Codigos,0)),"CODIGO NO VALIDO")) | I65: USD | J65: 190 | K65: 0 | L65: =IF($C65="","",$J65+$K65) | M65: 632 | N65: =IF($C65="","",IF($I65="PEN",1,IFERROR(IF(_xlfn.XLOOKUP($B65,TC_Fechas,TC_Venta_Rango,"",-1)="","",_xlfn.XLOOKUP($B65,TC_Fechas,TC_Venta_Rango,"",-1)),""))) | O65: =IF(OR($C65="",$N65=""),"",ROUND($J65*$N65,2)+ROUND($K65*$N65,2)) | P65: =IF($G65="","",IFERROR(INDEX(Catalogo_Tasas,MATCH($G65,Catalogo_Codigos,0)),"")) | Q65: =IF($G65="","",IFERROR(INDEX(Catalogo_Umbrales,MATCH($G65,Catalogo_Codigos,0)),"")) | R65: =IF(OR($C65="",$P65="",$O65=""),"",IF($F65<>"FACTURA","NO",IF(AND($P65>0,$O65>$Q65),"SI","NO"))) | S65: =IF($R65="SI",ROUND($O65*$P65,2),IF($C65="","",0)) | U65: =IF($C65="","",IF($R65<>"SI","",IF($T65="","SIN DATO",IF(ABS($T65-$S65)<=0.5,"OK","REVISAR")))) | W65: =IF(OR($C65="",$N65=""),"",IF($F65="RHE",ROUND($L65-$V65,2),ROUND($L65-($S65/$N65),2))) | AB65: PROVEEDOR
A66: 63 | B66: =DATE(2026,8,6) | C66: E001-324 | D66: 20603668406 | E66: LUXURY ADVENTURE CUSCO PERU E.I.R.L. | F66: FACTURA | G66: N/A | H66: =IF($G66="","",IFERROR(INDEX(Catalogo_Etiquetas,MATCH($G66,Catalogo_Codigos,0)),"CODIGO NO VALIDO")) | I66: USD | J66: 118.64 | K66: 21.36 | L66: =IF($C66="","",$J66+$K66) | M66: 639 | N66: =IF($C66="","",IF($I66="PEN",1,IFERROR(IF(_xlfn.XLOOKUP($B66,TC_Fechas,TC_Venta_Rango,"",-1)="","",_xlfn.XLOOKUP($B66,TC_Fechas,TC_Venta_Rango,"",-1)),""))) | O66: =IF(OR($C66="",$N66=""),"",ROUND($J66*$N66,2)+ROUND($K66*$N66,2)) | P66: =IF($G66="","",IFERROR(INDEX(Catalogo_Tasas,MATCH($G66,Catalogo_Codigos,0)),"")) | Q66: =IF($G66="","",IFERROR(INDEX(Catalogo_Umbrales,MATCH($G66,Catalogo_Codigos,0)),"")) | R66: =IF(OR($C66="",$P66="",$O66=""),"",IF($F66<>"FACTURA","NO",IF(AND($P66>0,$O66>$Q66),"SI","NO"))) | S66: =IF($R66="SI",ROUND($O66*$P66,2),IF($C66="","",0)) | U66: =IF($C66="","",IF($R66<>"SI","",IF($T66="","SIN DATO",IF(ABS($T66-$S66)<=0.5,"OK","REVISAR")))) | W66: =IF(OR($C66="",$N66=""),"",IF($F66="RHE",ROUND($L66-$V66,2),ROUND($L66-($S66/$N66),2))) | AB66: PROVEEDOR
A67: 64 | B67: =DATE(2026,8,6) | C67: E001-329 | D67: 20603668406 | E67: LUXURY ADVENTURE CUSCO PERU E.I.R.L. | F67: FACTURA | G67: 037 | H67: =IF($G67="","",IFERROR(INDEX(Catalogo_Etiquetas,MATCH($G67,Catalogo_Codigos,0)),"CODIGO NO VALIDO")) | I67: USD | J67: 177.97 | K67: 32.03 | L67: =IF($C67="","",$J67+$K67) | M67: 639 | N67: =IF($C67="","",IF($I67="PEN",1,IFERROR(IF(_xlfn.XLOOKUP($B67,TC_Fechas,TC_Venta_Rango,"",-1)="","",_xlfn.XLOOKUP($B67,TC_Fechas,TC_Venta_Rango,"",-1)),""))) | O67: =IF(OR($C67="",$N67=""),"",ROUND($J67*$N67,2)+ROUND($K67*$N67,2)) | P67: =IF($G67="","",IFERROR(INDEX(Catalogo_Tasas,MATCH($G67,Catalogo_Codigos,0)),"")) | Q67: =IF($G67="","",IFERROR(INDEX(Catalogo_Umbrales,MATCH($G67,Catalogo_Codigos,0)),"")) | R67: =IF(OR($C67="",$P67="",$O67=""),"",IF($F67<>"FACTURA","NO",IF(AND($P67>0,$O67>$Q67),"SI","NO"))) | S67: =IF($R67="SI",ROUND($O67*$P67,2),IF($C67="","",0)) | T67: 86 | U67: =IF($C67="","",IF($R67<>"SI","",IF($T67="","SIN DATO",IF(ABS($T67-$S67)<=0.5,"OK","REVISAR")))) | W67: =IF(OR($C67="",$N67=""),"",IF($F67="RHE",ROUND($L67-$V67,2),ROUND($L67-($S67/$N67),2))) | AB67: PROVEEDOR
A68: 65 | B68: =DATE(2026,8,6) | C68: E001-334 | D68: 20603668406 | E68: LUXURY ADVENTURE CUSCO PERU E.I.R.L. | F68: FACTURA | G68: N/A | H68: =IF($G68="","",IFERROR(INDEX(Catalogo_Etiquetas,MATCH($G68,Catalogo_Codigos,0)),"CODIGO NO VALIDO")) | I68: USD | J68: 133.48 | K68: 24.03 | L68: =IF($C68="","",$J68+$K68) | M68: 639 | N68: =IF($C68="","",IF($I68="PEN",1,IFERROR(IF(_xlfn.XLOOKUP($B68,TC_Fechas,TC_Venta_Rango,"",-1)="","",_xlfn.XLOOKUP($B68,TC_Fechas,TC_Venta_Rango,"",-1)),""))) | O68: =IF(OR($C68="",$N68=""),"",ROUND($J68*$N68,2)+ROUND($K68*$N68,2)) | P68: =IF($G68="","",IFERROR(INDEX(Catalogo_Tasas,MATCH($G68,Catalogo_Codigos,0)),"")) | Q68: =IF($G68="","",IFERROR(INDEX(Catalogo_Umbrales,MATCH($G68,Catalogo_Codigos,0)),"")) | R68: =IF(OR($C68="",$P68="",$O68=""),"",IF($F68<>"FACTURA","NO",IF(AND($P68>0,$O68>$Q68),"SI","NO"))) | S68: =IF($R68="SI",ROUND($O68*$P68,2),IF($C68="","",0)) | U68: =IF($C68="","",IF($R68<>"SI","",IF($T68="","SIN DATO",IF(ABS($T68-$S68)<=0.5,"OK","REVISAR")))) | W68: =IF(OR($C68="",$N68=""),"",IF($F68="RHE",ROUND($L68-$V68,2),ROUND($L68-($S68/$N68),2))) | AB68: PROVEEDOR
A69: 66 | B69: =DATE(2026,8,13) | C69: E001-111 | D69: 10731722124 | E69: ALCAZAR GONZALES ERNESTO ANDRES | F69: RHE | G69: N/A | H69: =IF($G69="","",IFERROR(INDEX(Catalogo_Etiquetas,MATCH($G69,Catalogo_Codigos,0)),"CODIGO NO VALIDO")) | I69: PEN | J69: 160 | K69: 0 | L69: =IF($C69="","",$J69+$K69) | M69: 632 | N69: =IF($C69="","",IF($I69="PEN",1,IFERROR(IF(_xlfn.XLOOKUP($B69,TC_Fechas,TC_Venta_Rango,"",-1)="","",_xlfn.XLOOKUP($B69,TC_Fechas,TC_Venta_Rango,"",-1)),""))) | O69: =IF(OR($C69="",$N69=""),"",ROUND($J69*$N69,2)+ROUND($K69*$N69,2)) | P69: =IF($G69="","",IFERROR(INDEX(Catalogo_Tasas,MATCH($G69,Catalogo_Codigos,0)),"")) | Q69: =IF($G69="","",IFERROR(INDEX(Catalogo_Umbrales,MATCH($G69,Catalogo_Codigos,0)),"")) | R69: =IF(OR($C69="",$P69="",$O69=""),"",IF($F69<>"FACTURA","NO",IF(AND($P69>0,$O69>$Q69),"SI","NO"))) | S69: =IF($R69="SI",ROUND($O69*$P69,2),IF($C69="","",0)) | U69: =IF($C69="","",IF($R69<>"SI","",IF($T69="","SIN DATO",IF(ABS($T69-$S69)<=0.5,"OK","REVISAR")))) | W69: =IF(OR($C69="",$N69=""),"",IF($F69="RHE",ROUND($L69-$V69,2),ROUND($L69-($S69/$N69),2))) | AB69: PROVEEDOR
A70: 67 | B70: =DATE(2026,8,13) | C70: E001-7189 | D70: 20225253529 | E70: ARCOBALENO SOCIEDAD COMERCIAL DE RESPONSABILIDAD LIMITADA | F70: FACTURA | G70: 037 | H70: =IF($G70="","",IFERROR(INDEX(Catalogo_Etiquetas,MATCH($G70,Catalogo_Codigos,0)),"CODIGO NO VALIDO")) | I70: USD | J70: 455.29 | K70: 81.95 | L70: =IF($C70="","",$J70+$K70) | M70: 639 | N70: =IF($C70="","",IF($I70="PEN",1,IFERROR(IF(_xlfn.XLOOKUP($B70,TC_Fechas,TC_Venta_Rango,"",-1)="","",_xlfn.XLOOKUP($B70,TC_Fechas,TC_Venta_Rango,"",-1)),""))) | O70: =IF(OR($C70="",$N70=""),"",ROUND($J70*$N70,2)+ROUND($K70*$N70,2)) | P70: =IF($G70="","",IFERROR(INDEX(Catalogo_Tasas,MATCH($G70,Catalogo_Codigos,0)),"")) | Q70: =IF($G70="","",IFERROR(INDEX(Catalogo_Umbrales,MATCH($G70,Catalogo_Codigos,0)),"")) | R70: =IF(OR($C70="",$P70="",$O70=""),"",IF($F70<>"FACTURA","NO",IF(AND($P70>0,$O70>$Q70),"SI","NO"))) | S70: =IF($R70="SI",ROUND($O70*$P70,2),IF($C70="","",0)) | T70: 217 | U70: =IF($C70="","",IF($R70<>"SI","",IF($T70="","SIN DATO",IF(ABS($T70-$S70)<=0.5,"OK","REVISAR")))) | W70: =IF(OR($C70="",$N70=""),"",IF($F70="RHE",ROUND($L70-$V70,2),ROUND($L70-($S70/$N70),2))) | AB70: PROVEEDOR
A71: 68 | B71: =DATE(2026,8,10) | C71: E001- 176 | D71: 10408744151 | E71: BEOUTIS BAZAN URSULA CATHERINE | F71: RHE | G71: N/A | H71: =IF($G71="","",IFERROR(INDEX(Catalogo_Etiquetas,MATCH($G71,Catalogo_Codigos,0)),"CODIGO NO VALIDO")) | I71: PEN | J71: 1025 | K71: 0 | L71: =IF($C71="","",$J71+$K71) | M71: 632 | N71: =IF($C71="","",IF($I71="PEN",1,IFERROR(IF(_xlfn.XLOOKUP($B71,TC_Fechas,TC_Venta_Rango,"",-1)="","",_xlfn.XLOOKUP($B71,TC_Fechas,TC_Venta_Rango,"",-1)),""))) | O71: =IF(OR($C71="",$N71=""),"",ROUND($J71*$N71,2)+ROUND($K71*$N71,2)) | P71: =IF($G71="","",IFERROR(INDEX(Catalogo_Tasas,MATCH($G71,Catalogo_Codigos,0)),"")) | Q71: =IF($G71="","",IFERROR(INDEX(Catalogo_Umbrales,MATCH($G71,Catalogo_Codigos,0)),"")) | R71: =IF(OR($C71="",$P71="",$O71=""),"",IF($F71<>"FACTURA","NO",IF(AND($P71>0,$O71>$Q71),"SI","NO"))) | S71: =IF($R71="SI",ROUND($O71*$P71,2),IF($C71="","",0)) | U71: =IF($C71="","",IF($R71<>"SI","",IF($T71="","SIN DATO",IF(ABS($T71-$S71)<=0.5,"OK","REVISAR")))) | W71: =IF(OR($C71="",$N71=""),"",IF($F71="RHE",ROUND($L71-$V71,2),ROUND($L71-($S71/$N71),2))) | AB71: ADMINISTRATIVO
A72: 69 | B72: =DATE(2026,8,10) | C72: F001-11458 | D72: 20523732391 | E72: COMPAÃ‘IA HOTELERA BAMA S.A.C. (ANANAY HOTELS) | F72: FACTURA | G72: N/A | H72: =IF($G72="","",IFERROR(INDEX(Catalogo_Etiquetas,MATCH($G72,Catalogo_Codigos,0)),"CODIGO NO VALIDO")) | I72: USD | J72: 867.27 | K72: 0 | L72: =IF($C72="","",$J72+$K72) | M72: 639 | N72: =IF($C72="","",IF($I72="PEN",1,IFERROR(IF(_xlfn.XLOOKUP($B72,TC_Fechas,TC_Venta_Rango,"",-1)="","",_xlfn.XLOOKUP($B72,TC_Fechas,TC_Venta_Rango,"",-1)),""))) | O72: =IF(OR($C72="",$N72=""),"",ROUND($J72*$N72,2)+ROUND($K72*$N72,2)) | P72: =IF($G72="","",IFERROR(INDEX(Catalogo_Tasas,MATCH($G72,Catalogo_Codigos,0)),"")) | Q72: =IF($G72="","",IFERROR(INDEX(Catalogo_Umbrales,MATCH($G72,Catalogo_Codigos,0)),"")) | R72: =IF(OR($C72="",$P72="",$O72=""),"",IF($F72<>"FACTURA","NO",IF(AND($P72>0,$O72>$Q72),"SI","NO"))) | S72: =IF($R72="SI",ROUND($O72*$P72,2),IF($C72="","",0)) | U72: =IF($C72="","",IF($R72<>"SI","",IF($T72="","SIN DATO",IF(ABS($T72-$S72)<=0.5,"OK","REVISAR")))) | W72: =IF(OR($C72="",$N72=""),"",IF($F72="RHE",ROUND($L72-$V72,2),ROUND($L72-($S72/$N72),2))) | AB72: PROVEEDOR
A73: 70 | B73: =DATE(2026,8,6) | C73: F005-00003003 | D73: 20492015165 | E73: FOOD SERVICE INVESTMENT S.A.C. | F73: FACTURA | G73: N/A | H73: =IF($G73="","",IFERROR(INDEX(Catalogo_Etiquetas,MATCH($G73,Catalogo_Codigos,0)),"CODIGO NO VALIDO")) | I73: PEN | J73: 4144 | K73: 745.92 | L73: =IF($C73="","",$J73+$K73) | M73: 639 | N73: =IF($C73="","",IF($I73="PEN",1,IFERROR(IF(_xlfn.XLOOKUP($B73,TC_Fechas,TC_Venta_Rango,"",-1)="","",_xlfn.XLOOKUP($B73,TC_Fechas,TC_Venta_Rango,"",-1)),""))) | O73: =IF(OR($C73="",$N73=""),"",ROUND($J73*$N73,2)+ROUND($K73*$N73,2)) | P73: =IF($G73="","",IFERROR(INDEX(Catalogo_Tasas,MATCH($G73,Catalogo_Codigos,0)),"")) | Q73: =IF($G73="","",IFERROR(INDEX(Catalogo_Umbrales,MATCH($G73,Catalogo_Codigos,0)),"")) | R73: =IF(OR($C73="",$P73="",$O73=""),"",IF($F73<>"FACTURA","NO",IF(AND($P73>0,$O73>$Q73),"SI","NO"))) | S73: =IF($R73="SI",ROUND($O73*$P73,2),IF($C73="","",0)) | U73: =IF($C73="","",IF($R73<>"SI","",IF($T73="","SIN DATO",IF(ABS($T73-$S73)<=0.5,"OK","REVISAR")))) | W73: =IF(OR($C73="",$N73=""),"",IF($F73="RHE",ROUND($L73-$V73,2),ROUND($L73-($S73/$N73),2))) | AB73: PROVEEDOR
A74: 71 | B74: =DATE(2026,8,4) | C74: E001- 556 | D74: 10239898993 | E74: HANCO ASTETE ANDY | F74: RHE | G74: N/A | H74: =IF($G74="","",IFERROR(INDEX(Catalogo_Etiquetas,MATCH($G74,Catalogo_Codigos,0)),"CODIGO NO VALIDO")) | I74: USD | J74: 90 | K74: 0 | L74: =IF($C74="","",$J74+$K74) | M74: 632 | N74: =IF($C74="","",IF($I74="PEN",1,IFERROR(IF(_xlfn.XLOOKUP($B74,TC_Fechas,TC_Venta_Rango,"",-1)="","",_xlfn.XLOOKUP($B74,TC_Fechas,TC_Venta_Rango,"",-1)),""))) | O74: =IF(OR($C74="",$N74=""),"",ROUND($J74*$N74,2)+ROUND($K74*$N74,2)) | P74: =IF($G74="","",IFERROR(INDEX(Catalogo_Tasas,MATCH($G74,Catalogo_Codigos,0)),"")) | Q74: =IF($G74="","",IFERROR(INDEX(Catalogo_Umbrales,MATCH($G74,Catalogo_Codigos,0)),"")) | R74: =IF(OR($C74="",$P74="",$O74=""),"",IF($F74<>"FACTURA","NO",IF(AND($P74>0,$O74>$Q74),"SI","NO"))) | S74: =IF($R74="SI",ROUND($O74*$P74,2),IF($C74="","",0)) | U74: =IF($C74="","",IF($R74<>"SI","",IF($T74="","SIN DATO",IF(ABS($T74-$S74)<=0.5,"OK","REVISAR")))) | W74: =IF(OR($C74="",$N74=""),"",IF($F74="RHE",ROUND($L74-$V74,2),ROUND($L74-($S74/$N74),2))) | AB74: PROVEEDOR
A75: 72 | B75: =DATE(2026,8,18) | C75: F007-00024484 | D75: 20536047906 | E75: HOTELERIA PERUANA S.A.C. (Tierra Viva Hotels) | F75: FACTURA | G75: N/A | H75: =IF($G75="","",IFERROR(INDEX(Catalogo_Etiquetas,MATCH($G75,Catalogo_Codigos,0)),"CODIGO NO VALIDO")) | I75: USD | J75: 123.64 | K75: 0 | L75: =IF($C75="","",$J75+$K75) | M75: 639 | N75: =IF($C75="","",IF($I75="PEN",1,IFERROR(IF(_xlfn.XLOOKUP($B75,TC_Fechas,TC_Venta_Rango,"",-1)="","",_xlfn.XLOOKUP($B75,TC_Fechas,TC_Venta_Rango,"",-1)),""))) | O75: =IF(OR($C75="",$N75=""),"",ROUND($J75*$N75,2)+ROUND($K75*$N75,2)) | P75: =IF($G75="","",IFERROR(INDEX(Catalogo_Tasas,MATCH($G75,Catalogo_Codigos,0)),"")) | Q75: =IF($G75="","",IFERROR(INDEX(Catalogo_Umbrales,MATCH($G75,Catalogo_Codigos,0)),"")) | R75: =IF(OR($C75="",$P75="",$O75=""),"",IF($F75<>"FACTURA","NO",IF(AND($P75>0,$O75>$Q75),"SI","NO"))) | S75: =IF($R75="SI",ROUND($O75*$P75,2),IF($C75="","",0)) | U75: =IF($C75="","",IF($R75<>"SI","",IF($T75="","SIN DATO",IF(ABS($T75-$S75)<=0.5,"OK","REVISAR")))) | W75: =IF(OR($C75="",$N75=""),"",IF($F75="RHE",ROUND($L75-$V75,2),ROUND($L75-($S75/$N75),2))) | AB75: PROVEEDOR
A76: 73 | B76: =DATE(2026,8,19) | C76: F006-00003227 | D76: 20610235736 | E76: HOTELES LA HACIENDA S.A.C. (Bahia Paracas) | F76: FACTURA | G76: N/A | H76: =IF($G76="","",IFERROR(INDEX(Catalogo_Etiquetas,MATCH($G76,Catalogo_Codigos,0)),"CODIGO NO VALIDO")) | I76: USD | J76: 159.29 | K76: 0 | L76: =IF($C76="","",$J76+$K76) | M76: 639 | N76: =IF($C76="","",IF($I76="PEN",1,IFERROR(IF(_xlfn.XLOOKUP($B76,TC_Fechas,TC_Venta_Rango,"",-1)="","",_xlfn.XLOOKUP($B76,TC_Fechas,TC_Venta_Rango,"",-1)),""))) | O76: =IF(OR($C76="",$N76=""),"",ROUND($J76*$N76,2)+ROUND($K76*$N76,2)) | P76: =IF($G76="","",IFERROR(INDEX(Catalogo_Tasas,MATCH($G76,Catalogo_Codigos,0)),"")) | Q76: =IF($G76="","",IFERROR(INDEX(Catalogo_Umbrales,MATCH($G76,Catalogo_Codigos,0)),"")) | R76: =IF(OR($C76="",$P76="",$O76=""),"",IF($F76<>"FACTURA","NO",IF(AND($P76>0,$O76>$Q76),"SI","NO"))) | S76: =IF($R76="SI",ROUND($O76*$P76,2),IF($C76="","",0)) | U76: =IF($C76="","",IF($R76<>"SI","",IF($T76="","SIN DATO",IF(ABS($T76-$S76)<=0.5,"OK","REVISAR")))) | W76: =IF(OR($C76="",$N76=""),"",IF($F76="RHE",ROUND($L76-$V76,2),ROUND($L76-($S76/$N76),2))) | AB76: PROVEEDOR
A77: 74 | B77: =DATE(2026,8,16) | C77: FC01-00008808 | D77: 20477906380 | E77: INVERSIONES TRES POR OCHO S.A.C. (LAS QOLQAS) | F77: FACTURA | G77: N/A | H77: =IF($G77="","",IFERROR(INDEX(Catalogo_Etiquetas,MATCH($G77,Catalogo_Codigos,0)),"CODIGO NO VALIDO")) | I77: USD | J77: 681.82 | K77: 0 | L77: =IF($C77="","",$J77+$K77) | M77: 639 | N77: =IF($C77="","",IF($I77="PEN",1,IFERROR(IF(_xlfn.XLOOKUP($B77,TC_Fechas,TC_Venta_Rango,"",-1)="","",_xlfn.XLOOKUP($B77,TC_Fechas,TC_Venta_Rango,"",-1)),""))) | O77: =IF(OR($C77="",$N77=""),"",ROUND($J77*$N77,2)+ROUND($K77*$N77,2)) | P77: =IF($G77="","",IFERROR(INDEX(Catalogo_Tasas,MATCH($G77,Catalogo_Codigos,0)),"")) | Q77: =IF($G77="","",IFERROR(INDEX(Catalogo_Umbrales,MATCH($G77,Catalogo_Codigos,0)),"")) | R77: =IF(OR($C77="",$P77="",$O77=""),"",IF($F77<>"FACTURA","NO",IF(AND($P77>0,$O77>$Q77),"SI","NO"))) | S77: =IF($R77="SI",ROUND($O77*$P77,2),IF($C77="","",0)) | U77: =IF($C77="","",IF($R77<>"SI","",IF($T77="","SIN DATO",IF(ABS($T77-$S77)<=0.5,"OK","REVISAR")))) | W77: =IF(OR($C77="",$N77=""),"",IF($F77="RHE",ROUND($L77-$V77,2),ROUND($L77-($S77/$N77),2))) | AB77: PROVEEDOR
A78: 75 | B78: =DATE(2026,8,7) | C78: F020-00016435 | D78: 20536180657 | E78: LA CASA DE BARRANCO S.A.C (HOTEL B) | F78: FACTURA | G78: N/A | H78: =IF($G78="","",IFERROR(INDEX(Catalogo_Etiquetas,MATCH($G78,Catalogo_Codigos,0)),"CODIGO NO VALIDO")) | I78: USD | J78: 2830 | K78: 0 | L78: =IF($C78="","",$J78+$K78) | M78: 639 | N78: =IF($C78="","",IF($I78="PEN",1,IFERROR(IF(_xlfn.XLOOKUP($B78,TC_Fechas,TC_Venta_Rango,"",-1)="","",_xlfn.XLOOKUP($B78,TC_Fechas,TC_Venta_Rango,"",-1)),""))) | O78: =IF(OR($C78="",$N78=""),"",ROUND($J78*$N78,2)+ROUND($K78*$N78,2)) | P78: =IF($G78="","",IFERROR(INDEX(Catalogo_Tasas,MATCH($G78,Catalogo_Codigos,0)),"")) | Q78: =IF($G78="","",IFERROR(INDEX(Catalogo_Umbrales,MATCH($G78,Catalogo_Codigos,0)),"")) | R78: =IF(OR($C78="",$P78="",$O78=""),"",IF($F78<>"FACTURA","NO",IF(AND($P78>0,$O78>$Q78),"SI","NO"))) | S78: =IF($R78="SI",ROUND($O78*$P78,2),IF($C78="","",0)) | U78: =IF($C78="","",IF($R78<>"SI","",IF($T78="","SIN DATO",IF(ABS($T78-$S78)<=0.5,"OK","REVISAR")))) | W78: =IF(OR($C78="",$N78=""),"",IF($F78="RHE",ROUND($L78-$V78,2),ROUND($L78-($S78/$N78),2))) | AB78: PROVEEDOR
A79: 76 | B79: =DATE(2026,8,8) | C79: F001-10305 | D79: 20490257188 | E79: NATURA VIVE S.A.C. | F79: FACTURA | G79: N/A | H79: =IF($G79="","",IFERROR(INDEX(Catalogo_Etiquetas,MATCH($G79,Catalogo_Codigos,0)),"CODIGO NO VALIDO")) | I79: PEN | J79: 441 | K79: 79.38 | L79: =IF($C79="","",$J79+$K79) | M79: 639 | N79: =IF($C79="","",IF($I79="PEN",1,IFERROR(IF(_xlfn.XLOOKUP($B79,TC_Fechas,TC_Venta_Rango,"",-1)="","",_xlfn.XLOOKUP($B79,TC_Fechas,TC_Venta_Rango,"",-1)),""))) | O79: =IF(OR($C79="",$N79=""),"",ROUND($J79*$N79,2)+ROUND($K79*$N79,2)) | P79: =IF($G79="","",IFERROR(INDEX(Catalogo_Tasas,MATCH($G79,Catalogo_Codigos,0)),"")) | Q79: =IF($G79="","",IFERROR(INDEX(Catalogo_Umbrales,MATCH($G79,Catalogo_Codigos,0)),"")) | R79: =IF(OR($C79="",$P79="",$O79=""),"",IF($F79<>"FACTURA","NO",IF(AND($P79>0,$O79>$Q79),"SI","NO"))) | S79: =IF($R79="SI",ROUND($O79*$P79,2),IF($C79="","",0)) | U79: =IF($C79="","",IF($R79<>"SI","",IF($T79="","SIN DATO",IF(ABS($T79-$S79)<=0.5,"OK","REVISAR")))) | W79: =IF(OR($C79="",$N79=""),"",IF($F79="RHE",ROUND($L79-$V79,2),ROUND($L79-($S79/$N79),2))) | AB79: PROVEEDOR
A80: 77 | B80: =DATE(2026,8,11) | C80: F001-00000734 | D80: 20603386214 | E80: PERUVIAN CULTURE TRAVEL AGENCIA DE VIAJES Y TURISMO S.R.L. | F80: FACTURA | G80: 037 | H80: =IF($G80="","",IFERROR(INDEX(Catalogo_Etiquetas,MATCH($G80,Catalogo_Codigos,0)),"CODIGO NO VALIDO")) | I80: USD | J80: 1056.44 | K80: 190.16 | L80: =IF($C80="","",$J80+$K80) | M80: 639 | N80: =IF($C80="","",IF($I80="PEN",1,IFERROR(IF(_xlfn.XLOOKUP($B80,TC_Fechas,TC_Venta_Rango,"",-1)="","",_xlfn.XLOOKUP($B80,TC_Fechas,TC_Venta_Rango,"",-1)),""))) | O80: =IF(OR($C80="",$N80=""),"",ROUND($J80*$N80,2)+ROUND($K80*$N80,2)) | P80: =IF($G80="","",IFERROR(INDEX(Catalogo_Tasas,MATCH($G80,Catalogo_Codigos,0)),"")) | Q80: =IF($G80="","",IFERROR(INDEX(Catalogo_Umbrales,MATCH($G80,Catalogo_Codigos,0)),"")) | R80: =IF(OR($C80="",$P80="",$O80=""),"",IF($F80<>"FACTURA","NO",IF(AND($P80>0,$O80>$Q80),"SI","NO"))) | S80: =IF($R80="SI",ROUND($O80*$P80,2),IF($C80="","",0)) | T80: 506.67 | U80: =IF($C80="","",IF($R80<>"SI","",IF($T80="","SIN DATO",IF(ABS($T80-$S80)<=0.5,"OK","REVISAR")))) | W80: =IF(OR($C80="",$N80=""),"",IF($F80="RHE",ROUND($L80-$V80,2),ROUND($L80-($S80/$N80),2))) | AB80: PROVEEDOR
A81: 78 | B81: =DATE(2026,8,10) | C81: E001-1128 | D81: 20563940281 | E81: QUECHUA TREKS PERU E.I.R.L. | F81: FACTURA | G81: 037 | H81: =IF($G81="","",IFERROR(INDEX(Catalogo_Etiquetas,MATCH($G81,Catalogo_Codigos,0)),"CODIGO NO VALIDO")) | I81: USD | J81: 200.85 | K81: 36.15 | L81: =IF($C81="","",$J81+$K81) | M81: 639 | N81: =IF($C81="","",IF($I81="PEN",1,IFERROR(IF(_xlfn.XLOOKUP($B81,TC_Fechas,TC_Venta_Rango,"",-1)="","",_xlfn.XLOOKUP($B81,TC_Fechas,TC_Venta_Rango,"",-1)),""))) | O81: =IF(OR($C81="",$N81=""),"",ROUND($J81*$N81,2)+ROUND($K81*$N81,2)) | P81: =IF($G81="","",IFERROR(INDEX(Catalogo_Tasas,MATCH($G81,Catalogo_Codigos,0)),"")) | Q81: =IF($G81="","",IFERROR(INDEX(Catalogo_Umbrales,MATCH($G81,Catalogo_Codigos,0)),"")) | R81: =IF(OR($C81="",$P81="",$O81=""),"",IF($F81<>"FACTURA","NO",IF(AND($P81>0,$O81>$Q81),"SI","NO"))) | S81: =IF($R81="SI",ROUND($O81*$P81,2),IF($C81="","",0)) | T81: 96 | U81: =IF($C81="","",IF($R81<>"SI","",IF($T81="","SIN DATO",IF(ABS($T81-$S81)<=0.5,"OK","REVISAR")))) | W81: =IF(OR($C81="",$N81=""),"",IF($F81="RHE",ROUND($L81-$V81,2),ROUND($L81-($S81/$N81),2))) | AB81: PROVEEDOR
A82: 79 | B82: =DATE(2026,8,8) | C82: E001-1228 | D82: 20600179005 | E82: TRANSPORTES TURISTICOS LASER S.A.C. | F82: FACTURA | G82: N/A | H82: =IF($G82="","",IFERROR(INDEX(Catalogo_Etiquetas,MATCH($G82,Catalogo_Codigos,0)),"CODIGO NO VALIDO")) | I82: USD | J82: 150.33 | K82: 27.06 | L82: =IF($C82="","",$J82+$K82) | M82: 639 | N82: =IF($C82="","",IF($I82="PEN",1,IFERROR(IF(_xlfn.XLOOKUP($B82,TC_Fechas,TC_Venta_Rango,"",-1)="","",_xlfn.XLOOKUP($B82,TC_Fechas,TC_Venta_Rango,"",-1)),""))) | O82: =IF(OR($C82="",$N82=""),"",ROUND($J82*$N82,2)+ROUND($K82*$N82,2)) | P82: =IF($G82="","",IFERROR(INDEX(Catalogo_Tasas,MATCH($G82,Catalogo_Codigos,0)),"")) | Q82: =IF($G82="","",IFERROR(INDEX(Catalogo_Umbrales,MATCH($G82,Catalogo_Codigos,0)),"")) | R82: =IF(OR($C82="",$P82="",$O82=""),"",IF($F82<>"FACTURA","NO",IF(AND($P82>0,$O82>$Q82),"SI","NO"))) | S82: =IF($R82="SI",ROUND($O82*$P82,2),IF($C82="","",0)) | U82: =IF($C82="","",IF($R82<>"SI","",IF($T82="","SIN DATO",IF(ABS($T82-$S82)<=0.5,"OK","REVISAR")))) | W82: =IF(OR($C82="",$N82=""),"",IF($F82="RHE",ROUND($L82-$V82,2),ROUND($L82-($S82/$N82),2))) | AB82: PROVEEDOR
A83: 80 | B83: =DATE(2026,8,8) | C83: E001-1880 | D83: 20358309870 | E83: CAMPING TOURS E.I.R.LTDA | F83: FACTURA | G83: 037 | H83: =IF($G83="","",IFERROR(INDEX(Catalogo_Etiquetas,MATCH($G83,Catalogo_Codigos,0)),"CODIGO NO VALIDO")) | I83: USD | J83: 442.4 | K83: 79.63 | L83: =IF($C83="","",$J83+$K83) | M83: 639 | N83: =IF($C83="","",IF($I83="PEN",1,IFERROR(IF(_xlfn.XLOOKUP($B83,TC_Fechas,TC_Venta_Rango,"",-1)="","",_xlfn.XLOOKUP($B83,TC_Fechas,TC_Venta_Rango,"",-1)),""))) | O83: =IF(OR($C83="",$N83=""),"",ROUND($J83*$N83,2)+ROUND($K83*$N83,2)) | P83: =IF($G83="","",IFERROR(INDEX(Catalogo_Tasas,MATCH($G83,Catalogo_Codigos,0)),"")) | Q83: =IF($G83="","",IFERROR(INDEX(Catalogo_Umbrales,MATCH($G83,Catalogo_Codigos,0)),"")) | R83: =IF(OR($C83="",$P83="",$O83=""),"",IF($F83<>"FACTURA","NO",IF(AND($P83>0,$O83>$Q83),"SI","NO"))) | S83: =IF($R83="SI",ROUND($O83*$P83,2),IF($C83="","",0)) | T83: 212.4 | U83: =IF($C83="","",IF($R83<>"SI","",IF($T83="","SIN DATO",IF(ABS($T83-$S83)<=0.5,"OK","REVISAR")))) | W83: =IF(OR($C83="",$N83=""),"",IF($F83="RHE",ROUND($L83-$V83,2),ROUND($L83-($S83/$N83),2))) | AB83: PROVEEDOR
A84: 81 | B84: =DATE(2026,8,5) | C84: E001- 645 | D84: 10404124507 | E84: GONZALES ACHAHUI HENRY LUIS | F84: RHE | G84: N/A | H84: =IF($G84="","",IFERROR(INDEX(Catalogo_Etiquetas,MATCH($G84,Catalogo_Codigos,0)),"CODIGO NO VALIDO")) | I84: USD | J84: 75 | K84: 0 | L84: =IF($C84="","",$J84+$K84) | M84: 632 | N84: =IF($C84="","",IF($I84="PEN",1,IFERROR(IF(_xlfn.XLOOKUP($B84,TC_Fechas,TC_Venta_Rango,"",-1)="","",_xlfn.XLOOKUP($B84,TC_Fechas,TC_Venta_Rango,"",-1)),""))) | O84: =IF(OR($C84="",$N84=""),"",ROUND($J84*$N84,2)+ROUND($K84*$N84,2)) | P84: =IF($G84="","",IFERROR(INDEX(Catalogo_Tasas,MATCH($G84,Catalogo_Codigos,0)),"")) | Q84: =IF($G84="","",IFERROR(INDEX(Catalogo_Umbrales,MATCH($G84,Catalogo_Codigos,0)),"")) | R84: =IF(OR($C84="",$P84="",$O84=""),"",IF($F84<>"FACTURA","NO",IF(AND($P84>0,$O84>$Q84),"SI","NO"))) | S84: =IF($R84="SI",ROUND($O84*$P84,2),IF($C84="","",0)) | U84: =IF($C84="","",IF($R84<>"SI","",IF($T84="","SIN DATO",IF(ABS($T84-$S84)<=0.5,"OK","REVISAR")))) | W84: =IF(OR($C84="",$N84=""),"",IF($F84="RHE",ROUND($L84-$V84,2),ROUND($L84-($S84/$N84),2))) | AB84: PROVEEDOR
A85: 82 | B85: =DATE(2026,8,6) | C85: E001-325 | D85: 20603668406 | E85: LUXURY ADVENTURE CUSCO PERU E.I.R.L. | F85: FACTURA | G85: N/A | H85: =IF($G85="","",IFERROR(INDEX(Catalogo_Etiquetas,MATCH($G85,Catalogo_Codigos,0)),"CODIGO NO VALIDO")) | I85: USD | J85: 88.98 | K85: 16.02 | L85: =IF($C85="","",$J85+$K85) | M85: 639 | N85: =IF($C85="","",IF($I85="PEN",1,IFERROR(IF(_xlfn.XLOOKUP($B85,TC_Fechas,TC_Venta_Rango,"",-1)="","",_xlfn.XLOOKUP($B85,TC_Fechas,TC_Venta_Rango,"",-1)),""))) | O85: =IF(OR($C85="",$N85=""),"",ROUND($J85*$N85,2)+ROUND($K85*$N85,2)) | P85: =IF($G85="","",IFERROR(INDEX(Catalogo_Tasas,MATCH($G85,Catalogo_Codigos,0)),"")) | Q85: =IF($G85="","",IFERROR(INDEX(Catalogo_Umbrales,MATCH($G85,Catalogo_Codigos,0)),"")) | R85: =IF(OR($C85="",$P85="",$O85=""),"",IF($F85<>"FACTURA","NO",IF(AND($P85>0,$O85>$Q85),"SI","NO"))) | S85: =IF($R85="SI",ROUND($O85*$P85,2),IF($C85="","",0)) | U85: =IF($C85="","",IF($R85<>"SI","",IF($T85="","SIN DATO",IF(ABS($T85-$S85)<=0.5,"OK","REVISAR")))) | W85: =IF(OR($C85="",$N85=""),"",IF($F85="RHE",ROUND($L85-$V85,2),ROUND($L85-($S85/$N85),2))) | AB85: PROVEEDOR
A86: 83 | B86: =DATE(2026,8,6) | C86: E001-330 | D86: 20603668406 | E86: LUXURY ADVENTURE CUSCO PERU E.I.R.L. | F86: FACTURA | G86: N/A | H86: =IF($G86="","",IFERROR(INDEX(Catalogo_Etiquetas,MATCH($G86,Catalogo_Codigos,0)),"CODIGO NO VALIDO")) | I86: USD | J86: 133.48 | K86: 24.03 | L86: =IF($C86="","",$J86+$K86) | M86: 639 | N86: =IF($C86="","",IF($I86="PEN",1,IFERROR(IF(_xlfn.XLOOKUP($B86,TC_Fechas,TC_Venta_Rango,"",-1)="","",_xlfn.XLOOKUP($B86,TC_Fechas,TC_Venta_Rango,"",-1)),""))) | O86: =IF(OR($C86="",$N86=""),"",ROUND($J86*$N86,2)+ROUND($K86*$N86,2)) | P86: =IF($G86="","",IFERROR(INDEX(Catalogo_Tasas,MATCH($G86,Catalogo_Codigos,0)),"")) | Q86: =IF($G86="","",IFERROR(INDEX(Catalogo_Umbrales,MATCH($G86,Catalogo_Codigos,0)),"")) | R86: =IF(OR($C86="",$P86="",$O86=""),"",IF($F86<>"FACTURA","NO",IF(AND($P86>0,$O86>$Q86),"SI","NO"))) | S86: =IF($R86="SI",ROUND($O86*$P86,2),IF($C86="","",0)) | U86: =IF($C86="","",IF($R86<>"SI","",IF($T86="","SIN DATO",IF(ABS($T86-$S86)<=0.5,"OK","REVISAR")))) | W86: =IF(OR($C86="",$N86=""),"",IF($F86="RHE",ROUND($L86-$V86,2),ROUND($L86-($S86/$N86),2))) | AB86: PROVEEDOR
A87: 84 | B87: =DATE(2026,8,6) | C87: E001-335 | D87: 20603668406 | E87: LUXURY ADVENTURE CUSCO PERU E.I.R.L. | F87: FACTURA | G87: N/A | H87: =IF($G87="","",IFERROR(INDEX(Catalogo_Etiquetas,MATCH($G87,Catalogo_Codigos,0)),"CODIGO NO VALIDO")) | I87: USD | J87: 163.14 | K87: 29.36 | L87: =IF($C87="","",$J87+$K87) | M87: 639 | N87: =IF($C87="","",IF($I87="PEN",1,IFERROR(IF(_xlfn.XLOOKUP($B87,TC_Fechas,TC_Venta_Rango,"",-1)="","",_xlfn.XLOOKUP($B87,TC_Fechas,TC_Venta_Rango,"",-1)),""))) | O87: =IF(OR($C87="",$N87=""),"",ROUND($J87*$N87,2)+ROUND($K87*$N87,2)) | P87: =IF($G87="","",IFERROR(INDEX(Catalogo_Tasas,MATCH($G87,Catalogo_Codigos,0)),"")) | Q87: =IF($G87="","",IFERROR(INDEX(Catalogo_Umbrales,MATCH($G87,Catalogo_Codigos,0)),"")) | R87: =IF(OR($C87="",$P87="",$O87=""),"",IF($F87<>"FACTURA","NO",IF(AND($P87>0,$O87>$Q87),"SI","NO"))) | S87: =IF($R87="SI",ROUND($O87*$P87,2),IF($C87="","",0)) | U87: =IF($C87="","",IF($R87<>"SI","",IF($T87="","SIN DATO",IF(ABS($T87-$S87)<=0.5,"OK","REVISAR")))) | W87: =IF(OR($C87="",$N87=""),"",IF($F87="RHE",ROUND($L87-$V87,2),ROUND($L87-($S87/$N87),2))) | AB87: PROVEEDOR
A88: 85 | B88: =DATE(2026,8,10) | C88: F003-00000024 | D88: 20606383356 | E88: ALQA GALERIA DE EXPRESIONES ANDINAS SRL | F88: FACTURA | G88: N/A | H88: =IF($G88="","",IFERROR(INDEX(Catalogo_Etiquetas,MATCH($G88,Catalogo_Codigos,0)),"CODIGO NO VALIDO")) | I88: PEN | J88: 660.64 | K88: 69.36 | L88: =IF($C88="","",$J88+$K88) | M88: 639 | N88: =IF($C88="","",IF($I88="PEN",1,IFERROR(IF(_xlfn.XLOOKUP($B88,TC_Fechas,TC_Venta_Rango,"",-1)="","",_xlfn.XLOOKUP($B88,TC_Fechas,TC_Venta_Rango,"",-1)),""))) | O88: =IF(OR($C88="",$N88=""),"",ROUND($J88*$N88,2)+ROUND($K88*$N88,2)) | P88: =IF($G88="","",IFERROR(INDEX(Catalogo_Tasas,MATCH($G88,Catalogo_Codigos,0)),"")) | Q88: =IF($G88="","",IFERROR(INDEX(Catalogo_Umbrales,MATCH($G88,Catalogo_Codigos,0)),"")) | R88: =IF(OR($C88="",$P88="",$O88=""),"",IF($F88<>"FACTURA","NO",IF(AND($P88>0,$O88>$Q88),"SI","NO"))) | S88: =IF($R88="SI",ROUND($O88*$P88,2),IF($C88="","",0)) | U88: =IF($C88="","",IF($R88<>"SI","",IF($T88="","SIN DATO",IF(ABS($T88-$S88)<=0.5,"OK","REVISAR")))) | W88: =IF(OR($C88="",$N88=""),"",IF($F88="RHE",ROUND($L88-$V88,2),ROUND($L88-($S88/$N88),2))) | AB88: PROVEEDOR
A89: 86 | B89: =DATE(2026,8,7) | C89: E001-172 | D89: 10408744151 | E89: BEOUTIS BAZAN URSULA CATHERINE | F89: RHE | G89: N/A | H89: =IF($G89="","",IFERROR(INDEX(Catalogo_Etiquetas,MATCH($G89,Catalogo_Codigos,0)),"CODIGO NO VALIDO")) | I89: PEN | J89: 1025 | K89: 0 | L89: =IF($C89="","",$J89+$K89) | M89: 632 | N89: =IF($C89="","",IF($I89="PEN",1,IFERROR(IF(_xlfn.XLOOKUP($B89,TC_Fechas,TC_Venta_Rango,"",-1)="","",_xlfn.XLOOKUP($B89,TC_Fechas,TC_Venta_Rango,"",-1)),""))) | O89: =IF(OR($C89="",$N89=""),"",ROUND($J89*$N89,2)+ROUND($K89*$N89,2)) | P89: =IF($G89="","",IFERROR(INDEX(Catalogo_Tasas,MATCH($G89,Catalogo_Codigos,0)),"")) | Q89: =IF($G89="","",IFERROR(INDEX(Catalogo_Umbrales,MATCH($G89,Catalogo_Codigos,0)),"")) | R89: =IF(OR($C89="",$P89="",$O89=""),"",IF($F89<>"FACTURA","NO",IF(AND($P89>0,$O89>$Q89),"SI","NO"))) | S89: =IF($R89="SI",ROUND($O89*$P89,2),IF($C89="","",0)) | U89: =IF($C89="","",IF($R89<>"SI","",IF($T89="","SIN DATO",IF(ABS($T89-$S89)<=0.5,"OK","REVISAR")))) | W89: =IF(OR($C89="",$N89=""),"",IF($F89="RHE",ROUND($L89-$V89,2),ROUND($L89-($S89/$N89),2))) | AB89: ADMINISTRATIVO
A90: 87 | B90: =DATE(2026,8,10) | C90: F002-0023975 | D90: 20452235073 | E90: BUGANVILLA TOURS S.A.C. | F90: FACTURA | G90: 037 | H90: =IF($G90="","",IFERROR(INDEX(Catalogo_Etiquetas,MATCH($G90,Catalogo_Codigos,0)),"CODIGO NO VALIDO")) | I90: USD | J90: 273 | K90: 49.14 | L90: =IF($C90="","",$J90+$K90) | M90: 639 | N90: =IF($C90="","",IF($I90="PEN",1,IFERROR(IF(_xlfn.XLOOKUP($B90,TC_Fechas,TC_Venta_Rango,"",-1)="","",_xlfn.XLOOKUP($B90,TC_Fechas,TC_Venta_Rango,"",-1)),""))) | O90: =IF(OR($C90="",$N90=""),"",ROUND($J90*$N90,2)+ROUND($K90*$N90,2)) | P90: =IF($G90="","",IFERROR(INDEX(Catalogo_Tasas,MATCH($G90,Catalogo_Codigos,0)),"")) | Q90: =IF($G90="","",IFERROR(INDEX(Catalogo_Umbrales,MATCH($G90,Catalogo_Codigos,0)),"")) | R90: =IF(OR($C90="",$P90="",$O90=""),"",IF($F90<>"FACTURA","NO",IF(AND($P90>0,$O90>$Q90),"SI","NO"))) | S90: =IF($R90="SI",ROUND($O90*$P90,2),IF($C90="","",0)) | T90: 131.1 | U90: =IF($C90="","",IF($R90<>"SI","",IF($T90="","SIN DATO",IF(ABS($T90-$S90)<=0.5,"OK","REVISAR")))) | W90: =IF(OR($C90="",$N90=""),"",IF($F90="RHE",ROUND($L90-$V90,2),ROUND($L90-($S90/$N90),2))) | AB90: PROVEEDOR
A91: 88 | B91: =DATE(2026,8,5) | C91: E001-950 | D91: 20101091083 | E91: COOPERATIVA DE AHORRO Y CREDITO ABACO | F91: FACTURA | G91: 019 | H91: =IF($G91="","",IFERROR(INDEX(Catalogo_Etiquetas,MATCH($G91,Catalogo_Codigos,0)),"CODIGO NO VALIDO")) | I91: USD | J91: 919.28 | K91: 165.47 | L91: =IF($C91="","",$J91+$K91) | M91: 635 | N91: =IF($C91="","",IF($I91="PEN",1,IFERROR(IF(_xlfn.XLOOKUP($B91,TC_Fechas,TC_Venta_Rango,"",-1)="","",_xlfn.XLOOKUP($B91,TC_Fechas,TC_Venta_Rango,"",-1)),""))) | O91: =IF(OR($C91="",$N91=""),"",ROUND($J91*$N91,2)+ROUND($K91*$N91,2)) | P91: =IF($G91="","",IFERROR(INDEX(Catalogo_Tasas,MATCH($G91,Catalogo_Codigos,0)),"")) | Q91: =IF($G91="","",IFERROR(INDEX(Catalogo_Umbrales,MATCH($G91,Catalogo_Codigos,0)),"")) | R91: =IF(OR($C91="",$P91="",$O91=""),"",IF($F91<>"FACTURA","NO",IF(AND($P91>0,$O91>$Q91),"SI","NO"))) | S91: =IF($R91="SI",ROUND($O91*$P91,2),IF($C91="","",0)) | T91: 368 | U91: =IF($C91="","",IF($R91<>"SI","",IF($T91="","SIN DATO",IF(ABS($T91-$S91)<=0.5,"OK","REVISAR")))) | W91: =IF(OR($C91="",$N91=""),"",IF($F91="RHE",ROUND($L91-$V91,2),ROUND($L91-($S91/$N91),2))) | AB91: ADMINISTRATIVO
A92: 89 | B92: =DATE(2026,8,6) | C92: F005-00003004 | D92: 20492015165 | E92: FOOD SERVICE INVESTMENT S.A.C. | F92: FACTURA | G92: N/A | H92: =IF($G92="","",IFERROR(INDEX(Catalogo_Etiquetas,MATCH($G92,Catalogo_Codigos,0)),"CODIGO NO VALIDO")) | I92: PEN | J92: 1092.8 | K92: 196.7 | L92: =IF($C92="","",$J92+$K92) | M92: 639 | N92: =IF($C92="","",IF($I92="PEN",1,IFERROR(IF(_xlfn.XLOOKUP($B92,TC_Fechas,TC_Venta_Rango,"",-1)="","",_xlfn.XLOOKUP($B92,TC_Fechas,TC_Venta_Rango,"",-1)),""))) | O92: =IF(OR($C92="",$N92=""),"",ROUND($J92*$N92,2)+ROUND($K92*$N92,2)) | P92: =IF($G92="","",IFERROR(INDEX(Catalogo_Tasas,MATCH($G92,Catalogo_Codigos,0)),"")) | Q92: =IF($G92="","",IFERROR(INDEX(Catalogo_Umbrales,MATCH($G92,Catalogo_Codigos,0)),"")) | R92: =IF(OR($C92="",$P92="",$O92=""),"",IF($F92<>"FACTURA","NO",IF(AND($P92>0,$O92>$Q92),"SI","NO"))) | S92: =IF($R92="SI",ROUND($O92*$P92,2),IF($C92="","",0)) | U92: =IF($C92="","",IF($R92<>"SI","",IF($T92="","SIN DATO",IF(ABS($T92-$S92)<=0.5,"OK","REVISAR")))) | W92: =IF(OR($C92="",$N92=""),"",IF($F92="RHE",ROUND($L92-$V92,2),ROUND($L92-($S92/$N92),2))) | AB92: PROVEEDOR
A93: 90 | B93: =DATE(2026,8,4) | C93: E001- 557 | D93: 10239898993 | E93: HANCO ASTETE ANDY | F93: RHE | G93: N/A | H93: =IF($G93="","",IFERROR(INDEX(Catalogo_Etiquetas,MATCH($G93,Catalogo_Codigos,0)),"CODIGO NO VALIDO")) | I93: USD | J93: 180 | K93: 0 | L93: =IF($C93="","",$J93+$K93) | M93: 632 | N93: =IF($C93="","",IF($I93="PEN",1,IFERROR(IF(_xlfn.XLOOKUP($B93,TC_Fechas,TC_Venta_Rango,"",-1)="","",_xlfn.XLOOKUP($B93,TC_Fechas,TC_Venta_Rango,"",-1)),""))) | O93: =IF(OR($C93="",$N93=""),"",ROUND($J93*$N93,2)+ROUND($K93*$N93,2)) | P93: =IF($G93="","",IFERROR(INDEX(Catalogo_Tasas,MATCH($G93,Catalogo_Codigos,0)),"")) | Q93: =IF($G93="","",IFERROR(INDEX(Catalogo_Umbrales,MATCH($G93,Catalogo_Codigos,0)),"")) | R93: =IF(OR($C93="",$P93="",$O93=""),"",IF($F93<>"FACTURA","NO",IF(AND($P93>0,$O93>$Q93),"SI","NO"))) | S93: =IF($R93="SI",ROUND($O93*$P93,2),IF($C93="","",0)) | U93: =IF($C93="","",IF($R93<>"SI","",IF($T93="","SIN DATO",IF(ABS($T93-$S93)<=0.5,"OK","REVISAR")))) | W93: =IF(OR($C93="",$N93=""),"",IF($F93="RHE",ROUND($L93-$V93,2),ROUND($L93-($S93/$N93),2))) | AB93: PROVEEDOR
A94: 91 | B94: =DATE(2026,8,13) | C94: F006-00003137 | D94: 20610235736 | E94: HOTELES LA HACIENDA S.A.C. | F94: FACTURA | G94: N/A | H94: =IF($G94="","",IFERROR(INDEX(Catalogo_Etiquetas,MATCH($G94,Catalogo_Codigos,0)),"CODIGO NO VALIDO")) | I94: USD | J94: 47.33 | K94: 8.52 | L94: =IF($C94="","",$J94+$K94) | M94: 639 | N94: =IF($C94="","",IF($I94="PEN",1,IFERROR(IF(_xlfn.XLOOKUP($B94,TC_Fechas,TC_Venta_Rango,"",-1)="","",_xlfn.XLOOKUP($B94,TC_Fechas,TC_Venta_Rango,"",-1)),""))) | O94: =IF(OR($C94="",$N94=""),"",ROUND($J94*$N94,2)+ROUND($K94*$N94,2)) | P94: =IF($G94="","",IFERROR(INDEX(Catalogo_Tasas,MATCH($G94,Catalogo_Codigos,0)),"")) | Q94: =IF($G94="","",IFERROR(INDEX(Catalogo_Umbrales,MATCH($G94,Catalogo_Codigos,0)),"")) | R94: =IF(OR($C94="",$P94="",$O94=""),"",IF($F94<>"FACTURA","NO",IF(AND($P94>0,$O94>$Q94),"SI","NO"))) | S94: =IF($R94="SI",ROUND($O94*$P94,2),IF($C94="","",0)) | U94: =IF($C94="","",IF($R94<>"SI","",IF($T94="","SIN DATO",IF(ABS($T94-$S94)<=0.5,"OK","REVISAR")))) | W94: =IF(OR($C94="",$N94=""),"",IF($F94="RHE",ROUND($L94-$V94,2),ROUND($L94-($S94/$N94),2))) | AB94: PROVEEDOR
A95: 92 | B95: =DATE(2026,8,19) | C95: F003-00002785 | D95: 20610235736 | E95: HOTELES LA HACIENDA S.A.C. (Bahia Paracas) | F95: FACTURA | G95: N/A | H95: =IF($G95="","",IFERROR(INDEX(Catalogo_Etiquetas,MATCH($G95,Catalogo_Codigos,0)),"CODIGO NO VALIDO")) | I95: USD | J95: 47.33 | K95: 8.52 | L95: =IF($C95="","",$J95+$K95) | M95: 639 | N95: =IF($C95="","",IF($I95="PEN",1,IFERROR(IF(_xlfn.XLOOKUP($B95,TC_Fechas,TC_Venta_Rango,"",-1)="","",_xlfn.XLOOKUP($B95,TC_Fechas,TC_Venta_Rango,"",-1)),""))) | O95: =IF(OR($C95="",$N95=""),"",ROUND($J95*$N95,2)+ROUND($K95*$N95,2)) | P95: =IF($G95="","",IFERROR(INDEX(Catalogo_Tasas,MATCH($G95,Catalogo_Codigos,0)),"")) | Q95: =IF($G95="","",IFERROR(INDEX(Catalogo_Umbrales,MATCH($G95,Catalogo_Codigos,0)),"")) | R95: =IF(OR($C95="",$P95="",$O95=""),"",IF($F95<>"FACTURA","NO",IF(AND($P95>0,$O95>$Q95),"SI","NO"))) | S95: =IF($R95="SI",ROUND($O95*$P95,2),IF($C95="","",0)) | U95: =IF($C95="","",IF($R95<>"SI","",IF($T95="","SIN DATO",IF(ABS($T95-$S95)<=0.5,"OK","REVISAR")))) | W95: =IF(OR($C95="",$N95=""),"",IF($F95="RHE",ROUND($L95-$V95,2),ROUND($L95-($S95/$N95),2))) | AB95: PROVEEDOR
A96: 93 | B96: =DATE(2026,8,16) | C96: FC01-00001238 | D96: 20477906380 | E96: INVERSIONES TRES POR OCHO S.A.C. (LAS QOLQAS) | F96: NOTA DE CREDITO | G96: N/A | H96: =IF($G96="","",IFERROR(INDEX(Catalogo_Etiquetas,MATCH($G96,Catalogo_Codigos,0)),"CODIGO NO VALIDO")) | I96: USD | J96: -678.73 | K96: -71.27 | L96: =IF($C96="","",$J96+$K96) | M96: 639 | N96: =IF($C96="","",IF($I96="PEN",1,IFERROR(IF(_xlfn.XLOOKUP($B96,TC_Fechas,TC_Venta_Rango,"",-1)="","",_xlfn.XLOOKUP($B96,TC_Fechas,TC_Venta_Rango,"",-1)),""))) | O96: =IF(OR($C96="",$N96=""),"",ROUND($J96*$N96,2)+ROUND($K96*$N96,2)) | P96: =IF($G96="","",IFERROR(INDEX(Catalogo_Tasas,MATCH($G96,Catalogo_Codigos,0)),"")) | Q96: =IF($G96="","",IFERROR(INDEX(Catalogo_Umbrales,MATCH($G96,Catalogo_Codigos,0)),"")) | R96: =IF(OR($C96="",$P96="",$O96=""),"",IF($F96<>"FACTURA","NO",IF(AND($P96>0,$O96>$Q96),"SI","NO"))) | S96: =IF($R96="SI",ROUND($O96*$P96,2),IF($C96="","",0)) | U96: =IF($C96="","",IF($R96<>"SI","",IF($T96="","SIN DATO",IF(ABS($T96-$S96)<=0.5,"OK","REVISAR")))) | W96: =IF(OR($C96="",$N96=""),"",IF($F96="RHE",ROUND($L96-$V96,2),ROUND($L96-($S96/$N96),2))) | AB96: PROVEEDOR
A97: 94 | B97: =DATE(2026,8,7) | C97: FF20-00003162 | D97: 20536180657 | E97: LA CASA DE BARRANCO S.A.C (HOTEL B) | F97: NOTA DE CREDITO | G97: N/A | H97: =IF($G97="","",IFERROR(INDEX(Catalogo_Etiquetas,MATCH($G97,Catalogo_Codigos,0)),"CODIGO NO VALIDO")) | I97: USD | J97: -2432.03 | K97: -437.77 | L97: =IF($C97="","",$J97+$K97) | M97: 639 | N97: =IF($C97="","",IF($I97="PEN",1,IFERROR(IF(_xlfn.XLOOKUP($B97,TC_Fechas,TC_Venta_Rango,"",-1)="","",_xlfn.XLOOKUP($B97,TC_Fechas,TC_Venta_Rango,"",-1)),""))) | O97: =IF(OR($C97="",$N97=""),"",ROUND($J97*$N97,2)+ROUND($K97*$N97,2)) | P97: =IF($G97="","",IFERROR(INDEX(Catalogo_Tasas,MATCH($G97,Catalogo_Codigos,0)),"")) | Q97: =IF($G97="","",IFERROR(INDEX(Catalogo_Umbrales,MATCH($G97,Catalogo_Codigos,0)),"")) | R97: =IF(OR($C97="",$P97="",$O97=""),"",IF($F97<>"FACTURA","NO",IF(AND($P97>0,$O97>$Q97),"SI","NO"))) | S97: =IF($R97="SI",ROUND($O97*$P97,2),IF($C97="","",0)) | U97: =IF($C97="","",IF($R97<>"SI","",IF($T97="","SIN DATO",IF(ABS($T97-$S97)<=0.5,"OK","REVISAR")))) | W97: =IF(OR($C97="",$N97=""),"",IF($F97="RHE",ROUND($L97-$V97,2),ROUND($L97-($S97/$N97),2))) | AB97: PROVEEDOR
A98: 95 | B98: =DATE(2026,8,13) | C98: F001-10336 | D98: 20490257188 | E98: NATURA VIVE S.A.C. | F98: FACTURA | G98: N/A | H98: =IF($G98="","",IFERROR(INDEX(Catalogo_Etiquetas,MATCH($G98,Catalogo_Codigos,0)),"CODIGO NO VALIDO")) | I98: PEN | J98: 4371.04 | K98: 458.96 | L98: =IF($C98="","",$J98+$K98) | M98: 639 | N98: =IF($C98="","",IF($I98="PEN",1,IFERROR(IF(_xlfn.XLOOKUP($B98,TC_Fechas,TC_Venta_Rango,"",-1)="","",_xlfn.XLOOKUP($B98,TC_Fechas,TC_Venta_Rango,"",-1)),""))) | O98: =IF(OR($C98="",$N98=""),"",ROUND($J98*$N98,2)+ROUND($K98*$N98,2)) | P98: =IF($G98="","",IFERROR(INDEX(Catalogo_Tasas,MATCH($G98,Catalogo_Codigos,0)),"")) | Q98: =IF($G98="","",IFERROR(INDEX(Catalogo_Umbrales,MATCH($G98,Catalogo_Codigos,0)),"")) | R98: =IF(OR($C98="",$P98="",$O98=""),"",IF($F98<>"FACTURA","NO",IF(AND($P98>0,$O98>$Q98),"SI","NO"))) | S98: =IF($R98="SI",ROUND($O98*$P98,2),IF($C98="","",0)) | U98: =IF($C98="","",IF($R98<>"SI","",IF($T98="","SIN DATO",IF(ABS($T98-$S98)<=0.5,"OK","REVISAR")))) | W98: =IF(OR($C98="",$N98=""),"",IF($F98="RHE",ROUND($L98-$V98,2),ROUND($L98-($S98/$N98),2))) | AB98: PROVEEDOR
A99: 96 | B99: =DATE(2026,8,11) | C99: F001-00000736 | D99: 20603386214 | E99: PERUVIAN CULTURE TRAVEL AGENCIA DE VIAJES Y TURISMO S.R.L. | F99: FACTURA | G99: 037 | H99: =IF($G99="","",IFERROR(INDEX(Catalogo_Etiquetas,MATCH($G99,Catalogo_Codigos,0)),"CODIGO NO VALIDO")) | I99: USD | J99: 1040.68 | K99: 187.32 | L99: =IF($C99="","",$J99+$K99) | M99: 639 | N99: =IF($C99="","",IF($I99="PEN",1,IFERROR(IF(_xlfn.XLOOKUP($B99,TC_Fechas,TC_Venta_Rango,"",-1)="","",_xlfn.XLOOKUP($B99,TC_Fechas,TC_Venta_Rango,"",-1)),""))) | O99: =IF(OR($C99="",$N99=""),"",ROUND($J99*$N99,2)+ROUND($K99*$N99,2)) | P99: =IF($G99="","",IFERROR(INDEX(Catalogo_Tasas,MATCH($G99,Catalogo_Codigos,0)),"")) | Q99: =IF($G99="","",IFERROR(INDEX(Catalogo_Umbrales,MATCH($G99,Catalogo_Codigos,0)),"")) | R99: =IF(OR($C99="",$P99="",$O99=""),"",IF($F99<>"FACTURA","NO",IF(AND($P99>0,$O99>$Q99),"SI","NO"))) | S99: =IF($R99="SI",ROUND($O99*$P99,2),IF($C99="","",0)) | T99: 499.11 | U99: =IF($C99="","",IF($R99<>"SI","",IF($T99="","SIN DATO",IF(ABS($T99-$S99)<=0.5,"OK","REVISAR")))) | W99: =IF(OR($C99="",$N99=""),"",IF($F99="RHE",ROUND($L99-$V99,2),ROUND($L99-($S99/$N99),2))) | AB99: PROVEEDOR
A100: 97 | B100: =DATE(2026,8,14) | C100: E001- 503 | D100: 10422800102 | E100: SARMIENTO LOPEZ LUIS RONALD | F100: RHE | G100: N/A | H100: =IF($G100="","",IFERROR(INDEX(Catalogo_Etiquetas,MATCH($G100,Catalogo_Codigos,0)),"CODIGO NO VALIDO")) | I100: USD | J100: 87 | K100: 0 | L100: =IF($C100="","",$J100+$K100) | M100: 632 | N100: =IF($C100="","",IF($I100="PEN",1,IFERROR(IF(_xlfn.XLOOKUP($B100,TC_Fechas,TC_Venta_Rango,"",-1)="","",_xlfn.XLOOKUP($B100,TC_Fechas,TC_Venta_Rango,"",-1)),""))) | O100: =IF(OR($C100="",$N100=""),"",ROUND($J100*$N100,2)+ROUND($K100*$N100,2)) | P100: =IF($G100="","",IFERROR(INDEX(Catalogo_Tasas,MATCH($G100,Catalogo_Codigos,0)),"")) | Q100: =IF($G100="","",IFERROR(INDEX(Catalogo_Umbrales,MATCH($G100,Catalogo_Codigos,0)),"")) | R100: =IF(OR($C100="",$P100="",$O100=""),"",IF($F100<>"FACTURA","NO",IF(AND($P100>0,$O100>$Q100),"SI","NO"))) | S100: =IF($R100="SI",ROUND($O100*$P100,2),IF($C100="","",0)) | U100: =IF($C100="","",IF($R100<>"SI","",IF($T100="","SIN DATO",IF(ABS($T100-$S100)<=0.5,"OK","REVISAR")))) | V100: 6.96 | W100: =IF(OR($C100="",$N100=""),"",IF($F100="RHE",ROUND($L100-$V100,2),ROUND($L100-($S100/$N100),2))) | AB100: PROVEEDOR
...

Sheet Registro_Ventas
A1: Registro de Ventas — Comprobantes Emitidos a Clientes
A2: Caso normal: "¿Sujeto a Detracción Emitida?" = NO (Braidy Wonders casi siempre es el adquiriente, no el emisor, de servicios del Anexo 3). Marca SI solo si el servicio que facturas está en el catálogo (ej. transporte de personas).
A3: N° | B3: Fecha Emisión | C3: N° Comprobante | D3: RUC/Doc. Cliente | E3: Cliente | F3: Moneda | G3: Valor Venta | H3: IGV (18%) | I3: Total Factura | J3: ¿Sujeto a Detracción Emitida? | K3: Concepto (si aplica, elige de la lista) | L3: % Detracción | M3: Monto Detracción | N3: Neto a Cobrar | O3: ¿Cobrado? | P3: Fecha de Cobro | Q3: Estado | R3: ¿Exportación de Servicios Turísticos (No Domiciliado)?
A4: 1 | B4: 2026-08-10 | C4: F001-EJEMPLO | D4: 10999999999 | E4: Cliente de Ejemplo [BORRAR/REEMPLAZAR] | F4: USD | G4: 2000 | H4: =IF(C4="","",IF(R4="SI",0,G4*0.18)) | I4: =IF(C4="","",G4+H4) | J4: NO | L4: =IF(OR(C4="",J4<>"SI",K4=""),IF(C4="","",0),IFERROR(INDEX(Catalogo_Tasas,MATCH(K4,Catalogo_Etiquetas,0)),0)) | M4: =IF(C4="","",IF(J4="SI",ROUND(I4*L4,2),0)) | N4: =IF(C4="","",I4-M4) | O4: SI | P4: 2026-08-20 | Q4: EJEMPLO | R4: SI
A5: 2 | H5: =IF(C5="","",IF(R5="SI",0,G5*0.18)) | I5: =IF(C5="","",G5+H5) | L5: =IF(OR(C5="",J5<>"SI",K5=""),IF(C5="","",0),IFERROR(INDEX(Catalogo_Tasas,MATCH(K5,Catalogo_Etiquetas,0)),0)) | M5: =IF(C5="","",IF(J5="SI",ROUND(I5*L5,2),0)) | N5: =IF(C5="","",I5-M5)
A6: 3 | H6: =IF(C6="","",IF(R6="SI",0,G6*0.18)) | I6: =IF(C6="","",G6+H6) | L6: =IF(OR(C6="",J6<>"SI",K6=""),IF(C6="","",0),IFERROR(INDEX(Catalogo_Tasas,MATCH(K6,Catalogo_Etiquetas,0)),0)) | M6: =IF(C6="","",IF(J6="SI",ROUND(I6*L6,2),0)) | N6: =IF(C6="","",I6-M6)
A7: 4 | H7: =IF(C7="","",IF(R7="SI",0,G7*0.18)) | I7: =IF(C7="","",G7+H7) | L7: =IF(OR(C7="",J7<>"SI",K7=""),IF(C7="","",0),IFERROR(INDEX(Catalogo_Tasas,MATCH(K7,Catalogo_Etiquetas,0)),0)) | M7: =IF(C7="","",IF(J7="SI",ROUND(I7*L7,2),0)) | N7: =IF(C7="","",I7-M7)
A8: 5 | H8: =IF(C8="","",IF(R8="SI",0,G8*0.18)) | I8: =IF(C8="","",G8+H8) | L8: =IF(OR(C8="",J8<>"SI",K8=""),IF(C8="","",0),IFERROR(INDEX(Catalogo_Tasas,MATCH(K8,Catalogo_Etiquetas,0)),0)) | M8: =IF(C8="","",IF(J8="SI",ROUND(I8*L8,2),0)) | N8: =IF(C8="","",I8-M8)
A9: 6 | H9: =IF(C9="","",IF(R9="SI",0,G9*0.18)) | I9: =IF(C9="","",G9+H9) | L9: =IF(OR(C9="",J9<>"SI",K9=""),IF(C9="","",0),IFERROR(INDEX(Catalogo_Tasas,MATCH(K9,Catalogo_Etiquetas,0)),0)) | M9: =IF(C9="","",IF(J9="SI",ROUND(I9*L9,2),0)) | N9: =IF(C9="","",I9-M9)
A10: 7 | H10: =IF(C10="","",IF(R10="SI",0,G10*0.18)) | I10: =IF(C10="","",G10+H10) | L10: =IF(OR(C10="",J10<>"SI",K10=""),IF(C10="","",0),IFERROR(INDEX(Catalogo_Tasas,MATCH(K10,Catalogo_Etiquetas,0)),0)) | M10: =IF(C10="","",IF(J10="SI",ROUND(I10*L10,2),0)) | N10: =IF(C10="","",I10-M10)
A11: 8 | H11: =IF(C11="","",IF(R11="SI",0,G11*0.18)) | I11: =IF(C11="","",G11+H11) | L11: =IF(OR(C11="",J11<>"SI",K11=""),IF(C11="","",0),IFERROR(INDEX(Catalogo_Tasas,MATCH(K11,Catalogo_Etiquetas,0)),0)) | M11: =IF(C11="","",IF(J11="SI",ROUND(I11*L11,2),0)) | N11: =IF(C11="","",I11-M11)
A12: 9 | H12: =IF(C12="","",IF(R12="SI",0,G12*0.18)) | I12: =IF(C12="","",G12+H12) | L12: =IF(OR(C12="",J12<>"SI",K12=""),IF(C12="","",0),IFERROR(INDEX(Catalogo_Tasas,MATCH(K12,Catalogo_Etiquetas,0)),0)) | M12: =IF(C12="","",IF(J12="SI",ROUND(I12*L12,2),0)) | N12: =IF(C12="","",I12-M12)
A13: 10 | H13: =IF(C13="","",IF(R13="SI",0,G13*0.18)) | I13: =IF(C13="","",G13+H13) | L13: =IF(OR(C13="",J13<>"SI",K13=""),IF(C13="","",0),IFERROR(INDEX(Catalogo_Tasas,MATCH(K13,Catalogo_Etiquetas,0)),0)) | M13: =IF(C13="","",IF(J13="SI",ROUND(I13*L13,2),0)) | N13: =IF(C13="","",I13-M13)
A14: 11 | H14: =IF(C14="","",IF(R14="SI",0,G14*0.18)) | I14: =IF(C14="","",G14+H14) | L14: =IF(OR(C14="",J14<>"SI",K14=""),IF(C14="","",0),IFERROR(INDEX(Catalogo_Tasas,MATCH(K14,Catalogo_Etiquetas,0)),0)) | M14: =IF(C14="","",IF(J14="SI",ROUND(I14*L14,2),0)) | N14: =IF(C14="","",I14-M14)
A15: 12 | H15: =IF(C15="","",IF(R15="SI",0,G15*0.18)) | I15: =IF(C15="","",G15+H15) | L15: =IF(OR(C15="",J15<>"SI",K15=""),IF(C15="","",0),IFERROR(INDEX(Catalogo_Tasas,MATCH(K15,Catalogo_Etiquetas,0)),0)) | M15: =IF(C15="","",IF(J15="SI",ROUND(I15*L15,2),0)) | N15: =IF(C15="","",I15-M15)
A16: 13 | H16: =IF(C16="","",IF(R16="SI",0,G16*0.18)) | I16: =IF(C16="","",G16+H16) | L16: =IF(OR(C16="",J16<>"SI",K16=""),IF(C16="","",0),IFERROR(INDEX(Catalogo_Tasas,MATCH(K16,Catalogo_Etiquetas,0)),0)) | M16: =IF(C16="","",IF(J16="SI",ROUND(I16*L16,2),0)) | N16: =IF(C16="","",I16-M16)
... A53: 50 | H53: =IF(C53="","",IF(R53="SI",0,G53*0.18)) | I53: =IF(C53="","",G53+H53) | L53: =IF(OR(C53="",J53<>"SI",K53=""),IF(C53="","",0),IFERROR(INDEX(Catalogo_Tasas,MATCH(K53,Catalogo_Etiquetas,0)),0)) | M53: =IF(C53="","",IF(J53="SI",ROUND(I53*L53,2),0)) | N53: =IF(C53="","",I53-M53)

Sheet Libro_Diario
A1: Libro Diario - Braidy Wonders SAC
A2: Se genera solo desde Registro_Compras y Registro_Ventas. No editar a mano. Importes en PEN. Los asientos de deposito de detraccion y de pago del neto solo aparecen cuando la fecha real correspondiente esta cargada en el registro de origen.
A3: Fecha | B3: N° Asiento | C3: Cuenta | D3: Denominación | E3: Debe | F3: Haber | G3: Glosa | H3: Ref. Comprobante
A4: COMPRAS - Facturas de Proveedores
A5: =IF($C5="","",Registro_Compras!$B$4) | B5: =IF($C5="","","C"&TEXT(INT((ROW()-5)/9)+1,"000")&"-1") | C5: =IF(OR(Registro_Compras!$C$4="",Registro_Compras!$O$4=""),"",IF(Registro_Compras!$F$4="NOTA DE CREDITO","4212",IF(Registro_Compras!$M$4="","63",Registro_Compras!$M$4))) | D5: =IF(OR(Registro_Compras!$C$4="",Registro_Compras!$O$4=""),"",IF(Registro_Compras!$F$4="NOTA DE CREDITO","Cuentas por Pagar Comerciales - Terceros (Emitidas)",IF(Registro_Compras!$F$4="RHE","Honorarios Profesionales - Servicios de Terceros","Gastos de Servicios Prestados por Terceros"))) | E5: =IF($C5="","",IF(Registro_Compras!$F$4="NOTA DE CREDITO",ABS(Registro_Compras!$O$4),IF(Registro_Compras!$F$4="RHE",ROUND(Registro_Compras!$L$4*Registro_Compras!$N$4,2),ROUND(Registro_Compras!$J$4*Registro_Compras!$N$4,2)))) | F5: ="" | G5: =IF($C5="","",IF(Registro_Compras!$F$4="NOTA DE CREDITO","Por la nota de credito "&Registro_Compras!$C$4&" de "&Registro_Compras!$E$4&" [PATRON POR CONFIRMAR CON CONTADOR]",IF(Registro_Compras!$F$4="RHE","Por el registro del recibo por honorarios "&Registro_Compras!$C$4&" de "&Registro_Compras!$E$4&" [PATRON POR CONFIRMAR CON CONTADOR]","Por el registro de la factura "&Registro_Compras!$C$4&" de "&Registro_Compras!$E$4))) | H5: =IF($C5="","",Registro_Compras!$C$4)
A6: =IF($C6="","",Registro_Compras!$B$4) | B6: =IF($C6="","","C"&TEXT(INT((ROW()-5)/9)+1,"000")&"-1") | C6: =IF(OR(Registro_Compras!$C$4="",Registro_Compras!$O$4=""),"",IF(Registro_Compras!$F$4="RHE",IF(Registro_Compras!$V$4=0,"","40172"),IF(Registro_Compras!$F$4="NOTA DE CREDITO",IF(Registro_Compras!$M$4="","63",Registro_Compras!$M$4),IF(Registro_Compras!$K$4=0,"","40111")))) | D6: =IF(OR(Registro_Compras!$C$4="",Registro_Compras!$O$4=""),"",IF(Registro_Compras!$F$4="RHE","Retencion Renta 4ta Categoria por Pagar",IF(Registro_Compras!$F$4="NOTA DE CREDITO","Gastos de Servicios Prestados por Terceros","IGV - Cuenta Propia (Credito Fiscal)"))) | E6: =IF($C6="","",IF(Registro_Compras!$F$4="FACTURA",ROUND(Registro_Compras!$K$4*Registro_Compras!$N$4,2),"")) | F6: =IF($C6="","",IF(Registro_Compras!$F$4="RHE",ROUND(Registro_Compras!$V$4*Registro_Compras!$N$4,2),IF(Registro_Compras!$F$4="NOTA DE CREDITO",ROUND(ABS(Registro_Compras!$J$4*Registro_Compras!$N$4),2),""))) | G6: =IF($C6="","",IF(Registro_Compras!$F$4="NOTA DE CREDITO","Por la nota de credito "&Registro_Compras!$C$4&" de "&Registro_Compras!$E$4&" [PATRON POR CONFIRMAR CON CONTADOR]",IF(Registro_Compras!$F$4="RHE","Por el registro del recibo por honorarios "&Registro_Compras!$C$4&" de "&Registro_Compras!$E$4&" [PATRON POR CONFIRMAR CON CONTADOR]","Por el registro de la factura "&Registro_Compras!$C$4&" de "&Registro_Compras!$E$4))) | H6: =IF($C6="","",Registro_Compras!$C$4)
A7: =IF($C7="","",Registro_Compras!$B$4) | B7: =IF($C7="","","C"&TEXT(INT((ROW()-5)/9)+1,"000")&"-1") | C7: =IF(OR(Registro_Compras!$C$4="",Registro_Compras!$O$4=""),"",IF(Registro_Compras!$F$4="NOTA DE CREDITO",IF(Registro_Compras!$K$4=0,"","40111"),"4212")) | D7: =IF(OR(Registro_Compras!$C$4="",Registro_Compras!$O$4=""),"",IF(Registro_Compras!$F$4="NOTA DE CREDITO","IGV - Cuenta Propia (Credito Fiscal)","Cuentas por Pagar Comerciales - Terceros (Emitidas)")) | E7: ="" | F7: =IF($C7="","",IF(Registro_Compras!$F$4="NOTA DE CREDITO",ROUND(ABS(Registro_Compras!$K$4*Registro_Compras!$N$4),2),IF(Registro_Compras!$F$4="RHE",(ROUND(Registro_Compras!$L$4*Registro_Compras!$N$4,2)-ROUND(Registro_Compras!$V$4*Registro_Compras!$N$4,2)),Registro_Compras!$O$4))) | G7: =IF($C7="","",IF(Registro_Compras!$F$4="NOTA DE CREDITO","Por la nota de credito "&Registro_Compras!$C$4&" de "&Registro_Compras!$E$4&" [PATRON POR CONFIRMAR CON CONTADOR]",IF(Registro_Compras!$F$4="RHE","Por el registro del recibo por honorarios "&Registro_Compras!$C$4&" de "&Registro_Compras!$E$4&" [PATRON POR CONFIRMAR CON CONTADOR]","Por el registro de la factura "&Registro_Compras!$C$4&" de "&Registro_Compras!$E$4))) | H7: =IF($C7="","",Registro_Compras!$C$4)
A8: =IF($C8="","",Registro_Compras!$B$4) | B8: =IF($C8="","","C"&TEXT(INT((ROW()-5)/9)+1,"000")&"-2") | C8: =IF(OR(Registro_Compras!$C$4="",Registro_Compras!$O$4=""),"",IF(Registro_Compras!$AB$4="ADMINISTRATIVO","94","95")) | D8: =IF(OR(Registro_Compras!$C$4="",Registro_Compras!$O$4=""),"",IF(Registro_Compras!$AB$4="ADMINISTRATIVO","Gastos Administrativos","Gastos de Venta y Operacion")) | E8: =IF($C8="","",IF(Registro_Compras!$F$4="NOTA DE CREDITO","",IF(Registro_Compras!$F$4="RHE",ROUND(Registro_Compras!$L$4*Registro_Compras!$N$4,2),ROUND(Registro_Compras!$J$4*Registro_Compras!$N$4,2)))) | F8: =IF($C8="","",IF(Registro_Compras!$F$4="NOTA DE CREDITO",ROUND(ABS(Registro_Compras!$J$4*Registro_Compras!$N$4),2),"")) | G8: =IF($C8="","","Por el destino del gasto") | H8: =IF($C8="","",Registro_Compras!$C$4)
A9: =IF($C9="","",Registro_Compras!$B$4) | B9: =IF($C9="","","C"&TEXT(INT((ROW()-5)/9)+1,"000")&"-2") | C9: =IF(OR(Registro_Compras!$C$4="",Registro_Compras!$O$4=""),"","79/791") | D9: =IF(OR(Registro_Compras!$C$4="",Registro_Compras!$O$4=""),"","Cargas Imputables a Cuentas de Costos y Gastos") | E9: =IF($C9="","",IF(Registro_Compras!$F$4="NOTA DE CREDITO",ROUND(ABS(Registro_Compras!$J$4*Registro_Compras!$N$4),2),"")) | F9: =IF($C9="","",IF(Registro_Compras!$F$4="NOTA DE CREDITO","",IF(Registro_Compras!$F$4="RHE",ROUND(Registro_Compras!$L$4*Registro_Compras!$N$4,2),ROUND(Registro_Compras!$J$4*Registro_Compras!$N$4,2)))) | G9: =IF($C9="","","Por el destino del gasto") | H9: =IF($C9="","",Registro_Compras!$C$4)
A10: =IF($C10="","",Registro_Compras!$X$4) | B10: =IF($C10="","","C"&TEXT(INT((ROW()-5)/9)+1,"000")&"-3") | C10: =IF(OR(Registro_Compras!$C$4="",Registro_Compras!$O$4="",Registro_Compras!$R$4<>"SI",Registro_Compras!$X$4=""),"","4212") | D10: =IF(OR(Registro_Compras!$C$4="",Registro_Compras!$O$4=""),"","Cuentas por Pagar Comerciales - Terceros") | E10: =IF($C10="","",Registro_Compras!$S$4) | F10: ="" | G10: =IF($C10="","","Por el deposito de la detraccion en el Banco de la Nacion") | H10: =IF($C10="","",Registro_Compras!$C$4)
A11: =IF($C11="","",Registro_Compras!$X$4) | B11: =IF($C11="","","C"&TEXT(INT((ROW()-5)/9)+1,"000")&"-3") | C11: =IF(OR(Registro_Compras!$C$4="",Registro_Compras!$O$4="",Registro_Compras!$R$4<>"SI",Registro_Compras!$X$4=""),"","10413") | D11: =IF(OR(Registro_Compras!$C$4="",Registro_Compras!$O$4=""),"","Efectivo y Equivalentes - Cta. Cte. Operativa") | E11: ="" | F11: =IF($C11="","",Registro_Compras!$S$4) | G11: =IF($C11="","","Por el deposito de la detraccion en el Banco de la Nacion") | H11: =IF($C11="","",Registro_Compras!$C$4)
A12: =IF($C12="","",Registro_Compras!$Y$4) | B12: =IF($C12="","","C"&TEXT(INT((ROW()-5)/9)+1,"000")&"-4") | C12: =IF(OR(Registro_Compras!$C$4="",Registro_Compras!$O$4="",Registro_Compras!$Y$4="",Registro_Compras!$F$4="NOTA DE CREDITO"),"","4212") | D12: =IF(OR(Registro_Compras!$C$4="",Registro_Compras!$O$4=""),"","Cuentas por Pagar Comerciales - Terceros") | E12: =IF($C12="","",IF(Registro_Compras!$F$4="RHE",(ROUND(Registro_Compras!$L$4*Registro_Compras!$N$4,2)-ROUND(Registro_Compras!$V$4*Registro_Compras!$N$4,2)),ROUND(Registro_Compras!$O$4-Registro_Compras!$S$4,2))) | F12: ="" | G12: =IF($C12="","","Por la cancelacion del saldo al proveedor") | H12: =IF($C12="","",Registro_Compras!$C$4)
A13: =IF($C13="","",Registro_Compras!$Y$4) | B13: =IF($C13="","","C"&TEXT(INT((ROW()-5)/9)+1,"000")&"-4") | C13: =IF(OR(Registro_Compras!$C$4="",Registro_Compras!$O$4="",Registro_Compras!$Y$4="",Registro_Compras!$F$4="NOTA DE CREDITO"),"","10413") | D13: =IF(OR(Registro_Compras!$C$4="",Registro_Compras!$O$4=""),"","Efectivo y Equivalentes - Cta. Cte. Operativa") | E13: ="" | F13: =IF($C13="","",IF(Registro_Compras!$F$4="RHE",(ROUND(Registro_Compras!$L$4*Registro_Compras!$N$4,2)-ROUND(Registro_Compras!$V$4*Registro_Compras!$N$4,2)),ROUND(Registro_Compras!$O$4-Registro_Compras!$S$4,2))) | G13: =IF($C13="","","Por la cancelacion del saldo al proveedor") | H13: =IF($C13="","",Registro_Compras!$C$4)
A14: =IF($C14="","",Registro_Compras!$B$5) | B14: =IF($C14="","","C"&TEXT(INT((ROW()-5)/9)+1,"000")&"-1") | C14: =IF(OR(Registro_Compras!$C$5="",Registro_Compras!$O$5=""),"",IF(Registro_Compras!$F$5="NOTA DE CREDITO","4212",IF(Registro_Compras!$M$5="","63",Registro_Compras!$M$5))) | D14: =IF(OR(Registro_Compras!$C$5="",Registro_Compras!$O$5=""),"",IF(Registro_Compras!$F$5="NOTA DE CREDITO","Cuentas por Pagar Comerciales - Terceros (Emitidas)",IF(Registro_Compras!$F$5="RHE","Honorarios Profesionales - Servicios de Terceros","Gastos de Servicios Prestados por Terceros"))) | E14: =IF($C14="","",IF(Registro_Compras!$F$5="NOTA DE CREDITO",ABS(Registro_Compras!$O$5),IF(Registro_Compras!$F$5="RHE",ROUND(Registro_Compras!$L$5*Registro_Compras!$N$5,2),ROUND(Registro_Compras!$J$5*Registro_Compras!$N$5,2)))) | F14: ="" | G14: =IF($C14="","",IF(Registro_Compras!$F$5="NOTA DE CREDITO","Por la nota de credito "&Registro_Compras!$C$5&" de "&Registro_Compras!$E$5&" [PATRON POR CONFIRMAR CON CONTADOR]",IF(Registro_Compras!$F$5="RHE","Por el registro del recibo por honorarios "&Registro_Compras!$C$5&" de "&Registro_Compras!$E$5&" [PATRON POR CONFIRMAR CON CONTADOR]","Por el registro de la factura "&Registro_Compras!$C$5&" de "&Registro_Compras!$E$5))) | H14: =IF($C14="","",Registro_Compras!$C$5)
A15: =IF($C15="","",Registro_Compras!$B$5) | B15: =IF($C15="","","C"&TEXT(INT((ROW()-5)/9)+1,"000")&"-1") | C15: =IF(OR(Registro_Compras!$C$5="",Registro_Compras!$O$5=""),"",IF(Registro_Compras!$F$5="RHE",IF(Registro_Compras!$V$5=0,"","40172"),IF(Registro_Compras!$F$5="NOTA DE CREDITO",IF(Registro_Compras!$M$5="","63",Registro_Compras!$M$5),IF(Registro_Compras!$K$5=0,"","40111")))) | D15: =IF(OR(Registro_Compras!$C$5="",Registro_Compras!$O$5=""),"",IF(Registro_Compras!$F$5="RHE","Retencion Renta 4ta Categoria por Pagar",IF(Registro_Compras!$F$5="NOTA DE CREDITO","Gastos de Servicios Prestados por Terceros","IGV - Cuenta Propia (Credito Fiscal)"))) | E15: =IF($C15="","",IF(Registro_Compras!$F$5="FACTURA",ROUND(Registro_Compras!$K$5*Registro_Compras!$N$5,2),"")) | F15: =IF($C15="","",IF(Registro_Compras!$F$5="RHE",ROUND(Registro_Compras!$V$5*Registro_Compras!$N$5,2),IF(Registro_Compras!$F$5="NOTA DE CREDITO",ROUND(ABS(Registro_Compras!$J$5*Registro_Compras!$N$5),2),""))) | G15: =IF($C15="","",IF(Registro_Compras!$F$5="NOTA DE CREDITO","Por la nota de credito "&Registro_Compras!$C$5&" de "&Registro_Compras!$E$5&" [PATRON POR CONFIRMAR CON CONTADOR]",IF(Registro_Compras!$F$5="RHE","Por el registro del recibo por honorarios "&Registro_Compras!$C$5&" de "&Registro_Compras!$E$5&" [PATRON POR CONFIRMAR CON CONTADOR]","Por el registro de la factura "&Registro_Compras!$C$5&" de "&Registro_Compras!$E$5))) | H15: =IF($C15="","",Registro_Compras!$C$5)
A16: =IF($C16="","",Registro_Compras!$B$5) | B16: =IF($C16="","","C"&TEXT(INT((ROW()-5)/9)+1,"000")&"-1") | C16: =IF(OR(Registro_Compras!$C$5="",Registro_Compras!$O$5=""),"",IF(Registro_Compras!$F$5="NOTA DE CREDITO",IF(Registro_Compras!$K$5=0,"","40111"),"4212")) | D16: =IF(OR(Registro_Compras!$C$5="",Registro_Compras!$O$5=""),"",IF(Registro_Compras!$F$5="NOTA DE CREDITO","IGV - Cuenta Propia (Credito Fiscal)","Cuentas por Pagar Comerciales - Terceros (Emitidas)")) | E16: ="" | F16: =IF($C16="","",IF(Registro_Compras!$F$5="NOTA DE CREDITO",ROUND(ABS(Registro_Compras!$K$5*Registro_Compras!$N$5),2),IF(Registro_Compras!$F$5="RHE",(ROUND(Registro_Compras!$L$5*Registro_Compras!$N$5,2)-ROUND(Registro_Compras!$V$5*Registro_Compras!$N$5,2)),Registro_Compras!$O$5))) | G16: =IF($C16="","",IF(Registro_Compras!$F$5="NOTA DE CREDITO","Por la nota de credito "&Registro_Compras!$C$5&" de "&Registro_Compras!$E$5&" [PATRON POR CONFIRMAR CON CONTADOR]",IF(Registro_Compras!$F$5="RHE","Por el registro del recibo por honorarios "&Registro_Compras!$C$5&" de "&Registro_Compras!$E$5&" [PATRON POR CONFIRMAR CON CONTADOR]","Por el registro de la factura "&Registro_Compras!$C$5&" de "&Registro_Compras!$E$5))) | H16: =IF($C16="","",Registro_Compras!$C$5)
A17: =IF($C17="","",Registro_Compras!$B$5) | B17: =IF($C17="","","C"&TEXT(INT((ROW()-5)/9)+1,"000")&"-2") | C17: =IF(OR(Registro_Compras!$C$5="",Registro_Compras!$O$5=""),"",IF(Registro_Compras!$AB$5="ADMINISTRATIVO","94","95")) | D17: =IF(OR(Registro_Compras!$C$5="",Registro_Compras!$O$5=""),"",IF(Registro_Compras!$AB$5="ADMINISTRATIVO","Gastos Administrativos","Gastos de Venta y Operacion")) | E17: =IF($C17="","",IF(Registro_Compras!$F$5="NOTA DE CREDITO","",IF(Registro_Compras!$F$5="RHE",ROUND(Registro_Compras!$L$5*Registro_Compras!$N$5,2),ROUND(Registro_Compras!$J$5*Registro_Compras!$N$5,2)))) | F17: =IF($C17="","",IF(Registro_Compras!$F$5="NOTA DE CREDITO",ROUND(ABS(Registro_Compras!$J$5*Registro_Compras!$N$5),2),"")) | G17: =IF($C17="","","Por el destino del gasto") | H17: =IF($C17="","",Registro_Compras!$C$5)
A18: =IF($C18="","",Registro_Compras!$B$5) | B18: =IF($C18="","","C"&TEXT(INT((ROW()-5)/9)+1,"000")&"-2") | C18: =IF(OR(Registro_Compras!$C$5="",Registro_Compras!$O$5=""),"","79/791") | D18: =IF(OR(Registro_Compras!$C$5="",Registro_Compras!$O$5=""),"","Cargas Imputables a Cuentas de Costos y Gastos") | E18: =IF($C18="","",IF(Registro_Compras!$F$5="NOTA DE CREDITO",ROUND(ABS(Registro_Compras!$J$5*Registro_Compras!$N$5),2),"")) | F18: =IF($C18="","",IF(Registro_Compras!$F$5="NOTA DE CREDITO","",IF(Registro_Compras!$F$5="RHE",ROUND(Registro_Compras!$L$5*Registro_Compras!$N$5,2),ROUND(Registro_Compras!$J$5*Registro_Compras!$N$5,2)))) | G18: =IF($C18="","","Por el destino del gasto") | H18: =IF($C18="","",Registro_Compras!$C$5)
A19: =IF($C19="","",Registro_Compras!$X$5) | B19: =IF($C19="","","C"&TEXT(INT((ROW()-5)/9)+1,"000")&"-3") | C19: =IF(OR(Registro_Compras!$C$5="",Registro_Compras!$O$5="",Registro_Compras!$R$5<>"SI",Registro_Compras!$X$5=""),"","4212") | D19: =IF(OR(Registro_Compras!$C$5="",Registro_Compras!$O$5=""),"","Cuentas por Pagar Comerciales - Terceros") | E19: =IF($C19="","",Registro_Compras!$S$5) | F19: ="" | G19: =IF($C19="","","Por el deposito de la detraccion en el Banco de la Nacion") | H19: =IF($C19="","",Registro_Compras!$C$5)
A20: =IF($C20="","",Registro_Compras!$X$5) | B20: =IF($C20="","","C"&TEXT(INT((ROW()-5)/9)+1,"000")&"-3") | C20: =IF(OR(Registro_Compras!$C$5="",Registro_Compras!$O$5="",Registro_Compras!$R$5<>"SI",Registro_Compras!$X$5=""),"","10413") | D20: =IF(OR(Registro_Compras!$C$5="",Registro_Compras!$O$5=""),"","Efectivo y Equivalentes - Cta. Cte. Operativa") | E20: ="" | F20: =IF($C20="","",Registro_Compras!$S$5) | G20: =IF($C20="","","Por el deposito de la detraccion en el Banco de la Nacion") | H20: =IF($C20="","",Registro_Compras!$C$5)
A21: =IF($C21="","",Registro_Compras!$Y$5) | B21: =IF($C21="","","C"&TEXT(INT((ROW()-5)/9)+1,"000")&"-4") | C21: =IF(OR(Registro_Compras!$C$5="",Registro_Compras!$O$5="",Registro_Compras!$Y$5="",Registro_Compras!$F$5="NOTA DE CREDITO"),"","4212") | D21: =IF(OR(Registro_Compras!$C$5="",Registro_Compras!$O$5=""),"","Cuentas por Pagar Comerciales - Terceros") | E21: =IF($C21="","",IF(Registro_Compras!$F$5="RHE",(ROUND(Registro_Compras!$L$5*Registro_Compras!$N$5,2)-ROUND(Registro_Compras!$V$5*Registro_Compras!$N$5,2)),ROUND(Registro_Compras!$O$5-Registro_Compras!$S$5,2))) | F21: ="" | G21: =IF($C21="","","Por la cancelacion del saldo al proveedor") | H21: =IF($C21="","",Registro_Compras!$C$5)
A22: =IF($C22="","",Registro_Compras!$Y$5) | B22: =IF($C22="","","C"&TEXT(INT((ROW()-5)/9)+1,"000")&"-4") | C22: =IF(OR(Registro_Compras!$C$5="",Registro_Compras!$O$5="",Registro_Compras!$Y$5="",Registro_Compras!$F$5="NOTA DE CREDITO"),"","10413") | D22: =IF(OR(Registro_Compras!$C$5="",Registro_Compras!$O$5=""),"","Efectivo y Equivalentes - Cta. Cte. Operativa") | E22: ="" | F22: =IF($C22="","",IF(Registro_Compras!$F$5="RHE",(ROUND(Registro_Compras!$L$5*Registro_Compras!$N$5,2)-ROUND(Registro_Compras!$V$5*Registro_Compras!$N$5,2)),ROUND(Registro_Compras!$O$5-Registro_Compras!$S$5,2))) | G22: =IF($C22="","","Por la cancelacion del saldo al proveedor") | H22: =IF($C22="","",Registro_Compras!$C$5)
A23: =IF($C23="","",Registro_Compras!$B$6) | B23: =IF($C23="","","C"&TEXT(INT((ROW()-5)/9)+1,"000")&"-1") | C23: =IF(OR(Registro_Compras!$C$6="",Registro_Compras!$O$6=""),"",IF(Registro_Compras!$F$6="NOTA DE CREDITO","4212",IF(Registro_Compras!$M$6="","63",Registro_Compras!$M$6))) | D23: =IF(OR(Registro_Compras!$C$6="",Registro_Compras!$O$6=""),"",IF(Registro_Compras!$F$6="NOTA DE CREDITO","Cuentas por Pagar Comerciales - Terceros (Emitidas)",IF(Registro_Compras!$F$6="RHE","Honorarios Profesionales - Servicios de Terceros","Gastos de Servicios Prestados por Terceros"))) | E23: =IF($C23="","",IF(Registro_Compras!$F$6="NOTA DE CREDITO",ABS(Registro_Compras!$O$6),IF(Registro_Compras!$F$6="RHE",ROUND(Registro_Compras!$L$6*Registro_Compras!$N$6,2),ROUND(Registro_Compras!$J$6*Registro_Compras!$N$6,2)))) | F23: ="" | G23: =IF($C23="","",IF(Registro_Compras!$F$6="NOTA DE CREDITO","Por la nota de credito "&Registro_Compras!$C$6&" de "&Registro_Compras!$E$6&" [PATRON POR CONFIRMAR CON CONTADOR]",IF(Registro_Compras!$F$6="RHE","Por el registro del recibo por honorarios "&Registro_Compras!$C$6&" de "&Registro_Compras!$E$6&" [PATRON POR CONFIRMAR CON CONTADOR]","Por el registro de la factura "&Registro_Compras!$C$6&" de "&Registro_Compras!$E$6))) | H23: =IF($C23="","",Registro_Compras!$C$6)
A24: =IF($C24="","",Registro_Compras!$B$6) | B24: =IF($C24="","","C"&TEXT(INT((ROW()-5)/9)+1,"000")&"-1") | C24: =IF(OR(Registro_Compras!$C$6="",Registro_Compras!$O$6=""),"",IF(Registro_Compras!$F$6="RHE",IF(Registro_Compras!$V$6=0,"","40172"),IF(Registro_Compras!$F$6="NOTA DE CREDITO",IF(Registro_Compras!$M$6="","63",Registro_Compras!$M$6),IF(Registro_Compras!$K$6=0,"","40111")))) | D24: =IF(OR(Registro_Compras!$C$6="",Registro_Compras!$O$6=""),"",IF(Registro_Compras!$F$6="RHE","Retencion Renta 4ta Categoria por Pagar",IF(Registro_Compras!$F$6="NOTA DE CREDITO","Gastos de Servicios Prestados por Terceros","IGV - Cuenta Propia (Credito Fiscal)"))) | E24: =IF($C24="","",IF(Registro_Compras!$F$6="FACTURA",ROUND(Registro_Compras!$K$6*Registro_Compras!$N$6,2),"")) | F24: =IF($C24="","",IF(Registro_Compras!$F$6="RHE",ROUND(Registro_Compras!$V$6*Registro_Compras!$N$6,2),IF(Registro_Compras!$F$6="NOTA DE CREDITO",ROUND(ABS(Registro_Compras!$J$6*Registro_Compras!$N$6),2),""))) | G24: =IF($C24="","",IF(Registro_Compras!$F$6="NOTA DE CREDITO","Por la nota de credito "&Registro_Compras!$C$6&" de "&Registro_Compras!$E$6&" [PATRON POR CONFIRMAR CON CONTADOR]",IF(Registro_Compras!$F$6="RHE","Por el registro del recibo por honorarios "&Registro_Compras!$C$6&" de "&Registro_Compras!$E$6&" [PATRON POR CONFIRMAR CON CONTADOR]","Por el registro de la factura "&Registro_Compras!$C$6&" de "&Registro_Compras!$E$6))) | H24: =IF($C24="","",Registro_Compras!$C$6)
A25: =IF($C25="","",Registro_Compras!$B$6) | B25: =IF($C25="","","C"&TEXT(INT((ROW()-5)/9)+1,"000")&"-1") | C25: =IF(OR(Registro_Compras!$C$6="",Registro_Compras!$O$6=""),"",IF(Registro_Compras!$F$6="NOTA DE CREDITO",IF(Registro_Compras!$K$6=0,"","40111"),"4212")) | D25: =IF(OR(Registro_Compras!$C$6="",Registro_Compras!$O$6=""),"",IF(Registro_Compras!$F$6="NOTA DE CREDITO","IGV - Cuenta Propia (Credito Fiscal)","Cuentas por Pagar Comerciales - Terceros (Emitidas)")) | E25: ="" | F25: =IF($C25="","",IF(Registro_Compras!$F$6="NOTA DE CREDITO",ROUND(ABS(Registro_Compras!$K$6*Registro_Compras!$N$6),2),IF(Registro_Compras!$F$6="RHE",(ROUND(Registro_Compras!$L$6*Registro_Compras!$N$6,2)-ROUND(Registro_Compras!$V$6*Registro_Compras!$N$6,2)),Registro_Compras!$O$6))) | G25: =IF($C25="","",IF(Registro_Compras!$F$6="NOTA DE CREDITO","Por la nota de credito "&Registro_Compras!$C$6&" de "&Registro_Compras!$E$6&" [PATRON POR CONFIRMAR CON CONTADOR]",IF(Registro_Compras!$F$6="RHE","Por el registro del recibo por honorarios "&Registro_Compras!$C$6&" de "&Registro_Compras!$E$6&" [PATRON POR CONFIRMAR CON CONTADOR]","Por el registro de la factura "&Registro_Compras!$C$6&" de "&Registro_Compras!$E$6))) | H25: =IF($C25="","",Registro_Compras!$C$6)
A26: =IF($C26="","",Registro_Compras!$B$6) | B26: =IF($C26="","","C"&TEXT(INT((ROW()-5)/9)+1,"000")&"-2") | C26: =IF(OR(Registro_Compras!$C$6="",Registro_Compras!$O$6=""),"",IF(Registro_Compras!$AB$6="ADMINISTRATIVO","94","95")) | D26: =IF(OR(Registro_Compras!$C$6="",Registro_Compras!$O$6=""),"",IF(Registro_Compras!$AB$6="ADMINISTRATIVO","Gastos Administrativos","Gastos de Venta y Operacion")) | E26: =IF($C26="","",IF(Registro_Compras!$F$6="NOTA DE CREDITO","",IF(Registro_Compras!$F$6="RHE",ROUND(Registro_Compras!$L$6*Registro_Compras!$N$6,2),ROUND(Registro_Compras!$J$6*Registro_Compras!$N$6,2)))) | F26: =IF($C26="","",IF(Registro_Compras!$F$6="NOTA DE CREDITO",ROUND(ABS(Registro_Compras!$J$6*Registro_Compras!$N$6),2),"")) | G26: =IF($C26="","","Por el destino del gasto") | H26: =IF($C26="","",Registro_Compras!$C$6)
A27: =IF($C27="","",Registro_Compras!$B$6) | B27: =IF($C27="","","C"&TEXT(INT((ROW()-5)/9)+1,"000")&"-2") | C27: =IF(OR(Registro_Compras!$C$6="",Registro_Compras!$O$6=""),"","79/791") | D27: =IF(OR(Registro_Compras!$C$6="",Registro_Compras!$O$6=""),"","Cargas Imputables a Cuentas de Costos y Gastos") | E27: =IF($C27="","",IF(Registro_Compras!$F$6="NOTA DE CREDITO",ROUND(ABS(Registro_Compras!$J$6*Registro_Compras!$N$6),2),"")) | F27: =IF($C27="","",IF(Registro_Compras!$F$6="NOTA DE CREDITO","",IF(Registro_Compras!$F$6="RHE",ROUND(Registro_Compras!$L$6*Registro_Compras!$N$6,2),ROUND(Registro_Compras!$J$6*Registro_Compras!$N$6,2)))) | G27: =IF($C27="","","Por el destino del gasto") | H27: =IF($C27="","",Registro_Compras!$C$6)
A28: =IF($C28="","",Registro_Compras!$X$6) | B28: =IF($C28="","","C"&TEXT(INT((ROW()-5)/9)+1,"000")&"-3") | C28: =IF(OR(Registro_Compras!$C$6="",Registro_Compras!$O$6="",Registro_Compras!$R$6<>"SI",Registro_Compras!$X$6=""),"","4212") | D28: =IF(OR(Registro_Compras!$C$6="",Registro_Compras!$O$6=""),"","Cuentas por Pagar Comerciales - Terceros") | E28: =IF($C28="","",Registro_Compras!$S$6) | F28: ="" | G28: =IF($C28="","","Por el deposito de la detraccion en el Banco de la Nacion") | H28: =IF($C28="","",Registro_Compras!$C$6)
A29: =IF($C29="","",Registro_Compras!$X$6) | B29: =IF($C29="","","C"&TEXT(INT((ROW()-5)/9)+1,"000")&"-3") | C29: =IF(OR(Registro_Compras!$C$6="",Registro_Compras!$O$6="",Registro_Compras!$R$6<>"SI",Registro_Compras!$X$6=""),"","10413") | D29: =IF(OR(Registro_Compras!$C$6="",Registro_Compras!$O$6=""),"","Efectivo y Equivalentes - Cta. Cte. Operativa") | E29: ="" | F29: =IF($C29="","",Registro_Compras!$S$6) | G29: =IF($C29="","","Por el deposito de la detraccion en el Banco de la Nacion") | H29: =IF($C29="","",Registro_Compras!$C$6)
A30: =IF($C30="","",Registro_Compras!$Y$6) | B30: =IF($C30="","","C"&TEXT(INT((ROW()-5)/9)+1,"000")&"-4") | C30: =IF(OR(Registro_Compras!$C$6="",Registro_Compras!$O$6="",Registro_Compras!$Y$6="",Registro_Compras!$F$6="NOTA DE CREDITO"),"","4212") | D30: =IF(OR(Registro_Compras!$C$6="",Registro_Compras!$O$6=""),"","Cuentas por Pagar Comerciales - Terceros") | E30: =IF($C30="","",IF(Registro_Compras!$F$6="RHE",(ROUND(Registro_Compras!$L$6*Registro_Compras!$N$6,2)-ROUND(Registro_Compras!$V$6*Registro_Compras!$N$6,2)),ROUND(Registro_Compras!$O$6-Registro_Compras!$S$6,2))) | F30: ="" | G30: =IF($C30="","","Por la cancelacion del saldo al proveedor") | H30: =IF($C30="","",Registro_Compras!$C$6)
A31: =IF($C31="","",Registro_Compras!$Y$6) | B31: =IF($C31="","","C"&TEXT(INT((ROW()-5)/9)+1,"000")&"-4") | C31: =IF(OR(Registro_Compras!$C$6="",Registro_Compras!$O$6="",Registro_Compras!$Y$6="",Registro_Compras!$F$6="NOTA DE CREDITO"),"","10413") | D31: =IF(OR(Registro_Compras!$C$6="",Registro_Compras!$O$6=""),"","Efectivo y Equivalentes - Cta. Cte. Operativa") | E31: ="" | F31: =IF($C31="","",IF(Registro_Compras!$F$6="RHE",(ROUND(Registro_Compras!$L$6*Registro_Compras!$N$6,2)-ROUND(Registro_Compras!$V$6*Registro_Compras!$N$6,2)),ROUND(Registro_Compras!$O$6-Registro_Compras!$S$6,2))) | G31: =IF($C31="","","Por la cancelacion del saldo al proveedor") | H31: =IF($C31="","",Registro_Compras!$C$6)
A32: =IF($C32="","",Registro_Compras!$B$7) | B32: =IF($C32="","","C"&TEXT(INT((ROW()-5)/9)+1,"000")&"-1") | C32: =IF(OR(Registro_Compras!$C$7="",Registro_Compras!$O$7=""),"",IF(Registro_Compras!$F$7="NOTA DE CREDITO","4212",IF(Registro_Compras!$M$7="","63",Registro_Compras!$M$7))) | D32: =IF(OR(Registro_Compras!$C$7="",Registro_Compras!$O$7=""),"",IF(Registro_Compras!$F$7="NOTA DE CREDITO","Cuentas por Pagar Comerciales - Terceros (Emitidas)",IF(Registro_Compras!$F$7="RHE","Honorarios Profesionales - Servicios de Terceros","Gastos de Servicios Prestados por Terceros"))) | E32: =IF($C32="","",IF(Registro_Compras!$F$7="NOTA DE CREDITO",ABS(Registro_Compras!$O$7),IF(Registro_Compras!$F$7="RHE",ROUND(Registro_Compras!$L$7*Registro_Compras!$N$7,2),ROUND(Registro_Compras!$J$7*Registro_Compras!$N$7,2)))) | F32: ="" | G32: =IF($C32="","",IF(Registro_Compras!$F$7="NOTA DE CREDITO","Por la nota de credito "&Registro_Compras!$C$7&" de "&Registro_Compras!$E$7&" [PATRON POR CONFIRMAR CON CONTADOR]",IF(Registro_Compras!$F$7="RHE","Por el registro del recibo por honorarios "&Registro_Compras!$C$7&" de "&Registro_Compras!$E$7&" [PATRON POR CONFIRMAR CON CONTADOR]","Por el registro de la factura "&Registro_Compras!$C$7&" de "&Registro_Compras!$E$7))) | H32: =IF($C32="","",Registro_Compras!$C$7)
A33: =IF($C33="","",Registro_Compras!$B$7) | B33: =IF($C33="","","C"&TEXT(INT((ROW()-5)/9)+1,"000")&"-1") | C33: =IF(OR(Registro_Compras!$C$7="",Registro_Compras!$O$7=""),"",IF(Registro_Compras!$F$7="RHE",IF(Registro_Compras!$V$7=0,"","40172"),IF(Registro_Compras!$F$7="NOTA DE CREDITO",IF(Registro_Compras!$M$7="","63",Registro_Compras!$M$7),IF(Registro_Compras!$K$7=0,"","40111")))) | D33: =IF(OR(Registro_Compras!$C$7="",Registro_Compras!$O$7=""),"",IF(Registro_Compras!$F$7="RHE","Retencion Renta 4ta Categoria por Pagar",IF(Registro_Compras!$F$7="NOTA DE CREDITO","Gastos de Servicios Prestados por Terceros","IGV - Cuenta Propia (Credito Fiscal)"))) | E33: =IF($C33="","",IF(Registro_Compras!$F$7="FACTURA",ROUND(Registro_Compras!$K$7*Registro_Compras!$N$7,2),"")) | F33: =IF($C33="","",IF(Registro_Compras!$F$7="RHE",ROUND(Registro_Compras!$V$7*Registro_Compras!$N$7,2),IF(Registro_Compras!$F$7="NOTA DE CREDITO",ROUND(ABS(Registro_Compras!$J$7*Registro_Compras!$N$7),2),""))) | G33: =IF($C33="","",IF(Registro_Compras!$F$7="NOTA DE CREDITO","Por la nota de credito "&Registro_Compras!$C$7&" de "&Registro_Compras!$E$7&" [PATRON POR CONFIRMAR CON CONTADOR]",IF(Registro_Compras!$F$7="RHE","Por el registro del recibo por honorarios "&Registro_Compras!$C$7&" de "&Registro_Compras!$E$7&" [PATRON POR CONFIRMAR CON CONTADOR]","Por el registro de la factura "&Registro_Compras!$C$7&" de "&Registro_Compras!$E$7))) | H33: =IF($C33="","",Registro_Compras!$C$7)
A34: =IF($C34="","",Registro_Compras!$B$7) | B34: =IF($C34="","","C"&TEXT(INT((ROW()-5)/9)+1,"000")&"-1") | C34: =IF(OR(Registro_Compras!$C$7="",Registro_Compras!$O$7=""),"",IF(Registro_Compras!$F$7="NOTA DE CREDITO",IF(Registro_Compras!$K$7=0,"","40111"),"4212")) | D34: =IF(OR(Registro_Compras!$C$7="",Registro_Compras!$O$7=""),"",IF(Registro_Compras!$F$7="NOTA DE CREDITO","IGV - Cuenta Propia (Credito Fiscal)","Cuentas por Pagar Comerciales - Terceros (Emitidas)")) | E34: ="" | F34: =IF($C34="","",IF(Registro_Compras!$F$7="NOTA DE CREDITO",ROUND(ABS(Registro_Compras!$K$7*Registro_Compras!$N$7),2),IF(Registro_Compras!$F$7="RHE",(ROUND(Registro_Compras!$L$7*Registro_Compras!$N$7,2)-ROUND(Registro_Compras!$V$7*Registro_Compras!$N$7,2)),Registro_Compras!$O$7))) | G34: =IF($C34="","",IF(Registro_Compras!$F$7="NOTA DE CREDITO","Por la nota de credito "&Registro_Compras!$C$7&" de "&Registro_Compras!$E$7&" [PATRON POR CONFIRMAR CON CONTADOR]",IF(Registro_Compras!$F$7="RHE","Por el registro del recibo por honorarios "&Registro_Compras!$C$7&" de "&Registro_Compras!$E$7&" [PATRON POR CONFIRMAR CON CONTADOR]","Por el registro de la factura "&Registro_Compras!$C$7&" de "&Registro_Compras!$E$7))) | H34: =IF($C34="","",Registro_Compras!$C$7)
A35: =IF($C35="","",Registro_Compras!$B$7) | B35: =IF($C35="","","C"&TEXT(INT((ROW()-5)/9)+1,"000")&"-2") | C35: =IF(OR(Registro_Compras!$C$7="",Registro_Compras!$O$7=""),"",IF(Registro_Compras!$AB$7="ADMINISTRATIVO","94","95")) | D35: =IF(OR(Registro_Compras!$C$7="",Registro_Compras!$O$7=""),"",IF(Registro_Compras!$AB$7="ADMINISTRATIVO","Gastos Administrativos","Gastos de Venta y Operacion")) | E35: =IF($C35="","",IF(Registro_Compras!$F$7="NOTA DE CREDITO","",IF(Registro_Compras!$F$7="RHE",ROUND(Registro_Compras!$L$7*Registro_Compras!$N$7,2),ROUND(Registro_Compras!$J$7*Registro_Compras!$N$7,2)))) | F35: =IF($C35="","",IF(Registro_Compras!$F$7="NOTA DE CREDITO",ROUND(ABS(Registro_Compras!$J$7*Registro_Compras!$N$7),2),"")) | G35: =IF($C35="","","Por el destino del gasto") | H35: =IF($C35="","",Registro_Compras!$C$7)
A36: =IF($C36="","",Registro_Compras!$B$7) | B36: =IF($C36="","","C"&TEXT(INT((ROW()-5)/9)+1,"000")&"-2") | C36: =IF(OR(Registro_Compras!$C$7="",Registro_Compras!$O$7=""),"","79/791") | D36: =IF(OR(Registro_Compras!$C$7="",Registro_Compras!$O$7=""),"","Cargas Imputables a Cuentas de Costos y Gastos") | E36: =IF($C36="","",IF(Registro_Compras!$F$7="NOTA DE CREDITO",ROUND(ABS(Registro_Compras!$J$7*Registro_Compras!$N$7),2),"")) | F36: =IF($C36="","",IF(Registro_Compras!$F$7="NOTA DE CREDITO","",IF(Registro_Compras!$F$7="RHE",ROUND(Registro_Compras!$L$7*Registro_Compras!$N$7,2),ROUND(Registro_Compras!$J$7*Registro_Compras!$N$7,2)))) | G36: =IF($C36="","","Por el destino del gasto") | H36: =IF($C36="","",Registro_Compras!$C$7)
A37: =IF($C37="","",Registro_Compras!$X$7) | B37: =IF($C37="","","C"&TEXT(INT((ROW()-5)/9)+1,"000")&"-3") | C37: =IF(OR(Registro_Compras!$C$7="",Registro_Compras!$O$7="",Registro_Compras!$R$7<>"SI",Registro_Compras!$X$7=""),"","4212") | D37: =IF(OR(Registro_Compras!$C$7="",Registro_Compras!$O$7=""),"","Cuentas por Pagar Comerciales - Terceros") | E37: =IF($C37="","",Registro_Compras!$S$7) | F37: ="" | G37: =IF($C37="","","Por el deposito de la detraccion en el Banco de la Nacion") | H37: =IF($C37="","",Registro_Compras!$C$7)
A38: =IF($C38="","",Registro_Compras!$X$7) | B38: =IF($C38="","","C"&TEXT(INT((ROW()-5)/9)+1,"000")&"-3") | C38: =IF(OR(Registro_Compras!$C$7="",Registro_Compras!$O$7="",Registro_Compras!$R$7<>"SI",Registro_Compras!$X$7=""),"","10413") | D38: =IF(OR(Registro_Compras!$C$7="",Registro_Compras!$O$7=""),"","Efectivo y Equivalentes - Cta. Cte. Operativa") | E38: ="" | F38: =IF($C38="","",Registro_Compras!$S$7) | G38: =IF($C38="","","Por el deposito de la detraccion en el Banco de la Nacion") | H38: =IF($C38="","",Registro_Compras!$C$7)
A39: =IF($C39="","",Registro_Compras!$Y$7) | B39: =IF($C39="","","C"&TEXT(INT((ROW()-5)/9)+1,"000")&"-4") | C39: =IF(OR(Registro_Compras!$C$7="",Registro_Compras!$O$7="",Registro_Compras!$Y$7="",Registro_Compras!$F$7="NOTA DE CREDITO"),"","4212") | D39: =IF(OR(Registro_Compras!$C$7="",Registro_Compras!$O$7=""),"","Cuentas por Pagar Comerciales - Terceros") | E39: =IF($C39="","",IF(Registro_Compras!$F$7="RHE",(ROUND(Registro_Compras!$L$7*Registro_Compras!$N$7,2)-ROUND(Registro_Compras!$V$7*Registro_Compras!$N$7,2)),ROUND(Registro_Compras!$O$7-Registro_Compras!$S$7,2))) | F39: ="" | G39: =IF($C39="","","Por la cancelacion del saldo al proveedor") | H39: =IF($C39="","",Registro_Compras!$C$7)
A40: =IF($C40="","",Registro_Compras!$Y$7) | B40: =IF($C40="","","C"&TEXT(INT((ROW()-5)/9)+1,"000")&"-4") | C40: =IF(OR(Registro_Compras!$C$7="",Registro_Compras!$O$7="",Registro_Compras!$Y$7="",Registro_Compras!$F$7="NOTA DE CREDITO"),"","10413") | D40: =IF(OR(Registro_Compras!$C$7="",Registro_Compras!$O$7=""),"","Efectivo y Equivalentes - Cta. Cte. Operativa") | E40: ="" | F40: =IF($C40="","",IF(Registro_Compras!$F$7="RHE",(ROUND(Registro_Compras!$L$7*Registro_Compras!$N$7,2)-ROUND(Registro_Compras!$V$7*Registro_Compras!$N$7,2)),ROUND(Registro_Compras!$O$7-Registro_Compras!$S$7,2))) | G40: =IF($C40="","","Por la cancelacion del saldo al proveedor") | H40: =IF($C40="","",Registro_Compras!$C$7)
A41: =IF($C41="","",Registro_Compras!$B$8) | B41: =IF($C41="","","C"&TEXT(INT((ROW()-5)/9)+1,"000")&"-1") | C41: =IF(OR(Registro_Compras!$C$8="",Registro_Compras!$O$8=""),"",IF(Registro_Compras!$F$8="NOTA DE CREDITO","4212",IF(Registro_Compras!$M$8="","63",Registro_Compras!$M$8))) | D41: =IF(OR(Registro_Compras!$C$8="",Registro_Compras!$O$8=""),"",IF(Registro_Compras!$F$8="NOTA DE CREDITO","Cuentas por Pagar Comerciales - Terceros (Emitidas)",IF(Registro_Compras!$F$8="RHE","Honorarios Profesionales - Servicios de Terceros","Gastos de Servicios Prestados por Terceros"))) | E41: =IF($C41="","",IF(Registro_Compras!$F$8="NOTA DE CREDITO",ABS(Registro_Compras!$O$8),IF(Registro_Compras!$F$8="RHE",ROUND(Registro_Compras!$L$8*Registro_Compras!$N$8,2),ROUND(Registro_Compras!$J$8*Registro_Compras!$N$8,2)))) | F41: ="" | G41: =IF($C41="","",IF(Registro_Compras!$F$8="NOTA DE CREDITO","Por la nota de credito "&Registro_Compras!$C$8&" de "&Registro_Compras!$E$8&" [PATRON POR CONFIRMAR CON CONTADOR]",IF(Registro_Compras!$F$8="RHE","Por el registro del recibo por honorarios "&Registro_Compras!$C$8&" de "&Registro_Compras!$E$8&" [PATRON POR CONFIRMAR CON CONTADOR]","Por el registro de la factura "&Registro_Compras!$C$8&" de "&Registro_Compras!$E$8))) | H41: =IF($C41="","",Registro_Compras!$C$8)
A42: =IF($C42="","",Registro_Compras!$B$8) | B42: =IF($C42="","","C"&TEXT(INT((ROW()-5)/9)+1,"000")&"-1") | C42: =IF(OR(Registro_Compras!$C$8="",Registro_Compras!$O$8=""),"",IF(Registro_Compras!$F$8="RHE",IF(Registro_Compras!$V$8=0,"","40172"),IF(Registro_Compras!$F$8="NOTA DE CREDITO",IF(Registro_Compras!$M$8="","63",Registro_Compras!$M$8),IF(Registro_Compras!$K$8=0,"","40111")))) | D42: =IF(OR(Registro_Compras!$C$8="",Registro_Compras!$O$8=""),"",IF(Registro_Compras!$F$8="RHE","Retencion Renta 4ta Categoria por Pagar",IF(Registro_Compras!$F$8="NOTA DE CREDITO","Gastos de Servicios Prestados por Terceros","IGV - Cuenta Propia (Credito Fiscal)"))) | E42: =IF($C42="","",IF(Registro_Compras!$F$8="FACTURA",ROUND(Registro_Compras!$K$8*Registro_Compras!$N$8,2),"")) | F42: =IF($C42="","",IF(Registro_Compras!$F$8="RHE",ROUND(Registro_Compras!$V$8*Registro_Compras!$N$8,2),IF(Registro_Compras!$F$8="NOTA DE CREDITO",ROUND(ABS(Registro_Compras!$J$8*Registro_Compras!$N$8),2),""))) | G42: =IF($C42="","",IF(Registro_Compras!$F$8="NOTA DE CREDITO","Por la nota de credito "&Registro_Compras!$C$8&" de "&Registro_Compras!$E$8&" [PATRON POR CONFIRMAR CON CONTADOR]",IF(Registro_Compras!$F$8="RHE","Por el registro del recibo por honorarios "&Registro_Compras!$C$8&" de "&Registro_Compras!$E$8&" [PATRON POR CONFIRMAR CON CONTADOR]","Por el registro de la factura "&Registro_Compras!$C$8&" de "&Registro_Compras!$E$8))) | H42: =IF($C42="","",Registro_Compras!$C$8)
A43: =IF($C43="","",Registro_Compras!$B$8) | B43: =IF($C43="","","C"&TEXT(INT((ROW()-5)/9)+1,"000")&"-1") | C43: =IF(OR(Registro_Compras!$C$8="",Registro_Compras!$O$8=""),"",IF(Registro_Compras!$F$8="NOTA DE CREDITO",IF(Registro_Compras!$K$8=0,"","40111"),"4212")) | D43: =IF(OR(Registro_Compras!$C$8="",Registro_Compras!$O$8=""),"",IF(Registro_Compras!$F$8="NOTA DE CREDITO","IGV - Cuenta Propia (Credito Fiscal)","Cuentas por Pagar Comerciales - Terceros (Emitidas)")) | E43: ="" | F43: =IF($C43="","",IF(Registro_Compras!$F$8="NOTA DE CREDITO",ROUND(ABS(Registro_Compras!$K$8*Registro_Compras!$N$8),2),IF(Registro_Compras!$F$8="RHE",(ROUND(Registro_Compras!$L$8*Registro_Compras!$N$8,2)-ROUND(Registro_Compras!$V$8*Registro_Compras!$N$8,2)),Registro_Compras!$O$8))) | G43: =IF($C43="","",IF(Registro_Compras!$F$8="NOTA DE CREDITO","Por la nota de credito "&Registro_Compras!$C$8&" de "&Registro_Compras!$E$8&" [PATRON POR CONFIRMAR CON CONTADOR]",IF(Registro_Compras!$F$8="RHE","Por el registro del recibo por honorarios "&Registro_Compras!$C$8&" de "&Registro_Compras!$E$8&" [PATRON POR CONFIRMAR CON CONTADOR]","Por el registro de la factura "&Registro_Compras!$C$8&" de "&Registro_Compras!$E$8))) | H43: =IF($C43="","",Registro_Compras!$C$8)
A44: =IF($C44="","",Registro_Compras!$B$8) | B44: =IF($C44="","","C"&TEXT(INT((ROW()-5)/9)+1,"000")&"-2") | C44: =IF(OR(Registro_Compras!$C$8="",Registro_Compras!$O$8=""),"",IF(Registro_Compras!$AB$8="ADMINISTRATIVO","94","95")) | D44: =IF(OR(Registro_Compras!$C$8="",Registro_Compras!$O$8=""),"",IF(Registro_Compras!$AB$8="ADMINISTRATIVO","Gastos Administrativos","Gastos de Venta y Operacion")) | E44: =IF($C44="","",IF(Registro_Compras!$F$8="NOTA DE CREDITO","",IF(Registro_Compras!$F$8="RHE",ROUND(Registro_Compras!$L$8*Registro_Compras!$N$8,2),ROUND(Registro_Compras!$J$8*Registro_Compras!$N$8,2)))) | F44: =IF($C44="","",IF(Registro_Compras!$F$8="NOTA DE CREDITO",ROUND(ABS(Registro_Compras!$J$8*Registro_Compras!$N$8),2),"")) | G44: =IF($C44="","","Por el destino del gasto") | H44: =IF($C44="","",Registro_Compras!$C$8)
A45: =IF($C45="","",Registro_Compras!$B$8) | B45: =IF($C45="","","C"&TEXT(INT((ROW()-5)/9)+1,"000")&"-2") | C45: =IF(OR(Registro_Compras!$C$8="",Registro_Compras!$O$8=""),"","79/791") | D45: =IF(OR(Registro_Compras!$C$8="",Registro_Compras!$O$8=""),"","Cargas Imputables a Cuentas de Costos y Gastos") | E45: =IF($C45="","",IF(Registro_Compras!$F$8="NOTA DE CREDITO",ROUND(ABS(Registro_Compras!$J$8*Registro_Compras!$N$8),2),"")) | F45: =IF($C45="","",IF(Registro_Compras!$F$8="NOTA DE CREDITO","",IF(Registro_Compras!$F$8="RHE",ROUND(Registro_Compras!$L$8*Registro_Compras!$N$8,2),ROUND(Registro_Compras!$J$8*Registro_Compras!$N$8,2)))) | G45: =IF($C45="","","Por el destino del gasto") | H45: =IF($C45="","",Registro_Compras!$C$8)
A46: =IF($C46="","",Registro_Compras!$X$8) | B46: =IF($C46="","","C"&TEXT(INT((ROW()-5)/9)+1,"000")&"-3") | C46: =IF(OR(Registro_Compras!$C$8="",Registro_Compras!$O$8="",Registro_Compras!$R$8<>"SI",Registro_Compras!$X$8=""),"","4212") | D46: =IF(OR(Registro_Compras!$C$8="",Registro_Compras!$O$8=""),"","Cuentas por Pagar Comerciales - Terceros") | E46: =IF($C46="","",Registro_Compras!$S$8) | F46: ="" | G46: =IF($C46="","","Por el deposito de la detraccion en el Banco de la Nacion") | H46: =IF($C46="","",Registro_Compras!$C$8)
A47: =IF($C47="","",Registro_Compras!$X$8) | B47: =IF($C47="","","C"&TEXT(INT((ROW()-5)/9)+1,"000")&"-3") | C47: =IF(OR(Registro_Compras!$C$8="",Registro_Compras!$O$8="",Registro_Compras!$R$8<>"SI",Registro_Compras!$X$8=""),"","10413") | D47: =IF(OR(Registro_Compras!$C$8="",Registro_Compras!$O$8=""),"","Efectivo y Equivalentes - Cta. Cte. Operativa") | E47: ="" | F47: =IF($C47="","",Registro_Compras!$S$8) | G47: =IF($C47="","","Por el deposito de la detraccion en el Banco de la Nacion") | H47: =IF($C47="","",Registro_Compras!$C$8)
A48: =IF($C48="","",Registro_Compras!$Y$8) | B48: =IF($C48="","","C"&TEXT(INT((ROW()-5)/9)+1,"000")&"-4") | C48: =IF(OR(Registro_Compras!$C$8="",Registro_Compras!$O$8="",Registro_Compras!$Y$8="",Registro_Compras!$F$8="NOTA DE CREDITO"),"","4212") | D48: =IF(OR(Registro_Compras!$C$8="",Registro_Compras!$O$8=""),"","Cuentas por Pagar Comerciales - Terceros") | E48: =IF($C48="","",IF(Registro_Compras!$F$8="RHE",(ROUND(Registro_Compras!$L$8*Registro_Compras!$N$8,2)-ROUND(Registro_Compras!$V$8*Registro_Compras!$N$8,2)),ROUND(Registro_Compras!$O$8-Registro_Compras!$S$8,2))) | F48: ="" | G48: =IF($C48="","","Por la cancelacion del saldo al proveedor") | H48: =IF($C48="","",Registro_Compras!$C$8)
A49: =IF($C49="","",Registro_Compras!$Y$8) | B49: =IF($C49="","","C"&TEXT(INT((ROW()-5)/9)+1,"000")&"-4") | C49: =IF(OR(Registro_Compras!$C$8="",Registro_Compras!$O$8="",Registro_Compras!$Y$8="",Registro_Compras!$F$8="NOTA DE CREDITO"),"","10413") | D49: =IF(OR(Registro_Compras!$C$8="",Registro_Compras!$O$8=""),"","Efectivo y Equivalentes - Cta. Cte. Operativa") | E49: ="" | F49: =IF($C49="","",IF(Registro_Compras!$F$8="RHE",(ROUND(Registro_Compras!$L$8*Registro_Compras!$N$8,2)-ROUND(Registro_Compras!$V$8*Registro_Compras!$N$8,2)),ROUND(Registro_Compras!$O$8-Registro_Compras!$S$8,2))) | G49: =IF($C49="","","Por la cancelacion del saldo al proveedor") | H49: =IF($C49="","",Registro_Compras!$C$8)
A50: =IF($C50="","",Registro_Compras!$B$9) | B50: =IF($C50="","","C"&TEXT(INT((ROW()-5)/9)+1,"000")&"-1") | C50: =IF(OR(Registro_Compras!$C$9="",Registro_Compras!$O$9=""),"",IF(Registro_Compras!$F$9="NOTA DE CREDITO","4212",IF(Registro_Compras!$M$9="","63",Registro_Compras!$M$9))) | D50: =IF(OR(Registro_Compras!$C$9="",Registro_Compras!$O$9=""),"",IF(Registro_Compras!$F$9="NOTA DE CREDITO","Cuentas por Pagar Comerciales - Terceros (Emitidas)",IF(Registro_Compras!$F$9="RHE","Honorarios Profesionales - Servicios de Terceros","Gastos de Servicios Prestados por Terceros"))) | E50: =IF($C50="","",IF(Registro_Compras!$F$9="NOTA DE CREDITO",ABS(Registro_Compras!$O$9),IF(Registro_Compras!$F$9="RHE",ROUND(Registro_Compras!$L$9*Registro_Compras!$N$9,2),ROUND(Registro_Compras!$J$9*Registro_Compras!$N$9,2)))) | F50: ="" | G50: =IF($C50="","",IF(Registro_Compras!$F$9="NOTA DE CREDITO","Por la nota de credito "&Registro_Compras!$C$9&" de "&Registro_Compras!$E$9&" [PATRON POR CONFIRMAR CON CONTADOR]",IF(Registro_Compras!$F$9="RHE","Por el registro del recibo por honorarios "&Registro_Compras!$C$9&" de "&Registro_Compras!$E$9&" [PATRON POR CONFIRMAR CON CONTADOR]","Por el registro de la factura "&Registro_Compras!$C$9&" de "&Registro_Compras!$E$9))) | H50: =IF($C50="","",Registro_Compras!$C$9)
A51: =IF($C51="","",Registro_Compras!$B$9) | B51: =IF($C51="","","C"&TEXT(INT((ROW()-5)/9)+1,"000")&"-1") | C51: =IF(OR(Registro_Compras!$C$9="",Registro_Compras!$O$9=""),"",IF(Registro_Compras!$F$9="RHE",IF(Registro_Compras!$V$9=0,"","40172"),IF(Registro_Compras!$F$9="NOTA DE CREDITO",IF(Registro_Compras!$M$9="","63",Registro_Compras!$M$9),IF(Registro_Compras!$K$9=0,"","40111")))) | D51: =IF(OR(Registro_Compras!$C$9="",Registro_Compras!$O$9=""),"",IF(Registro_Compras!$F$9="RHE","Retencion Renta 4ta Categoria por Pagar",IF(Registro_Compras!$F$9="NOTA DE CREDITO","Gastos de Servicios Prestados por Terceros","IGV - Cuenta Propia (Credito Fiscal)"))) | E51: =IF($C51="","",IF(Registro_Compras!$F$9="FACTURA",ROUND(Registro_Compras!$K$9*Registro_Compras!$N$9,2),"")) | F51: =IF($C51="","",IF(Registro_Compras!$F$9="RHE",ROUND(Registro_Compras!$V$9*Registro_Compras!$N$9,2),IF(Registro_Compras!$F$9="NOTA DE CREDITO",ROUND(ABS(Registro_Compras!$J$9*Registro_Compras!$N$9),2),""))) | G51: =IF($C51="","",IF(Registro_Compras!$F$9="NOTA DE CREDITO","Por la nota de credito "&Registro_Compras!$C$9&" de "&Registro_Compras!$E$9&" [PATRON POR CONFIRMAR CON CONTADOR]",IF(Registro_Compras!$F$9="RHE","Por el registro del recibo por honorarios "&Registro_Compras!$C$9&" de "&Registro_Compras!$E$9&" [PATRON POR CONFIRMAR CON CONTADOR]","Por el registro de la factura "&Registro_Compras!$C$9&" de "&Registro_Compras!$E$9))) | H51: =IF($C51="","",Registro_Compras!$C$9)
A52: =IF($C52="","",Registro_Compras!$B$9) | B52: =IF($C52="","","C"&TEXT(INT((ROW()-5)/9)+1,"000")&"-1") | C52: =IF(OR(Registro_Compras!$C$9="",Registro_Compras!$O$9=""),"",IF(Registro_Compras!$F$9="NOTA DE CREDITO",IF(Registro_Compras!$K$9=0,"","40111"),"4212")) | D52: =IF(OR(Registro_Compras!$C$9="",Registro_Compras!$O$9=""),"",IF(Registro_Compras!$F$9="NOTA DE CREDITO","IGV - Cuenta Propia (Credito Fiscal)","Cuentas por Pagar Comerciales - Terceros (Emitidas)")) | E52: ="" | F52: =IF($C52="","",IF(Registro_Compras!$F$9="NOTA DE CREDITO",ROUND(ABS(Registro_Compras!$K$9*Registro_Compras!$N$9),2),IF(Registro_Compras!$F$9="RHE",(ROUND(Registro_Compras!$L$9*Registro_Compras!$N$9,2)-ROUND(Registro_Compras!$V$9*Registro_Compras!$N$9,2)),Registro_Compras!$O$9))) | G52: =IF($C52="","",IF(Registro_Compras!$F$9="NOTA DE CREDITO","Por la nota de credito "&Registro_Compras!$C$9&" de "&Registro_Compras!$E$9&" [PATRON POR CONFIRMAR CON CONTADOR]",IF(Registro_Compras!$F$9="RHE","Por el registro del recibo por honorarios "&Registro_Compras!$C$9&" de "&Registro_Compras!$E$9&" [PATRON POR CONFIRMAR CON CONTADOR]","Por el registro de la factura "&Registro_Compras!$C$9&" de "&Registro_Compras!$E$9))) | H52: =IF($C52="","",Registro_Compras!$C$9)
A53: =IF($C53="","",Registro_Compras!$B$9) | B53: =IF($C53="","","C"&TEXT(INT((ROW()-5)/9)+1,"000")&"-2") | C53: =IF(OR(Registro_Compras!$C$9="",Registro_Compras!$O$9=""),"",IF(Registro_Compras!$AB$9="ADMINISTRATIVO","94","95")) | D53: =IF(OR(Registro_Compras!$C$9="",Registro_Compras!$O$9=""),"",IF(Registro_Compras!$AB$9="ADMINISTRATIVO","Gastos Administrativos","Gastos de Venta y Operacion")) | E53: =IF($C53="","",IF(Registro_Compras!$F$9="NOTA DE CREDITO","",IF(Registro_Compras!$F$9="RHE",ROUND(Registro_Compras!$L$9*Registro_Compras!$N$9,2),ROUND(Registro_Compras!$J$9*Registro_Compras!$N$9,2)))) | F53: =IF($C53="","",IF(Registro_Compras!$F$9="NOTA DE CREDITO",ROUND(ABS(Registro_Compras!$J$9*Registro_Compras!$N$9),2),"")) | G53: =IF($C53="","","Por el destino del gasto") | H53: =IF($C53="","",Registro_Compras!$C$9)
A54: =IF($C54="","",Registro_Compras!$B$9) | B54: =IF($C54="","","C"&TEXT(INT((ROW()-5)/9)+1,"000")&"-2") | C54: =IF(OR(Registro_Compras!$C$9="",Registro_Compras!$O$9=""),"","79/791") | D54: =IF(OR(Registro_Compras!$C$9="",Registro_Compras!$O$9=""),"","Cargas Imputables a Cuentas de Costos y Gastos") | E54: =IF($C54="","",IF(Registro_Compras!$F$9="NOTA DE CREDITO",ROUND(ABS(Registro_Compras!$J$9*Registro_Compras!$N$9),2),"")) | F54: =IF($C54="","",IF(Registro_Compras!$F$9="NOTA DE CREDITO","",IF(Registro_Compras!$F$9="RHE",ROUND(Registro_Compras!$L$9*Registro_Compras!$N$9,2),ROUND(Registro_Compras!$J$9*Registro_Compras!$N$9,2)))) | G54: =IF($C54="","","Por el destino del gasto") | H54: =IF($C54="","",Registro_Compras!$C$9)
A55: =IF($C55="","",Registro_Compras!$X$9) | B55: =IF($C55="","","C"&TEXT(INT((ROW()-5)/9)+1,"000")&"-3") | C55: =IF(OR(Registro_Compras!$C$9="",Registro_Compras!$O$9="",Registro_Compras!$R$9<>"SI",Registro_Compras!$X$9=""),"","4212") | D55: =IF(OR(Registro_Compras!$C$9="",Registro_Compras!$O$9=""),"","Cuentas por Pagar Comerciales - Terceros") | E55: =IF($C55="","",Registro_Compras!$S$9) | F55: ="" | G55: =IF($C55="","","Por el deposito de la detraccion en el Banco de la Nacion") | H55: =IF($C55="","",Registro_Compras!$C$9)
A56: =IF($C56="","",Registro_Compras!$X$9) | B56: =IF($C56="","","C"&TEXT(INT((ROW()-5)/9)+1,"000")&"-3") | C56: =IF(OR(Registro_Compras!$C$9="",Registro_Compras!$O$9="",Registro_Compras!$R$9<>"SI",Registro_Compras!$X$9=""),"","10413") | D56: =IF(OR(Registro_Compras!$C$9="",Registro_Compras!$O$9=""),"","Efectivo y Equivalentes - Cta. Cte. Operativa") | E56: ="" | F56: =IF($C56="","",Registro_Compras!$S$9) | G56: =IF($C56="","","Por el deposito de la detraccion en el Banco de la Nacion") | H56: =IF($C56="","",Registro_Compras!$C$9)
A57: =IF($C57="","",Registro_Compras!$Y$9) | B57: =IF($C57="","","C"&TEXT(INT((ROW()-5)/9)+1,"000")&"-4") | C57: =IF(OR(Registro_Compras!$C$9="",Registro_Compras!$O$9="",Registro_Compras!$Y$9="",Registro_Compras!$F$9="NOTA DE CREDITO"),"","4212") | D57: =IF(OR(Registro_Compras!$C$9="",Registro_Compras!$O$9=""),"","Cuentas por Pagar Comerciales - Terceros") | E57: =IF($C57="","",IF(Registro_Compras!$F$9="RHE",(ROUND(Registro_Compras!$L$9*Registro_Compras!$N$9,2)-ROUND(Registro_Compras!$V$9*Registro_Compras!$N$9,2)),ROUND(Registro_Compras!$O$9-Registro_Compras!$S$9,2))) | F57: ="" | G57: =IF($C57="","","Por la cancelacion del saldo al proveedor") | H57: =IF($C57="","",Registro_Compras!$C$9)
A58: =IF($C58="","",Registro_Compras!$Y$9) | B58: =IF($C58="","","C"&TEXT(INT((ROW()-5)/9)+1,"000")&"-4") | C58: =IF(OR(Registro_Compras!$C$9="",Registro_Compras!$O$9="",Registro_Compras!$Y$9="",Registro_Compras!$F$9="NOTA DE CREDITO"),"","10413") | D58: =IF(OR(Registro_Compras!$C$9="",Registro_Compras!$O$9=""),"","Efectivo y Equivalentes - Cta. Cte. Operativa") | E58: ="" | F58: =IF($C58="","",IF(Registro_Compras!$F$9="RHE",(ROUND(Registro_Compras!$L$9*Registro_Compras!$N$9,2)-ROUND(Registro_Compras!$V$9*Registro_Compras!$N$9,2)),ROUND(Registro_Compras!$O$9-Registro_Compras!$S$9,2))) | G58: =IF($C58="","","Por la cancelacion del saldo al proveedor") | H58: =IF($C58="","",Registro_Compras!$C$9)
A59: =IF($C59="","",Registro_Compras!$B$10) | B59: =IF($C59="","","C"&TEXT(INT((ROW()-5)/9)+1,"000")&"-1") | C59: =IF(OR(Registro_Compras!$C$10="",Registro_Compras!$O$10=""),"",IF(Registro_Compras!$F$10="NOTA DE CREDITO","4212",IF(Registro_Compras!$M$10="","63",Registro_Compras!$M$10))) | D59: =IF(OR(Registro_Compras!$C$10="",Registro_Compras!$O$10=""),"",IF(Registro_Compras!$F$10="NOTA DE CREDITO","Cuentas por Pagar Comerciales - Terceros (Emitidas)",IF(Registro_Compras!$F$10="RHE","Honorarios Profesionales - Servicios de Terceros","Gastos de Servicios Prestados por Terceros"))) | E59: =IF($C59="","",IF(Registro_Compras!$F$10="NOTA DE CREDITO",ABS(Registro_Compras!$O$10),IF(Registro_Compras!$F$10="RHE",ROUND(Registro_Compras!$L$10*Registro_Compras!$N$10,2),ROUND(Registro_Compras!$J$10*Registro_Compras!$N$10,2)))) | F59: ="" | G59: =IF($C59="","",IF(Registro_Compras!$F$10="NOTA DE CREDITO","Por la nota de credito "&Registro_Compras!$C$10&" de "&Registro_Compras!$E$10&" [PATRON POR CONFIRMAR CON CONTADOR]",IF(Registro_Compras!$F$10="RHE","Por el registro del recibo por honorarios "&Registro_Compras!$C$10&" de "&Registro_Compras!$E$10&" [PATRON POR CONFIRMAR CON CONTADOR]","Por el registro de la factura "&Registro_Compras!$C$10&" de "&Registro_Compras!$E$10))) | H59: =IF($C59="","",Registro_Compras!$C$10)
A60: =IF($C60="","",Registro_Compras!$B$10) | B60: =IF($C60="","","C"&TEXT(INT((ROW()-5)/9)+1,"000")&"-1") | C60: =IF(OR(Registro_Compras!$C$10="",Registro_Compras!$O$10=""),"",IF(Registro_Compras!$F$10="RHE",IF(Registro_Compras!$V$10=0,"","40172"),IF(Registro_Compras!$F$10="NOTA DE CREDITO",IF(Registro_Compras!$M$10="","63",Registro_Compras!$M$10),IF(Registro_Compras!$K$10=0,"","40111")))) | D60: =IF(OR(Registro_Compras!$C$10="",Registro_Compras!$O$10=""),"",IF(Registro_Compras!$F$10="RHE","Retencion Renta 4ta Categoria por Pagar",IF(Registro_Compras!$F$10="NOTA DE CREDITO","Gastos de Servicios Prestados por Terceros","IGV - Cuenta Propia (Credito Fiscal)"))) | E60: =IF($C60="","",IF(Registro_Compras!$F$10="FACTURA",ROUND(Registro_Compras!$K$10*Registro_Compras!$N$10,2),"")) | F60: =IF($C60="","",IF(Registro_Compras!$F$10="RHE",ROUND(Registro_Compras!$V$10*Registro_Compras!$N$10,2),IF(Registro_Compras!$F$10="NOTA DE CREDITO",ROUND(ABS(Registro_Compras!$J$10*Registro_Compras!$N$10),2),""))) | G60: =IF($C60="","",IF(Registro_Compras!$F$10="NOTA DE CREDITO","Por la nota de credito "&Registro_Compras!$C$10&" de "&Registro_Compras!$E$10&" [PATRON POR CONFIRMAR CON CONTADOR]",IF(Registro_Compras!$F$10="RHE","Por el registro del recibo por honorarios "&Registro_Compras!$C$10&" de "&Registro_Compras!$E$10&" [PATRON POR CONFIRMAR CON CONTADOR]","Por el registro de la factura "&Registro_Compras!$C$10&" de "&Registro_Compras!$E$10))) | H60: =IF($C60="","",Registro_Compras!$C$10)
A61: =IF($C61="","",Registro_Compras!$B$10) | B61: =IF($C61="","","C"&TEXT(INT((ROW()-5)/9)+1,"000")&"-1") | C61: =IF(OR(Registro_Compras!$C$10="",Registro_Compras!$O$10=""),"",IF(Registro_Compras!$F$10="NOTA DE CREDITO",IF(Registro_Compras!$K$10=0,"","40111"),"4212")) | D61: =IF(OR(Registro_Compras!$C$10="",Registro_Compras!$O$10=""),"",IF(Registro_Compras!$F$10="NOTA DE CREDITO","IGV - Cuenta Propia (Credito Fiscal)","Cuentas por Pagar Comerciales - Terceros (Emitidas)")) | E61: ="" | F61: =IF($C61="","",IF(Registro_Compras!$F$10="NOTA DE CREDITO",ROUND(ABS(Registro_Compras!$K$10*Registro_Compras!$N$10),2),IF(Registro_Compras!$F$10="RHE",(ROUND(Registro_Compras!$L$10*Registro_Compras!$N$10,2)-ROUND(Registro_Compras!$V$10*Registro_Compras!$N$10,2)),Registro_Compras!$O$10))) | G61: =IF($C61="","",IF(Registro_Compras!$F$10="NOTA DE CREDITO","Por la nota de credito "&Registro_Compras!$C$10&" de "&Registro_Compras!$E$10&" [PATRON POR CONFIRMAR CON CONTADOR]",IF(Registro_Compras!$F$10="RHE","Por el registro del recibo por honorarios "&Registro_Compras!$C$10&" de "&Registro_Compras!$E$10&" [PATRON POR CONFIRMAR CON CONTADOR]","Por el registro de la factura "&Registro_Compras!$C$10&" de "&Registro_Compras!$E$10))) | H61: =IF($C61="","",Registro_Compras!$C$10)
A62: =IF($C62="","",Registro_Compras!$B$10) | B62: =IF($C62="","","C"&TEXT(INT((ROW()-5)/9)+1,"000")&"-2") | C62: =IF(OR(Registro_Compras!$C$10="",Registro_Compras!$O$10=""),"",IF(Registro_Compras!$AB$10="ADMINISTRATIVO","94","95")) | D62: =IF(OR(Registro_Compras!$C$10="",Registro_Compras!$O$10=""),"",IF(Registro_Compras!$AB$10="ADMINISTRATIVO","Gastos Administrativos","Gastos de Venta y Operacion")) | E62: =IF($C62="","",IF(Registro_Compras!$F$10="NOTA DE CREDITO","",IF(Registro_Compras!$F$10="RHE",ROUND(Registro_Compras!$L$10*Registro_Compras!$N$10,2),ROUND(Registro_Compras!$J$10*Registro_Compras!$N$10,2)))) | F62: =IF($C62="","",IF(Registro_Compras!$F$10="NOTA DE CREDITO",ROUND(ABS(Registro_Compras!$J$10*Registro_Compras!$N$10),2),"")) | G62: =IF($C62="","","Por el destino del gasto") | H62: =IF($C62="","",Registro_Compras!$C$10)
A63: =IF($C63="","",Registro_Compras!$B$10) | B63: =IF($C63="","","C"&TEXT(INT((ROW()-5)/9)+1,"000")&"-2") | C63: =IF(OR(Registro_Compras!$C$10="",Registro_Compras!$O$10=""),"","79/791") | D63: =IF(OR(Registro_Compras!$C$10="",Registro_Compras!$O$10=""),"","Cargas Imputables a Cuentas de Costos y Gastos") | E63: =IF($C63="","",IF(Registro_Compras!$F$10="NOTA DE CREDITO",ROUND(ABS(Registro_Compras!$J$10*Registro_Compras!$N$10),2),"")) | F63: =IF($C63="","",IF(Registro_Compras!$F$10="NOTA DE CREDITO","",IF(Registro_Compras!$F$10="RHE",ROUND(Registro_Compras!$L$10*Registro_Compras!$N$10,2),ROUND(Registro_Compras!$J$10*Registro_Compras!$N$10,2)))) | G63: =IF($C63="","","Por el destino del gasto") | H63: =IF($C63="","",Registro_Compras!$C$10)
A64: =IF($C64="","",Registro_Compras!$X$10) | B64: =IF($C64="","","C"&TEXT(INT((ROW()-5)/9)+1,"000")&"-3") | C64: =IF(OR(Registro_Compras!$C$10="",Registro_Compras!$O$10="",Registro_Compras!$R$10<>"SI",Registro_Compras!$X$10=""),"","4212") | D64: =IF(OR(Registro_Compras!$C$10="",Registro_Compras!$O$10=""),"","Cuentas por Pagar Comerciales - Terceros") | E64: =IF($C64="","",Registro_Compras!$S$10) | F64: ="" | G64: =IF($C64="","","Por el deposito de la detraccion en el Banco de la Nacion") | H64: =IF($C64="","",Registro_Compras!$C$10)
A65: =IF($C65="","",Registro_Compras!$X$10) | B65: =IF($C65="","","C"&TEXT(INT((ROW()-5)/9)+1,"000")&"-3") | C65: =IF(OR(Registro_Compras!$C$10="",Registro_Compras!$O$10="",Registro_Compras!$R$10<>"SI",Registro_Compras!$X$10=""),"","10413") | D65: =IF(OR(Registro_Compras!$C$10="",Registro_Compras!$O$10=""),"","Efectivo y Equivalentes - Cta. Cte. Operativa") | E65: ="" | F65: =IF($C65="","",Registro_Compras!$S$10) | G65: =IF($C65="","","Por el deposito de la detraccion en el Banco de la Nacion") | H65: =IF($C65="","",Registro_Compras!$C$10)
A66: =IF($C66="","",Registro_Compras!$Y$10) | B66: =IF($C66="","","C"&TEXT(INT((ROW()-5)/9)+1,"000")&"-4") | C66: =IF(OR(Registro_Compras!$C$10="",Registro_Compras!$O$10="",Registro_Compras!$Y$10="",Registro_Compras!$F$10="NOTA DE CREDITO"),"","4212") | D66: =IF(OR(Registro_Compras!$C$10="",Registro_Compras!$O$10=""),"","Cuentas por Pagar Comerciales - Terceros") | E66: =IF($C66="","",IF(Registro_Compras!$F$10="RHE",(ROUND(Registro_Compras!$L$10*Registro_Compras!$N$10,2)-ROUND(Registro_Compras!$V$10*Registro_Compras!$N$10,2)),ROUND(Registro_Compras!$O$10-Registro_Compras!$S$10,2))) | F66: ="" | G66: =IF($C66="","","Por la cancelacion del saldo al proveedor") | H66: =IF($C66="","",Registro_Compras!$C$10)
A67: =IF($C67="","",Registro_Compras!$Y$10) | B67: =IF($C67="","","C"&TEXT(INT((ROW()-5)/9)+1,"000")&"-4") | C67: =IF(OR(Registro_Compras!$C$10="",Registro_Compras!$O$10="",Registro_Compras!$Y$10="",Registro_Compras!$F$10="NOTA DE CREDITO"),"","10413") | D67: =IF(OR(Registro_Compras!$C$10="",Registro_Compras!$O$10=""),"","Efectivo y Equivalentes - Cta. Cte. Operativa") | E67: ="" | F67: =IF($C67="","",IF(Registro_Compras!$F$10="RHE",(ROUND(Registro_Compras!$L$10*Registro_Compras!$N$10,2)-ROUND(Registro_Compras!$V$10*Registro_Compras!$N$10,2)),ROUND(Registro_Compras!$O$10-Registro_Compras!$S$10,2))) | G67: =IF($C67="","","Por la cancelacion del saldo al proveedor") | H67: =IF($C67="","",Registro_Compras!$C$10)
A68: =IF($C68="","",Registro_Compras!$B$11) | B68: =IF($C68="","","C"&TEXT(INT((ROW()-5)/9)+1,"000")&"-1") | C68: =IF(OR(Registro_Compras!$C$11="",Registro_Compras!$O$11=""),"",IF(Registro_Compras!$F$11="NOTA DE CREDITO","4212",IF(Registro_Compras!$M$11="","63",Registro_Compras!$M$11))) | D68: =IF(OR(Registro_Compras!$C$11="",Registro_Compras!$O$11=""),"",IF(Registro_Compras!$F$11="NOTA DE CREDITO","Cuentas por Pagar Comerciales - Terceros (Emitidas)",IF(Registro_Compras!$F$11="RHE","Honorarios Profesionales - Servicios de Terceros","Gastos de Servicios Prestados por Terceros"))) | E68: =IF($C68="","",IF(Registro_Compras!$F$11="NOTA DE CREDITO",ABS(Registro_Compras!$O$11),IF(Registro_Compras!$F$11="RHE",ROUND(Registro_Compras!$L$11*Registro_Compras!$N$11,2),ROUND(Registro_Compras!$J$11*Registro_Compras!$N$11,2)))) | F68: ="" | G68: =IF($C68="","",IF(Registro_Compras!$F$11="NOTA DE CREDITO","Por la nota de credito "&Registro_Compras!$C$11&" de "&Registro_Compras!$E$11&" [PATRON POR CONFIRMAR CON CONTADOR]",IF(Registro_Compras!$F$11="RHE","Por el registro del recibo por honorarios "&Registro_Compras!$C$11&" de "&Registro_Compras!$E$11&" [PATRON POR CONFIRMAR CON CONTADOR]","Por el registro de la factura "&Registro_Compras!$C$11&" de "&Registro_Compras!$E$11))) | H68: =IF($C68="","",Registro_Compras!$C$11)
A69: =IF($C69="","",Registro_Compras!$B$11) | B69: =IF($C69="","","C"&TEXT(INT((ROW()-5)/9)+1,"000")&"-1") | C69: =IF(OR(Registro_Compras!$C$11="",Registro_Compras!$O$11=""),"",IF(Registro_Compras!$F$11="RHE",IF(Registro_Compras!$V$11=0,"","40172"),IF(Registro_Compras!$F$11="NOTA DE CREDITO",IF(Registro_Compras!$M$11="","63",Registro_Compras!$M$11),IF(Registro_Compras!$K$11=0,"","40111")))) | D69: =IF(OR(Registro_Compras!$C$11="",Registro_Compras!$O$11=""),"",IF(Registro_Compras!$F$11="RHE","Retencion Renta 4ta Categoria por Pagar",IF(Registro_Compras!$F$11="NOTA DE CREDITO","Gastos de Servicios Prestados por Terceros","IGV - Cuenta Propia (Credito Fiscal)"))) | E69: =IF($C69="","",IF(Registro_Compras!$F$11="FACTURA",ROUND(Registro_Compras!$K$11*Registro_Compras!$N$11,2),"")) | F69: =IF($C69="","",IF(Registro_Compras!$F$11="RHE",ROUND(Registro_Compras!$V$11*Registro_Compras!$N$11,2),IF(Registro_Compras!$F$11="NOTA DE CREDITO",ROUND(ABS(Registro_Compras!$J$11*Registro_Compras!$N$11),2),""))) | G69: =IF($C69="","",IF(Registro_Compras!$F$11="NOTA DE CREDITO","Por la nota de credito "&Registro_Compras!$C$11&" de "&Registro_Compras!$E$11&" [PATRON POR CONFIRMAR CON CONTADOR]",IF(Registro_Compras!$F$11="RHE","Por el registro del recibo por honorarios "&Registro_Compras!$C$11&" de "&Registro_Compras!$E$11&" [PATRON POR CONFIRMAR CON CONTADOR]","Por el registro de la factura "&Registro_Compras!$C$11&" de "&Registro_Compras!$E$11))) | H69: =IF($C69="","",Registro_Compras!$C$11)
A70: =IF($C70="","",Registro_Compras!$B$11) | B70: =IF($C70="","","C"&TEXT(INT((ROW()-5)/9)+1,"000")&"-1") | C70: =IF(OR(Registro_Compras!$C$11="",Registro_Compras!$O$11=""),"",IF(Registro_Compras!$F$11="NOTA DE CREDITO",IF(Registro_Compras!$K$11=0,"","40111"),"4212")) | D70: =IF(OR(Registro_Compras!$C$11="",Registro_Compras!$O$11=""),"",IF(Registro_Compras!$F$11="NOTA DE CREDITO","IGV - Cuenta Propia (Credito Fiscal)","Cuentas por Pagar Comerciales - Terceros (Emitidas)")) | E70: ="" | F70: =IF($C70="","",IF(Registro_Compras!$F$11="NOTA DE CREDITO",ROUND(ABS(Registro_Compras!$K$11*Registro_Compras!$N$11),2),IF(Registro_Compras!$F$11="RHE",(ROUND(Registro_Compras!$L$11*Registro_Compras!$N$11,2)-ROUND(Registro_Compras!$V$11*Registro_Compras!$N$11,2)),Registro_Compras!$O$11))) | G70: =IF($C70="","",IF(Registro_Compras!$F$11="NOTA DE CREDITO","Por la nota de credito "&Registro_Compras!$C$11&" de "&Registro_Compras!$E$11&" [PATRON POR CONFIRMAR CON CONTADOR]",IF(Registro_Compras!$F$11="RHE","Por el registro del recibo por honorarios "&Registro_Compras!$C$11&" de "&Registro_Compras!$E$11&" [PATRON POR CONFIRMAR CON CONTADOR]","Por el registro de la factura "&Registro_Compras!$C$11&" de "&Registro_Compras!$E$11))) | H70: =IF($C70="","",Registro_Compras!$C$11)
A71: =IF($C71="","",Registro_Compras!$B$11) | B71: =IF($C71="","","C"&TEXT(INT((ROW()-5)/9)+1,"000")&"-2") | C71: =IF(OR(Registro_Compras!$C$11="",Registro_Compras!$O$11=""),"",IF(Registro_Compras!$AB$11="ADMINISTRATIVO","94","95")) | D71: =IF(OR(Registro_Compras!$C$11="",Registro_Compras!$O$11=""),"",IF(Registro_Compras!$AB$11="ADMINISTRATIVO","Gastos Administrativos","Gastos de Venta y Operacion")) | E71: =IF($C71="","",IF(Registro_Compras!$F$11="NOTA DE CREDITO","",IF(Registro_Compras!$F$11="RHE",ROUND(Registro_Compras!$L$11*Registro_Compras!$N$11,2),ROUND(Registro_Compras!$J$11*Registro_Compras!$N$11,2)))) | F71: =IF($C71="","",IF(Registro_Compras!$F$11="NOTA DE CREDITO",ROUND(ABS(Registro_Compras!$J$11*Registro_Compras!$N$11),2),"")) | G71: =IF($C71="","","Por el destino del gasto") | H71: =IF($C71="","",Registro_Compras!$C$11)
A72: =IF($C72="","",Registro_Compras!$B$11) | B72: =IF($C72="","","C"&TEXT(INT((ROW()-5)/9)+1,"000")&"-2") | C72: =IF(OR(Registro_Compras!$C$11="",Registro_Compras!$O$11=""),"","79/791") | D72: =IF(OR(Registro_Compras!$C$11="",Registro_Compras!$O$11=""),"","Cargas Imputables a Cuentas de Costos y Gastos") | E72: =IF($C72="","",IF(Registro_Compras!$F$11="NOTA DE CREDITO",ROUND(ABS(Registro_Compras!$J$11*Registro_Compras!$N$11),2),"")) | F72: =IF($C72="","",IF(Registro_Compras!$F$11="NOTA DE CREDITO","",IF(Registro_Compras!$F$11="RHE",ROUND(Registro_Compras!$L$11*Registro_Compras!$N$11,2),ROUND(Registro_Compras!$J$11*Registro_Compras!$N$11,2)))) | G72: =IF($C72="","","Por el destino del gasto") | H72: =IF($C72="","",Registro_Compras!$C$11)
A73: =IF($C73="","",Registro_Compras!$X$11) | B73: =IF($C73="","","C"&TEXT(INT((ROW()-5)/9)+1,"000")&"-3") | C73: =IF(OR(Registro_Compras!$C$11="",Registro_Compras!$O$11="",Registro_Compras!$R$11<>"SI",Registro_Compras!$X$11=""),"","4212") | D73: =IF(OR(Registro_Compras!$C$11="",Registro_Compras!$O$11=""),"","Cuentas por Pagar Comerciales - Terceros") | E73: =IF($C73="","",Registro_Compras!$S$11) | F73: ="" | G73: =IF($C73="","","Por el deposito de la detraccion en el Banco de la Nacion") | H73: =IF($C73="","",Registro_Compras!$C$11)
A74: =IF($C74="","",Registro_Compras!$X$11) | B74: =IF($C74="","","C"&TEXT(INT((ROW()-5)/9)+1,"000")&"-3") | C74: =IF(OR(Registro_Compras!$C$11="",Registro_Compras!$O$11="",Registro_Compras!$R$11<>"SI",Registro_Compras!$X$11=""),"","10413") | D74: =IF(OR(Registro_Compras!$C$11="",Registro_Compras!$O$11=""),"","Efectivo y Equivalentes - Cta. Cte. Operativa") | E74: ="" | F74: =IF($C74="","",Registro_Compras!$S$11) | G74: =IF($C74="","","Por el deposito de la detraccion en el Banco de la Nacion") | H74: =IF($C74="","",Registro_Compras!$C$11)
A75: =IF($C75="","",Registro_Compras!$Y$11) | B75: =IF($C75="","","C"&TEXT(INT((ROW()-5)/9)+1,"000")&"-4") | C75: =IF(OR(Registro_Compras!$C$11="",Registro_Compras!$O$11="",Registro_Compras!$Y$11="",Registro_Compras!$F$11="NOTA DE CREDITO"),"","4212") | D75: =IF(OR(Registro_Compras!$C$11="",Registro_Compras!$O$11=""),"","Cuentas por Pagar Comerciales - Terceros") | E75: =IF($C75="","",IF(Registro_Compras!$F$11="RHE",(ROUND(Registro_Compras!$L$11*Registro_Compras!$N$11,2)-ROUND(Registro_Compras!$V$11*Registro_Compras!$N$11,2)),ROUND(Registro_Compras!$O$11-Registro_Compras!$S$11,2))) | F75: ="" | G75: =IF($C75="","","Por la cancelacion del saldo al proveedor") | H75: =IF($C75="","",Registro_Compras!$C$11)
A76: =IF($C76="","",Registro_Compras!$Y$11) | B76: =IF($C76="","","C"&TEXT(INT((ROW()-5)/9)+1,"000")&"-4") | C76: =IF(OR(Registro_Compras!$C$11="",Registro_Compras!$O$11="",Registro_Compras!$Y$11="",Registro_Compras!$F$11="NOTA DE CREDITO"),"","10413") | D76: =IF(OR(Registro_Compras!$C$11="",Registro_Compras!$O$11=""),"","Efectivo y Equivalentes - Cta. Cte. Operativa") | E76: ="" | F76: =IF($C76="","",IF(Registro_Compras!$F$11="RHE",(ROUND(Registro_Compras!$L$11*Registro_Compras!$N$11,2)-ROUND(Registro_Compras!$V$11*Registro_Compras!$N$11,2)),ROUND(Registro_Compras!$O$11-Registro_Compras!$S$11,2))) | G76: =IF($C76="","","Por la cancelacion del saldo al proveedor") | H76: =IF($C76="","",Registro_Compras!$C$11)
A77: =IF($C77="","",Registro_Compras!$B$12) | B77: =IF($C77="","","C"&TEXT(INT((ROW()-5)/9)+1,"000")&"-1") | C77: =IF(OR(Registro_Compras!$C$12="",Registro_Compras!$O$12=""),"",IF(Registro_Compras!$F$12="NOTA DE CREDITO","4212",IF(Registro_Compras!$M$12="","63",Registro_Compras!$M$12))) | D77: =IF(OR(Registro_Compras!$C$12="",Registro_Compras!$O$12=""),"",IF(Registro_Compras!$F$12="NOTA DE CREDITO","Cuentas por Pagar Comerciales - Terceros (Emitidas)",IF(Registro_Compras!$F$12="RHE","Honorarios Profesionales - Servicios de Terceros","Gastos de Servicios Prestados por Terceros"))) | E77: =IF($C77="","",IF(Registro_Compras!$F$12="NOTA DE CREDITO",ABS(Registro_Compras!$O$12),IF(Registro_Compras!$F$12="RHE",ROUND(Registro_Compras!$L$12*Registro_Compras!$N$12,2),ROUND(Registro_Compras!$J$12*Registro_Compras!$N$12,2)))) | F77: ="" | G77: =IF($C77="","",IF(Registro_Compras!$F$12="NOTA DE CREDITO","Por la nota de credito "&Registro_Compras!$C$12&" de "&Registro_Compras!$E$12&" [PATRON POR CONFIRMAR CON CONTADOR]",IF(Registro_Compras!$F$12="RHE","Por el registro del recibo por honorarios "&Registro_Compras!$C$12&" de "&Registro_Compras!$E$12&" [PATRON POR CONFIRMAR CON CONTADOR]","Por el registro de la factura "&Registro_Compras!$C$12&" de "&Registro_Compras!$E$12))) | H77: =IF($C77="","",Registro_Compras!$C$12)
A78: =IF($C78="","",Registro_Compras!$B$12) | B78: =IF($C78="","","C"&TEXT(INT((ROW()-5)/9)+1,"000")&"-1") | C78: =IF(OR(Registro_Compras!$C$12="",Registro_Compras!$O$12=""),"",IF(Registro_Compras!$F$12="RHE",IF(Registro_Compras!$V$12=0,"","40172"),IF(Registro_Compras!$F$12="NOTA DE CREDITO",IF(Registro_Compras!$M$12="","63",Registro_Compras!$M$12),IF(Registro_Compras!$K$12=0,"","40111")))) | D78: =IF(OR(Registro_Compras!$C$12="",Registro_Compras!$O$12=""),"",IF(Registro_Compras!$F$12="RHE","Retencion Renta 4ta Categoria por Pagar",IF(Registro_Compras!$F$12="NOTA DE CREDITO","Gastos de Servicios Prestados por Terceros","IGV - Cuenta Propia (Credito Fiscal)"))) | E78: =IF($C78="","",IF(Registro_Compras!$F$12="FACTURA",ROUND(Registro_Compras!$K$12*Registro_Compras!$N$12,2),"")) | F78: =IF($C78="","",IF(Registro_Compras!$F$12="RHE",ROUND(Registro_Compras!$V$12*Registro_Compras!$N$12,2),IF(Registro_Compras!$F$12="NOTA DE CREDITO",ROUND(ABS(Registro_Compras!$J$12*Registro_Compras!$N$12),2),""))) | G78: =IF($C78="","",IF(Registro_Compras!$F$12="NOTA DE CREDITO","Por la nota de credito "&Registro_Compras!$C$12&" de "&Registro_Compras!$E$12&" [PATRON POR CONFIRMAR CON CONTADOR]",IF(Registro_Compras!$F$12="RHE","Por el registro del recibo por honorarios "&Registro_Compras!$C$12&" de "&Registro_Compras!$E$12&" [PATRON POR CONFIRMAR CON CONTADOR]","Por el registro de la factura "&Registro_Compras!$C$12&" de "&Registro_Compras!$E$12))) | H78: =IF($C78="","",Registro_Compras!$C$12)
A79: =IF($C79="","",Registro_Compras!$B$12) | B79: =IF($C79="","","C"&TEXT(INT((ROW()-5)/9)+1,"000")&"-1") | C79: =IF(OR(Registro_Compras!$C$12="",Registro_Compras!$O$12=""),"",IF(Registro_Compras!$F$12="NOTA DE CREDITO",IF(Registro_Compras!$K$12=0,"","40111"),"4212")) | D79: =IF(OR(Registro_Compras!$C$12="",Registro_Compras!$O$12=""),"",IF(Registro_Compras!$F$12="NOTA DE CREDITO","IGV - Cuenta Propia (Credito Fiscal)","Cuentas por Pagar Comerciales - Terceros (Emitidas)")) | E79: ="" | F79: =IF($C79="","",IF(Registro_Compras!$F$12="NOTA DE CREDITO",ROUND(ABS(Registro_Compras!$K$12*Registro_Compras!$N$12),2),IF(Registro_Compras!$F$12="RHE",(ROUND(Registro_Compras!$L$12*Registro_Compras!$N$12,2)-ROUND(Registro_Compras!$V$12*Registro_Compras!$N$12,2)),Registro_Compras!$O$12))) | G79: =IF($C79="","",IF(Registro_Compras!$F$12="NOTA DE CREDITO","Por la nota de credito "&Registro_Compras!$C$12&" de "&Registro_Compras!$E$12&" [PATRON POR CONFIRMAR CON CONTADOR]",IF(Registro_Compras!$F$12="RHE","Por el registro del recibo por honorarios "&Registro_Compras!$C$12&" de "&Registro_Compras!$E$12&" [PATRON POR CONFIRMAR CON CONTADOR]","Por el registro de la factura "&Registro_Compras!$C$12&" de "&Registro_Compras!$E$12))) | H79: =IF($C79="","",Registro_Compras!$C$12)
A80: =IF($C80="","",Registro_Compras!$B$12) | B80: =IF($C80="","","C"&TEXT(INT((ROW()-5)/9)+1,"000")&"-2") | C80: =IF(OR(Registro_Compras!$C$12="",Registro_Compras!$O$12=""),"",IF(Registro_Compras!$AB$12="ADMINISTRATIVO","94","95")) | D80: =IF(OR(Registro_Compras!$C$12="",Registro_Compras!$O$12=""),"",IF(Registro_Compras!$AB$12="ADMINISTRATIVO","Gastos Administrativos","Gastos de Venta y Operacion")) | E80: =IF($C80="","",IF(Registro_Compras!$F$12="NOTA DE CREDITO","",IF(Registro_Compras!$F$12="RHE",ROUND(Registro_Compras!$L$12*Registro_Compras!$N$12,2),ROUND(Registro_Compras!$J$12*Registro_Compras!$N$12,2)))) | F80: =IF($C80="","",IF(Registro_Compras!$F$12="NOTA DE CREDITO",ROUND(ABS(Registro_Compras!$J$12*Registro_Compras!$N$12),2),"")) | G80: =IF($C80="","","Por el destino del gasto") | H80: =IF($C80="","",Registro_Compras!$C$12)
A81: =IF($C81="","",Registro_Compras!$B$12) | B81: =IF($C81="","","C"&TEXT(INT((ROW()-5)/9)+1,"000")&"-2") | C81: =IF(OR(Registro_Compras!$C$12="",Registro_Compras!$O$12=""),"","79/791") | D81: =IF(OR(Registro_Compras!$C$12="",Registro_Compras!$O$12=""),"","Cargas Imputables a Cuentas de Costos y Gastos") | E81: =IF($C81="","",IF(Registro_Compras!$F$12="NOTA DE CREDITO",ROUND(ABS(Registro_Compras!$J$12*Registro_Compras!$N$12),2),"")) | F81: =IF($C81="","",IF(Registro_Compras!$F$12="NOTA DE CREDITO","",IF(Registro_Compras!$F$12="RHE",ROUND(Registro_Compras!$L$12*Registro_Compras!$N$12,2),ROUND(Registro_Compras!$J$12*Registro_Compras!$N$12,2)))) | G81: =IF($C81="","","Por el destino del gasto") | H81: =IF($C81="","",Registro_Compras!$C$12)
A82: =IF($C82="","",Registro_Compras!$X$12) | B82: =IF($C82="","","C"&TEXT(INT((ROW()-5)/9)+1,"000")&"-3") | C82: =IF(OR(Registro_Compras!$C$12="",Registro_Compras!$O$12="",Registro_Compras!$R$12<>"SI",Registro_Compras!$X$12=""),"","4212") | D82: =IF(OR(Registro_Compras!$C$12="",Registro_Compras!$O$12=""),"","Cuentas por Pagar Comerciales - Terceros") | E82: =IF($C82="","",Registro_Compras!$S$12) | F82: ="" | G82: =IF($C82="","","Por el deposito de la detraccion en el Banco de la Nacion") | H82: =IF($C82="","",Registro_Compras!$C$12)
A83: =IF($C83="","",Registro_Compras!$X$12) | B83: =IF($C83="","","C"&TEXT(INT((ROW()-5)/9)+1,"000")&"-3") | C83: =IF(OR(Registro_Compras!$C$12="",Registro_Compras!$O$12="",Registro_Compras!$R$12<>"SI",Registro_Compras!$X$12=""),"","10413") | D83: =IF(OR(Registro_Compras!$C$12="",Registro_Compras!$O$12=""),"","Efectivo y Equivalentes - Cta. Cte. Operativa") | E83: ="" | F83: =IF($C83="","",Registro_Compras!$S$12) | G83: =IF($C83="","","Por el deposito de la detraccion en el Banco de la Nacion") | H83: =IF($C83="","",Registro_Compras!$C$12)
A84: =IF($C84="","",Registro_Compras!$Y$12) | B84: =IF($C84="","","C"&TEXT(INT((ROW()-5)/9)+1,"000")&"-4") | C84: =IF(OR(Registro_Compras!$C$12="",Registro_Compras!$O$12="",Registro_Compras!$Y$12="",Registro_Compras!$F$12="NOTA DE CREDITO"),"","4212") | D84: =IF(OR(Registro_Compras!$C$12="",Registro_Compras!$O$12=""),"","Cuentas por Pagar Comerciales - Terceros") | E84: =IF($C84="","",IF(Registro_Compras!$F$12="RHE",(ROUND(Registro_Compras!$L$12*Registro_Compras!$N$12,2)-ROUND(Registro_Compras!$V$12*Registro_Compras!$N$12,2)),ROUND(Registro_Compras!$O$12-Registro_Compras!$S$12,2))) | F84: ="" | G84: =IF($C84="","","Por la cancelacion del saldo al proveedor") | H84: =IF($C84="","",Registro_Compras!$C$12)
A85: =IF($C85="","",Registro_Compras!$Y$12) | B85: =IF($C85="","","C"&TEXT(INT((ROW()-5)/9)+1,"000")&"-4") | C85: =IF(OR(Registro_Compras!$C$12="",Registro_Compras!$O$12="",Registro_Compras!$Y$12="",Registro_Compras!$F$12="NOTA DE CREDITO"),"","10413") | D85: =IF(OR(Registro_Compras!$C$12="",Registro_Compras!$O$12=""),"","Efectivo y Equivalentes - Cta. Cte. Operativa") | E85: ="" | F85: =IF($C85="","",IF(Registro_Compras!$F$12="RHE",(ROUND(Registro_Compras!$L$12*Registro_Compras!$N$12,2)-ROUND(Registro_Compras!$V$12*Registro_Compras!$N$12,2)),ROUND(Registro_Compras!$O$12-Registro_Compras!$S$12,2))) | G85: =IF($C85="","","Por la cancelacion del saldo al proveedor") | H85: =IF($C85="","",Registro_Compras!$C$12)
A86: =IF($C86="","",Registro_Compras!$B$13) | B86: =IF($C86="","","C"&TEXT(INT((ROW()-5)/9)+1,"000")&"-1") | C86: =IF(OR(Registro_Compras!$C$13="",Registro_Compras!$O$13=""),"",IF(Registro_Compras!$F$13="NOTA DE CREDITO","4212",IF(Registro_Compras!$M$13="","63",Registro_Compras!$M$13))) | D86: =IF(OR(Registro_Compras!$C$13="",Registro_Compras!$O$13=""),"",IF(Registro_Compras!$F$13="NOTA DE CREDITO","Cuentas por Pagar Comerciales - Terceros (Emitidas)",IF(Registro_Compras!$F$13="RHE","Honorarios Profesionales - Servicios de Terceros","Gastos de Servicios Prestados por Terceros"))) | E86: =IF($C86="","",IF(Registro_Compras!$F$13="NOTA DE CREDITO",ABS(Registro_Compras!$O$13),IF(Registro_Compras!$F$13="RHE",ROUND(Registro_Compras!$L$13*Registro_Compras!$N$13,2),ROUND(Registro_Compras!$J$13*Registro_Compras!$N$13,2)))) | F86: ="" | G86: =IF($C86="","",IF(Registro_Compras!$F$13="NOTA DE CREDITO","Por la nota de credito "&Registro_Compras!$C$13&" de "&Registro_Compras!$E$13&" [PATRON POR CONFIRMAR CON CONTADOR]",IF(Registro_Compras!$F$13="RHE","Por el registro del recibo por honorarios "&Registro_Compras!$C$13&" de "&Registro_Compras!$E$13&" [PATRON POR CONFIRMAR CON CONTADOR]","Por el registro de la factura "&Registro_Compras!$C$13&" de "&Registro_Compras!$E$13))) | H86: =IF($C86="","",Registro_Compras!$C$13)
A87: =IF($C87="","",Registro_Compras!$B$13) | B87: =IF($C87="","","C"&TEXT(INT((ROW()-5)/9)+1,"000")&"-1") | C87: =IF(OR(Registro_Compras!$C$13="",Registro_Compras!$O$13=""),"",IF(Registro_Compras!$F$13="RHE",IF(Registro_Compras!$V$13=0,"","40172"),IF(Registro_Compras!$F$13="NOTA DE CREDITO",IF(Registro_Compras!$M$13="","63",Registro_Compras!$M$13),IF(Registro_Compras!$K$13=0,"","40111")))) | D87: =IF(OR(Registro_Compras!$C$13="",Registro_Compras!$O$13=""),"",IF(Registro_Compras!$F$13="RHE","Retencion Renta 4ta Categoria por Pagar",IF(Registro_Compras!$F$13="NOTA DE CREDITO","Gastos de Servicios Prestados por Terceros","IGV - Cuenta Propia (Credito Fiscal)"))) | E87: =IF($C87="","",IF(Registro_Compras!$F$13="FACTURA",ROUND(Registro_Compras!$K$13*Registro_Compras!$N$13,2),"")) | F87: =IF($C87="","",IF(Registro_Compras!$F$13="RHE",ROUND(Registro_Compras!$V$13*Registro_Compras!$N$13,2),IF(Registro_Compras!$F$13="NOTA DE CREDITO",ROUND(ABS(Registro_Compras!$J$13*Registro_Compras!$N$13),2),""))) | G87: =IF($C87="","",IF(Registro_Compras!$F$13="NOTA DE CREDITO","Por la nota de credito "&Registro_Compras!$C$13&" de "&Registro_Compras!$E$13&" [PATRON POR CONFIRMAR CON CONTADOR]",IF(Registro_Compras!$F$13="RHE","Por el registro del recibo por honorarios "&Registro_Compras!$C$13&" de "&Registro_Compras!$E$13&" [PATRON POR CONFIRMAR CON CONTADOR]","Por el registro de la factura "&Registro_Compras!$C$13&" de "&Registro_Compras!$E$13))) | H87: =IF($C87="","",Registro_Compras!$C$13)
A88: =IF($C88="","",Registro_Compras!$B$13) | B88: =IF($C88="","","C"&TEXT(INT((ROW()-5)/9)+1,"000")&"-1") | C88: =IF(OR(Registro_Compras!$C$13="",Registro_Compras!$O$13=""),"",IF(Registro_Compras!$F$13="NOTA DE CREDITO",IF(Registro_Compras!$K$13=0,"","40111"),"4212")) | D88: =IF(OR(Registro_Compras!$C$13="",Registro_Compras!$O$13=""),"",IF(Registro_Compras!$F$13="NOTA DE CREDITO","IGV - Cuenta Propia (Credito Fiscal)","Cuentas por Pagar Comerciales - Terceros (Emitidas)")) | E88: ="" | F88: =IF($C88="","",IF(Registro_Compras!$F$13="NOTA DE CREDITO",ROUND(ABS(Registro_Compras!$K$13*Registro_Compras!$N$13),2),IF(Registro_Compras!$F$13="RHE",(ROUND(Registro_Compras!$L$13*Registro_Compras!$N$13,2)-ROUND(Registro_Compras!$V$13*Registro_Compras!$N$13,2)),Registro_Compras!$O$13))) | G88: =IF($C88="","",IF(Registro_Compras!$F$13="NOTA DE CREDITO","Por la nota de credito "&Registro_Compras!$C$13&" de "&Registro_Compras!$E$13&" [PATRON POR CONFIRMAR CON CONTADOR]",IF(Registro_Compras!$F$13="RHE","Por el registro del recibo por honorarios "&Registro_Compras!$C$13&" de "&Registro_Compras!$E$13&" [PATRON POR CONFIRMAR CON CONTADOR]","Por el registro de la factura "&Registro_Compras!$C$13&" de "&Registro_Compras!$E$13))) | H88: =IF($C88="","",Registro_Compras!$C$13)
A89: =IF($C89="","",Registro_Compras!$B$13) | B89: =IF($C89="","","C"&TEXT(INT((ROW()-5)/9)+1,"000")&"-2") | C89: =IF(OR(Registro_Compras!$C$13="",Registro_Compras!$O$13=""),"",IF(Registro_Compras!$AB$13="ADMINISTRATIVO","94","95")) | D89: =IF(OR(Registro_Compras!$C$13="",Registro_Compras!$O$13=""),"",IF(Registro_Compras!$AB$13="ADMINISTRATIVO","Gastos Administrativos","Gastos de Venta y Operacion")) | E89: =IF($C89="","",IF(Registro_Compras!$F$13="NOTA DE CREDITO","",IF(Registro_Compras!$F$13="RHE",ROUND(Registro_Compras!$L$13*Registro_Compras!$N$13,2),ROUND(Registro_Compras!$J$13*Registro_Compras!$N$13,2)))) | F89: =IF($C89="","",IF(Registro_Compras!$F$13="NOTA DE CREDITO",ROUND(ABS(Registro_Compras!$J$13*Registro_Compras!$N$13),2),"")) | G89: =IF($C89="","","Por el destino del gasto") | H89: =IF($C89="","",Registro_Compras!$C$13)
A90: =IF($C90="","",Registro_Compras!$B$13) | B90: =IF($C90="","","C"&TEXT(INT((ROW()-5)/9)+1,"000")&"-2") | C90: =IF(OR(Registro_Compras!$C$13="",Registro_Compras!$O$13=""),"","79/791") | D90: =IF(OR(Registro_Compras!$C$13="",Registro_Compras!$O$13=""),"","Cargas Imputables a Cuentas de Costos y Gastos") | E90: =IF($C90="","",IF(Registro_Compras!$F$13="NOTA DE CREDITO",ROUND(ABS(Registro_Compras!$J$13*Registro_Compras!$N$13),2),"")) | F90: =IF($C90="","",IF(Registro_Compras!$F$13="NOTA DE CREDITO","",IF(Registro_Compras!$F$13="RHE",ROUND(Registro_Compras!$L$13*Registro_Compras!$N$13,2),ROUND(Registro_Compras!$J$13*Registro_Compras!$N$13,2)))) | G90: =IF($C90="","","Por el destino del gasto") | H90: =IF($C90="","",Registro_Compras!$C$13)
A91: =IF($C91="","",Registro_Compras!$X$13) | B91: =IF($C91="","","C"&TEXT(INT((ROW()-5)/9)+1,"000")&"-3") | C91: =IF(OR(Registro_Compras!$C$13="",Registro_Compras!$O$13="",Registro_Compras!$R$13<>"SI",Registro_Compras!$X$13=""),"","4212") | D91: =IF(OR(Registro_Compras!$C$13="",Registro_Compras!$O$13=""),"","Cuentas por Pagar Comerciales - Terceros") | E91: =IF($C91="","",Registro_Compras!$S$13) | F91: ="" | G91: =IF($C91="","","Por el deposito de la detraccion en el Banco de la Nacion") | H91: =IF($C91="","",Registro_Compras!$C$13)
A92: =IF($C92="","",Registro_Compras!$X$13) | B92: =IF($C92="","","C"&TEXT(INT((ROW()-5)/9)+1,"000")&"-3") | C92: =IF(OR(Registro_Compras!$C$13="",Registro_Compras!$O$13="",Registro_Compras!$R$13<>"SI",Registro_Compras!$X$13=""),"","10413") | D92: =IF(OR(Registro_Compras!$C$13="",Registro_Compras!$O$13=""),"","Efectivo y Equivalentes - Cta. Cte. Operativa") | E92: ="" | F92: =IF($C92="","",Registro_Compras!$S$13) | G92: =IF($C92="","","Por el deposito de la detraccion en el Banco de la Nacion") | H92: =IF($C92="","",Registro_Compras!$C$13)
